Workbook
Name MinYears: Inputs!$B$10
Name Settle: Inputs!$B$6
Name Sv_beta0: Inputs!$B$13
Name Sv_beta1: Inputs!$B$14
Name Sv_beta2: Inputs!$B$15
Name Sv_beta3: Inputs!$B$16
Name Sv_tau1: Inputs!$B$17
Name Sv_tau2: Inputs!$B$18
Name Weighted_SSE: Inputs!$B$21

Sheet Cover
B2: Miniproject 2 - Creating a ZCB Term Structure
B3: FRE 6103 Valuation for Financial Engineering (NYU Tandon), Prof. David Shimko
B4: Raj Pawar | Data: WSJ / Tullett Prebon Treasury notes & bonds, 2026-09-04
B6: What this workbook does
B7: Fits a continuously compounded zero-coupon (ZCB) term structure to all US Treasury note and bond quotes using the Svensson (1994) functional form, then reports the discount rate r(t) and discount factor d(t) = exp(-r(t) t) for every Treasury payment date (coupons and principal).
B9: Sheet map
B10: Inputs: dates, Svensson parameters, objective (weighted SSE) and fit statistics. Solver runs here. Data: raw WSJ quotes exactly as downloaded. Bonds: one row per bond - 32nds conversion, coupon dates (COUPPCD/COUPNCD), accrued interest, dirty price, street yield (Excel YIELD), duration, model price off the curve, price and yield errors. CashFlows: every remaining coupon/principal date of every bond, its zero rate and present value. ZeroCurve: the deliverable - r(t), d(t) and instantaneous forward f(t) at every payment date, with chart. Robustness: convention check, Nelson-Siegel benchmark and beta0 profile (values computed by the Python implementation). Methodology: the one-page write-up.
B12: Live formulas
B13: Everything on Bonds, CashFlows and ZeroCurve is a formula. Change a parameter on Inputs and all model prices, errors and the curve update. Values on Data and Robustness are inputs/records.
B15: Re-running the fit with Solver
B16: Data > Solver. Set Objective: Inputs!$B$21 (weighted SSE) to Min. By Changing: Inputs!$B$13:$B$18. Subject to: $B$13 >= 0, $B$17 >= 0.05, $B$18 >= 0.05. Method: GRG Nonlinear; untick 'Make Unconstrained Variables Non-Negative' (beta1..beta3 may be negative). The pre-loaded parameters are already the optimum found by the Python implementation (multi-start least squares), so Solver should not move them materially.
B18: Companion Python implementation
B19: github.com/pawarraj8888/zcb-term-structure - identical conventions; the Excel SSE and every model price reproduce the Python numbers.

Sheet Inputs
B2: Inputs and fit
A4: Quote date (WSJ) | B4: 46269
A5: Market holiday (Labor Day) | B5: 46272
A6: Settlement date (T+1 business) | B6: =WORKDAY(B4,1,B5) -> 46273
A7: Face value | B7: 100
A8: Coupons per year | B8: 2
A9: Days per year (continuous time) | B9: 365
A10: Min years to maturity in fit | B10: 0.25
A12: Svensson parameters (continuous zero rate, decimals)
A13: beta0 | B13: 1.0489727e-13 | C13: level: r(t) as t -> infinity
A14: beta1 | B14: 0.036276273 | C14: slope: r(0) = beta0 + beta1
A15: beta2 | B15: 0.044721606 | C15: first hump, decay tau1
A16: beta3 | B16: 0.16228661 | C16: second hump, decay tau2
A17: tau1 | B17: 1.7660987 | C17: decay (years) of slope/first hump
A18: tau2 | B18: 15.991117 | C18: decay (years) of second hump
A20: Fit objective and statistics (bonds with In fit = 1)
A21: Weighted SSE = SUM( InFit x ((Pmodel - Pmkt) / ModDuration)^2 ) | B21: =SUM(Bonds!AA4:AA356) -> 0.26126611
A22: Bonds in fit | B22: =SUM(Bonds!S4:S356) -> 339
A23: Bonds total | B23: =COUNT(Bonds!B4:B356) -> 353
A24: Price RMSE (per 100 face) | B24: =SQRT(SUMPRODUCT(Bonds!S4:S356,Bonds!V4:V356,Bonds!V4:V356)/B22) -> 0.1852953
A25: Yield RMSE (bp) | B25: =SQRT(SUMPRODUCT(Bonds!S4:S356,Bonds!X4:X356,Bonds!X4:X356)/B22) -> 2.8823362
A26: Yield MAE (bp) | B26: =SUMPRODUCT(Bonds!S4:S356,ABS(Bonds!X4:X356))/B22 -> 2.0774758
A27: Max |yield error| (bp) | B27: =MAX(INDEX(Bonds!S4:S356*ABS(Bonds!X4:X356),0)) -> 14.817889
A28: r(0) = beta0 + beta1 (%) | B28: =(Sv_beta0+Sv_beta1)*100 -> 3.6276273
A29: r(30y) (%) | B29: =(Sv_beta0+Sv_beta1*(1-EXP(-30/Sv_tau1))/(30/Sv_tau1)+Sv_beta2*((1-EXP(-30/Sv_tau1))/(30/Sv_tau1)-EXP(-30/Sv_tau1))+Sv_beta3*((1-EXP(-30/Sv_tau2))/(30/Sv_tau2)-EXP(-30/Sv_tau2)))*100 -> 5.3159463
A31: Solver set-up
A32: Objective: $B$21 -> Min. Changing cells: $B$13:$B$18. Constraints: $B$13 >= 0, $B$17 >= 0.05, $B$18 >= 0.05. GRG Nonlinear; untick 'Make Unconstrained Variables Non-Negative'.
A35: Yellow cells are inputs; everything else is calculated.

Sheet Data
A1: U.S. Treasury Quotes - Treasury Notes & Bonds (WSJ, source Tullett Prebon). Prices in 32nds; third decimal = eighths of a 32nd.
A2: Maturity | B2: Coupon | C2: Bid | D2: Asked | E2: Chg | F2: Asked yield
A3: 46280 | B3: 4.625 | C3: 100 | D3: 100.01 | E3: -0.002 | F3: 2.937
A4: 46295 | B4: 0.875 | C4: 99.256 | D4: 99.266 | E4: 0.01 | F4: 3.625
A5: 46295 | B5: 1.625 | C5: 99.276 | D5: 99.286 | E5: 0.004 | F5: 3.318
A6: 46295 | B6: 3.5 | C6: 99.306 | D6: 99.316 | E6: 0.002 | F6: 3.603
A7: 46310 | B7: 4.625 | C7: 100.022 | D7: 100.032 | E7: -0.002 | F7: 3.576
A8: 46326 | B8: 1.125 | C8: 99.186 | D8: 99.196 | E8: 0.01 | F8: 3.808
A9: 46326 | B9: 1.625 | C9: 99.212 | D9: 99.222 | E9: 0.008 | F9: 3.755
A10: 46326 | B10: 4.125 | C10: 100 | D10: 100.01 | E10: -0.006 | F10: 3.877
A11: 46341 | B11: 2 | C11: 99.204 | D11: 99.214 | E11: 0.004 | F11: 3.787
A12: 46341 | B12: 4.625 | C12: 100.04 | D12: 100.05 | E12: -0.002 | F12: 3.741
A13: 46341 | B13: 6.5 | C13: 100.13 | D13: 100.14 | E13: -0.014 | F13: 4.058
A14: 46356 | B14: 1.25 | C14: 99.126 | D14: 99.136 | E14: 0.006 | F14: 3.793
... A20: 46387 | B20: 4.25 | C20: 100.024 | D20: 100.034 | E20: -0.002 | F20: 3.876
A21: 46402 | B21: 4 | C21: 100.01 | D21: 100.02 | E21: unch. | F21: 3.807
A22: 46418 | B22: 1.5 | C22: 99.004 | D22: 99.014 | E22: 0.688 | F22: 3.959
A23: 46418 | B23: 4.125 | C23: 100.01 | D23: 100.02 | E23: 0.004 | F23: 3.955
A24: 46433 | B24: 2.25 | C24: 99.082 | D24: 99.092 | E24: 0.006 | F24: 3.912
A25: 46433 | B25: 4.125 | C25: 100.012 | D25: 100.022 | E25: -0.008 | F25: 3.955
A26: 46433 | B26: 6.625 | C26: 101.03 | D26: 101.04 | E26: -0.02 | F26: 3.981
A27: 46446 | B27: 1.125 | C27: 98.202 | D27: 98.212 | E27: 0.008 | F27: 3.974
A28: 46446 | B28: 1.875 | C28: 99.002 | D28: 99.012 | E28: 0.686 | F28: 3.923
A29: 46446 | B29: 4.125 | C29: 100.016 | D29: 100.026 | E29: unch. | F29: 3.94
A30: 46461 | B30: 4.25 | C30: 100.042 | D30: 100.052 | E30: -0.002 | F30: 3.926
A31: 46477 | B31: 0.625 | C31: 98.042 | D31: 98.052 | E31: 0.01 | F31: 3.971
A32: 46477 | B32: 2.5 | C32: 99.052 | D32: 99.062 | E32: 0.002 | F32: 3.964
A33: 46477 | B33: 3.875 | C33: 99.294 | D33: 99.304 | E33: 0.002 | F33: 3.957
A34: 46492 | B34: 4.5 | C34: 100.082 | D34: 100.092 | E34: unch. | F34: 4.002
A35: 46507 | B35: 0.5 | C35: 97.24 | D35: 97.25 | E35: 0.016 | F35: 4.024
A36: 46507 | B36: 2.75 | C36: 99.044 | D36: 99.054 | E36: unch. | F36: 4.061
A37: 46507 | B37: 3.75 | C37: 99.254 | D37: 99.264 | E37: 0.008 | F37: 4.017
A38: 46522 | B38: 2.375 | C38: 98.262 | D38: 98.272 | E38: 0.002 | F38: 4.089
A39: 46522 | B39: 4.5 | C39: 100.074 | D39: 100.084 | E39: -0.006 | F39: 4.095
A40: 46538 | B40: 0.5 | C40: 97.14 | D40: 97.15 | E40: 0.01 | F40: 4.069
A41: 46538 | B41: 2.625 | C41: 98.302 | D41: 98.312 | E41: 0.008 | F41: 4.064
A42: 46538 | B42: 3.875 | C42: 99.262 | D42: 99.272 | E42: -0.002 | F42: 4.078
A43: 46553 | B43: 4.625 | C43: 100.114 | D43: 100.124 | E43: -0.002 | F43: 4.095
A44: 46568 | B44: 0.5 | C44: 97.034 | D44: 97.044 | E44: 0.008 | F44: 4.126
A45: 46568 | B45: 3.25 | C45: 99.092 | D45: 99.102 | E45: unch. | F45: 4.107
A46: 46568 | B46: 3.75 | C46: 99.212 | D46: 99.222 | E46: -0.008 | F46: 4.131
A47: 46583 | B47: 4.375 | C47: 100.05 | D47: 100.06 | E47: -0.01 | F47: 4.143
A48: 46599 | B48: 0.375 | C48: 96.214 | D48: 96.224 | E48: 0.004 | F48: 4.17
A49: 46599 | B49: 2.75 | C49: 98.232 | D49: 98.242 | E49: -0.002 | F49: 4.177
A50: 46599 | B50: 3.875 | C50: 99.226 | D50: 99.236 | E50: -0.004 | F50: 4.168
A51: 46614 | B51: 2.25 | C51: 98.072 | D51: 98.082 | E51: 0.002 | F51: 4.168
A52: 46614 | B52: 3.75 | C52: 99.186 | D52: 99.196 | E52: -0.006 | F52: 4.169
A53: 46614 | B53: 6.375 | C53: 101.296 | D53: 101.306 | E53: -0.706 | F53: 4.21
A54: 46630 | B54: 0.5 | C54: 96.144 | D54: 96.154 | E54: -0.006 | F54: 4.207
A55: 46630 | B55: 3.125 | C55: 98.304 | D55: 98.314 | E55: -0.006 | F55: 4.195
A56: 46630 | B56: 3.625 | C56: 99.136 | D56: 99.146 | E56: -0.01 | F56: 4.193
A57: 46645 | B57: 3.375 | C57: 99.054 | D57: 99.064 | E57: -0.002 | F57: 4.181
... A61: 46675 | B61: 3.875 | C61: 99.186 | D61: 99.196 | E61: -0.006 | F61: 4.231
A62: 46691 | B62: 0.5 | C62: 95.26 | D62: 95.27 | E62: unch. | F62: 4.26
A63: 46691 | B63: 3.5 | C63: 99.044 | D63: 99.054 | E63: -0.006 | F63: 4.246
A64: 46691 | B64: 4.125 | C64: 99.264 | D64: 99.274 | E64: -0.01 | F64: 4.248
A65: 46706 | B65: 2.25 | C65: 97.212 | D65: 97.222 | E65: -0.002 | F65: 4.263
A66: 46706 | B66: 4.125 | C66: 99.26 | D66: 99.27 | E66: -0.01 | F66: 4.257
A67: 46706 | B67: 6.125 | C67: 102.026 | D67: 102.036 | E67: -0.016 | F67: 4.267
A68: 46721 | B68: 0.625 | C68: 95.212 | D68: 95.222 | E68: 0.002 | F68: 4.263
A69: 46721 | B69: 3.375 | C69: 98.29 | D69: 98.3 | E69: -0.006 | F69: 4.269
A70: 46721 | B70: 3.875 | C70: 99.16 | D70: 99.17 | E70: -0.01 | F70: 4.267
A71: 46736 | B71: 4 | C71: 99.2 | D71: 99.21 | E71: -0.012 | F71: 4.277
A72: 46752 | B72: 0.625 | C72: 95.112 | D72: 95.122 | E72: -0.002 | F72: 4.287
A73: 46752 | B73: 3.375 | C73: 98.26 | D73: 98.27 | E73: -0.012 | F73: 4.289
A74: 46752 | B74: 3.875 | C74: 99.14 | D74: 99.15 | E74: -0.016 | F74: 4.293
... A265: 51271 | B265: 4.375 | C265: 93.306 | D265: 94.006 | E265: -0.698 | F265: 4.982
A266: 51363 | B266: 1.125 | C266: 60.274 | D266: 60.294 | E266: unch. | F266: 5.069
A267: 51363 | B267: 3.875 | C267: 88.222 | D267: 88.242 | E267: -0.014 | F267: 5.005
A268: 51455 | B268: 1.375 | C268: 62.242 | D268: 62.262 | E268: -0.002 | F268: 5.086
A269: 51455 | B269: 4.25 | C269: 92.062 | D269: 92.082 | E269: -0.014 | F269: 5.019
A270: 51547 | B270: 1.875 | C270: 67.11 | D270: 67.13 | E270: 0.006 | F270: 5.091
A271: 51547 | B271: 4.75 | C271: 97.004 | D271: 97.024 | E271: -0.022 | F271: 5.037
A272: 51636 | B272: 2.25 | C272: 70.22 | D272: 70.24 | E272: -0.006 | F272: 5.105
A273: 51636 | B273: 4.375 | C273: 92.3 | D273: 93 | E273: -0.01 | F273: 5.055
A274: 51728 | B274: 1.75 | C274: 64.304 | D274: 65.004 | E274: -0.008 | F274: 5.132
A275: 51728 | B275: 3.75 | C275: 86.036 | D275: 86.056 | E275: -0.016 | F275: 5.081
A276: 51820 | B276: 3.125 | C276: 79.044 | D276: 79.064 | E276: unch. | F276: 5.11
A277: 51835 | B277: 2 | C277: 67.016 | D277: 67.036 | E277: -0.008 | F277: 5.147
A278: 51912 | B278: 2.375 | C278: 70.192 | D278: 70.212 | E278: 0.002 | F278: 5.154
A279: 51912 | B279: 3.125 | C279: 78.226 | D279: 78.246 | E279: -0.004 | F279: 5.133
A280: 52001 | B280: 3 | C280: 76.312 | D280: 77.012 | E280: -0.004 | F280: 5.151
A281: 52001 | B281: 3.25 | C281: 79.21 | D281: 79.23 | E281: -0.002 | F281: 5.15
A282: 52093 | B282: 2.75 | C282: 73.272 | D282: 73.292 | E282: -0.004 | F282: 5.173
A283: 52093 | B283: 3.375 | C283: 80.224 | D283: 80.244 | E283: unch. | F283: 5.16
A284: 52185 | B284: 2.75 | C284: 73.144 | D284: 73.164 | E284: unch. | F284: 5.188
A285: 52185 | B285: 4 | C285: 87.072 | D285: 87.092 | E285: -0.008 | F285: 5.168
A286: 52277 | B286: 3.125 | C286: 77.076 | D286: 77.096 | E286: -0.008 | F286: 5.195
A287: 52277 | B287: 3.875 | C287: 85.194 | D287: 85.214 | E287: -0.002 | F287: 5.18
A288: 52366 | B288: 2.875 | C288: 74.042 | D288: 74.062 | E288: -0.004 | F288: 5.208
A289: 52366 | B289: 3.875 | C289: 85.116 | D289: 85.136 | E289: unch. | F289: 5.19
A290: 52458 | B290: 3.625 | C290: 82.074 | D290: 82.094 | E290: -0.008 | F290: 5.211
A291: 52458 | B291: 4.375 | C291: 90.25 | D291: 90.27 | E291: -0.012 | F291: 5.194
A292: 52550 | B292: 3.75 | C292: 83.144 | D292: 83.164 | E292: -0.002 | F292: 5.213
A293: 52550 | B293: 4.75 | C293: 94.296 | D293: 94.316 | E293: -0.008 | F293: 5.193
A294: 52642 | B294: 3.625 | C294: 81.242 | D294: 81.262 | E294: -0.008 | F294: 5.226
A295: 52642 | B295: 4.5 | C295: 91.274 | D295: 91.294 | E295: -0.01 | F295: 5.211
A296: 52732 | B296: 3.375 | C296: 78.2 | D296: 78.22 | E296: -0.014 | F296: 5.237
A297: 52732 | B297: 4.625 | C297: 93.06 | D297: 93.08 | E297: -0.01 | F297: 5.213
A298: 52824 | B298: 3.125 | C298: 75.13 | D298: 75.15 | E298: -0.014 | F298: 5.253
...

Sheet Bonds
A1: Per-bond mechanics with Excel bond functions (basis 1 = actual/actual, frequency 2). Coupon-period days are taken as COUPNCD - COUPPCD because COUPDAYS(basis 1) mis-states some month-end periods (183 vs 184 days). Model prices come from the CashFlows sheet.
A3: # | B3: Maturity | C3: Coupon % | D3: Bid (WSJ) | E3: Ask (WSJ) | F3: WSJ asked yield % | G3: Ask clean price (decimal) | H3: Previous coupon | I3: Next coupon | J3: Days accrued (settle - prev) | K3: Days in period (next - prev) | L3: Accrued interest | M3: Dirty price | N3: Street yield % (Excel YIELD) | O3: Yield check vs WSJ (bp) | P3: Modified duration | Q3: Remaining cash flows | R3: Years to maturity | S3: In fit (1/0) | T3: Model dirty price | U3: Model clean price | V3: Price error (model - mkt) | W3: Model yield % | X3: Yield error (bp) | Y3: Weight = 1 / duration | Z3: Weighted residual | AA3: Weighted sq. residual (in fit)
A4: 1 | B4: =Data!A3 -> 46280 | C4: =Data!B3 -> 4.625 | D4: =Data!C3 -> 100 | E4: =Data!D3 -> 100.01 | F4: =Data!F3 -> 2.937 | G4: =INT(E4)+(VALUE(MID(TEXT(E4,"0.000"),FIND(".",TEXT(E4,"0.000"))+1,2))+VALUE(RIGHT(TEXT(E4,"0.000"),1))/8)/32 -> 100.03125 | H4: =COUPPCD(Settle,B4,2,1) -> 46096 | I4: =COUPNCD(Settle,B4,2,1) -> 46280 | J4: =Settle-H4 -> 177 | K4: =I4-H4 -> 184 | L4: =C4/2*J4/K4 -> 2.2245245 | M4: =G4+L4 -> 102.25577 | N4: =YIELD(Settle,B4,C4/100,G4,100,2,1)*100 -> 2.9163564 | O4: =(N4-F4)*100 -> -2.0643566 | P4: =MDURATION(Settle,B4,C4/100,N4/100,2,1) -> 0.018748355 | Q4: =COUPNUM(Settle,B4,2,1) -> 1 | R4: =(B4-Settle)/365 -> 0.019178082 | S4: =IF(R4>=MinYears,1,0) -> 0 | T4: =SUM(CashFlows!DX4:GE4) -> 102.24107 | U4: =T4-L4 -> 100.01654 | V4: =U4-G4 -> -0.014707997 | W4: =YIELD(Settle,B4,C4/100,U4,100,2,1)*100 -> 3.6730478 | X4: =(W4-N4)*100 -> 75.669138 | Y4: =1/P4 -> 53.338014 | Z4: =Y4*(T4-M4) -> -0.78449533 | AA4: =S4*Z4^2 -> 0
A5: 2 | B5: =Data!A4 -> 46295 | C5: =Data!B4 -> 0.875 | D5: =Data!C4 -> 99.256 | E5: =Data!D4 -> 99.266 | F5: =Data!F4 -> 3.625 | G5: =INT(E5)+(VALUE(MID(TEXT(E5,"0.000"),FIND(".",TEXT(E5,"0.000"))+1,2))+VALUE(RIGHT(TEXT(E5,"0.000"),1))/8)/32 -> 99.835938 | H5: =COUPPCD(Settle,B5,2,1) -> 46112 | I5: =COUPNCD(Settle,B5,2,1) -> 46295 | J5: =Settle-H5 -> 161 | K5: =I5-H5 -> 183 | L5: =C5/2*J5/K5 -> 0.38490437 | M5: =G5+L5 -> 100.22084 | N5: =YIELD(Settle,B5,C5/100,G5,100,2,1)*100 -> 3.5964609 | O5: =(N5-F5)*100 -> -2.8539083 | P5: =MDURATION(Settle,B5,C5/100,N5/100,2,1) -> 0.05904748 | Q5: =COUPNUM(Settle,B5,2,1) -> 1 | R5: =(B5-Settle)/365 -> 0.060273973 | S5: =IF(R5>=MinYears,1,0) -> 0 | T5: =SUM(CashFlows!DX5:GE5) -> 100.21548 | U5: =T5-L5 -> 99.830575 | V5: =U5-G5 -> -0.0053620183 | W5: =YIELD(Settle,B5,C5/100,U5,100,2,1)*100 -> 3.685666 | X5: =(W5-N5)*100 -> 8.920511 | Y5: =1/P5 -> 16.935524 | Z5: =Y5*(T5-M5) -> -0.090808588 | AA5: =S5*Z5^2 -> 0
A6: 3 | B6: =Data!A5 -> 46295 | C6: =Data!B5 -> 1.625 | D6: =Data!C5 -> 99.276 | E6: =Data!D5 -> 99.286 | F6: =Data!F5 -> 3.318 | G6: =INT(E6)+(VALUE(MID(TEXT(E6,"0.000"),FIND(".",TEXT(E6,"0.000"))+1,2))+VALUE(RIGHT(TEXT(E6,"0.000"),1))/8)/32 -> 99.898438 | H6: =COUPPCD(Settle,B6,2,1) -> 46112 | I6: =COUPNCD(Settle,B6,2,1) -> 46295 | J6: =Settle-H6 -> 161 | K6: =I6-H6 -> 183 | L6: =C6/2*J6/K6 -> 0.7148224 | M6: =G6+L6 -> 100.61326 | N6: =YIELD(Settle,B6,C6/100,G6,100,2,1)*100 -> 3.2944273 | O6: =(N6-F6)*100 -> -2.357272 | P6: =MDURATION(Settle,B6,C6/100,N6/100,2,1) -> 0.059135206 | Q6: =COUPNUM(Settle,B6,2,1) -> 1 | R6: =(B6-Settle)/365 -> 0.060273973 | S6: =IF(R6>=MinYears,1,0) -> 0 | T6: =SUM(CashFlows!DX6:GE6) -> 100.58965 | U6: =T6-L6 -> 99.874829 | V6: =U6-G6 -> -0.023609 | W6: =YIELD(Settle,B6,C6/100,U6,100,2,1)*100 -> 3.685666 | X6: =(W6-N6)*100 -> 39.123875 | Y6: =1/P6 -> 16.9104 | Z6: =Y6*(T6-M6) -> -0.39923764 | AA6: =S6*Z6^2 -> 0
A7: 4 | B7: =Data!A6 -> 46295 | C7: =Data!B6 -> 3.5 | D7: =Data!C6 -> 99.306 | E7: =Data!D6 -> 99.316 | F7: =Data!F6 -> 3.603 | G7: =INT(E7)+(VALUE(MID(TEXT(E7,"0.000"),FIND(".",TEXT(E7,"0.000"))+1,2))+VALUE(RIGHT(TEXT(E7,"0.000"),1))/8)/32 -> 99.992188 | H7: =COUPPCD(Settle,B7,2,1) -> 46112 | I7: =COUPNCD(Settle,B7,2,1) -> 46295 | J7: =Settle-H7 -> 161 | K7: =I7-H7 -> 183 | L7: =C7/2*J7/K7 -> 1.5396175 | M7: =G7+L7 -> 101.5318 | N7: =YIELD(Settle,B7,C7/100,G7,100,2,1)*100 -> 3.5752064 | O7: =(N7-F7)*100 -> -2.7793599 | P7: =MDURATION(Settle,B7,C7/100,N7/100,2,1) -> 0.059053645 | Q7: =COUPNUM(Settle,B7,2,1) -> 1 | R7: =(B7-Settle)/365 -> 0.060273973 | S7: =IF(R7>=MinYears,1,0) -> 0 | T7: =SUM(CashFlows!DX7:GE7) -> 101.52508 | U7: =T7-L7 -> 99.985461 | V7: =U7-G7 -> -0.0067264542 | W7: =YIELD(Settle,B7,C7/100,U7,100,2,1)*100 -> 3.685666 | X7: =(W7-N7)*100 -> 11.045963 | Y7: =1/P7 -> 16.933756 | Z7: =Y7*(T7-M7) -> -0.11390413 | AA7: =S7*Z7^2 -> 0
A8: 5 | B8: =Data!A7 -> 46310 | C8: =Data!B7 -> 4.625 | D8: =Data!C7 -> 100.022 | E8: =Data!D7 -> 100.032 | F8: =Data!F7 -> 3.576 | G8: =INT(E8)+(VALUE(MID(TEXT(E8,"0.000"),FIND(".",TEXT(E8,"0.000"))+1,2))+VALUE(RIGHT(TEXT(E8,"0.000"),1))/8)/32 -> 100.10156 | H8: =COUPPCD(Settle,B8,2,1) -> 46127 | I8: =COUPNCD(Settle,B8,2,1) -> 46310 | J8: =Settle-H8 -> 146 | K8: =I8-H8 -> 183 | L8: =C8/2*J8/K8 -> 1.8449454 | M8: =G8+L8 -> 101.94651 | N8: =YIELD(Settle,B8,C8/100,G8,100,2,1)*100 -> 3.5512298 | O8: =(N8-F8)*100 -> -2.4770237 | P8: =MDURATION(Settle,B8,C8/100,N8/100,2,1) -> 0.099329192 | Q8: =COUPNUM(Settle,B8,2,1) -> 1 | R8: =(B8-Settle)/365 -> 0.10136986 | S8: =IF(R8>=MinYears,1,0) -> 0 | T8: =SUM(CashFlows!DX8:GE8) -> 101.92945 | U8: =T8-L8 -> 100.08451 | V8: =U8-G8 -> -0.017056054 | W8: =YIELD(Settle,B8,C8/100,U8,100,2,1)*100 -> 3.717347 | X8: =(W8-N8)*100 -> 16.611719 | Y8: =1/P8 -> 10.067534 | Z8: =Y8*(T8-M8) -> -0.1717124 | AA8: =S8*Z8^2 -> 0
A9: 6 | B9: =Data!A8 -> 46326 | C9: =Data!B8 -> 1.125 | D9: =Data!C8 -> 99.186 | E9: =Data!D8 -> 99.196 | F9: =Data!F8 -> 3.808 | G9: =INT(E9)+(VALUE(MID(TEXT(E9,"0.000"),FIND(".",TEXT(E9,"0.000"))+1,2))+VALUE(RIGHT(TEXT(E9,"0.000"),1))/8)/32 -> 99.617188 | H9: =COUPPCD(Settle,B9,2,1) -> 46142 | I9: =COUPNCD(Settle,B9,2,1) -> 46326 | J9: =Settle-H9 -> 131 | K9: =I9-H9 -> 184 | L9: =C9/2*J9/K9 -> 0.40047554 | M9: =G9+L9 -> 100.01766 | N9: =YIELD(Settle,B9,C9/100,G9,100,2,1)*100 -> 3.7823508 | O9: =(N9-F9)*100 -> -2.564921 | P9: =MDURATION(Settle,B9,C9/100,N9/100,2,1) -> 0.14134859 | Q9: =COUPNUM(Settle,B9,2,1) -> 1 | R9: =(B9-Settle)/365 -> 0.14520548 | S9: =IF(R9>=MinYears,1,0) -> 0 | T9: =SUM(CashFlows!DX9:GE9) -> 100.01934 | U9: =T9-L9 -> 99.618861 | V9: =U9-G9 -> 0.001673366 | W9: =YIELD(Settle,B9,C9/100,U9,100,2,1)*100 -> 3.7706709 | X9: =(W9-N9)*100 -> -1.1679877 | Y9: =1/P9 -> 7.074708 | Z9: =Y9*(T9-M9) -> 0.011838576 | AA9: =S9*Z9^2 -> 0
A10: 7 | B10: =Data!A9 -> 46326 | C10: =Data!B9 -> 1.625 | D10: =Data!C9 -> 99.212 | E10: =Data!D9 -> 99.222 | F10: =Data!F9 -> 3.755 | G10: =INT(E10)+(VALUE(MID(TEXT(E10,"0.000"),FIND(".",TEXT(E10,"0.000"))+1,2))+VALUE(RIGHT(TEXT(E10,"0.000"),1))/8)/32 -> 99.695312 | H10: =COUPPCD(Settle,B10,2,1) -> 46142 | I10: =COUPNCD(Settle,B10,2,1) -> 46326 | J10: =Settle-H10 -> 131 | K10: =I10-H10 -> 184 | L10: =C10/2*J10/K10 -> 0.57846467 | M10: =G10+L10 -> 100.27378 | N10: =YIELD(Settle,B10,C10/100,G10,100,2,1)*100 -> 3.7303532 | O10: =(N10-F10)*100 -> -2.4646818 | P10: =MDURATION(Settle,B10,C10/100,N10/100,2,1) -> 0.14138467 | Q10: =COUPNUM(Settle,B10,2,1) -> 1 | R10: =(B10-Settle)/365 -> 0.14520548 | S10: =IF(R10>=MinYears,1,0) -> 0 | T10: =SUM(CashFlows!DX10:GE10) -> 100.26799 | U10: =T10-L10 -> 99.689521 | V10: =U10-G10 -> -0.0057910779 | W10: =YIELD(Settle,B10,C10/100,U10,100,2,1)*100 -> 3.7706709 | X10: =(W10-N10)*100 -> 4.031773 | Y10: =1/P10 -> 7.0729028 | Z10: =Y10*(T10-M10) -> -0.040959731 | AA10: =S10*Z10^2 -> 0
A11: 8 | B11: =Data!A10 -> 46326 | C11: =Data!B10 -> 4.125 | D11: =Data!C10 -> 100 | E11: =Data!D10 -> 100.01 | F11: =Data!F10 -> 3.877 | G11: =INT(E11)+(VALUE(MID(TEXT(E11,"0.000"),FIND(".",TEXT(E11,"0.000"))+1,2))+VALUE(RIGHT(TEXT(E11,"0.000"),1))/8)/32 -> 100.03125 | H11: =COUPPCD(Settle,B11,2,1) -> 46142 | I11: =COUPNCD(Settle,B11,2,1) -> 46326 | J11: =Settle-H11 -> 131 | K11: =I11-H11 -> 184 | L11: =C11/2*J11/K11 -> 1.4684103 | M11: =G11+L11 -> 101.49966 | N11: =YIELD(Settle,B11,C11/100,G11,100,2,1)*100 -> 3.8502778 | O11: =(N11-F11)*100 -> -2.672222 | P11: =MDURATION(Settle,B11,C11/100,N11/100,2,1) -> 0.14130149 | Q11: =COUPNUM(Settle,B11,2,1) -> 1 | R11: =(B11-Settle)/365 -> 0.14520548 | S11: =IF(R11>=MinYears,1,0) -> 0 | T11: =SUM(CashFlows!DX11:GE11) -> 101.51123 | U11: =T11-L11 -> 100.04282 | V11: =U11-G11 -> 0.011574203 | W11: =YIELD(Settle,B11,C11/100,U11,100,2,1)*100 -> 3.7706709 | X11: =(W11-N11)*100 -> -7.9606867 | Y11: =1/P11 -> 7.0770662 | Z11: =Y11*(T11-M11) -> 0.081911398 | AA11: =S11*Z11^2 -> 0
A12: 9 | B12: =Data!A11 -> 46341 | C12: =Data!B11 -> 2 | D12: =Data!C11 -> 99.204 | E12: =Data!D11 -> 99.214 | F12: =Data!F11 -> 3.787 | G12: =INT(E12)+(VALUE(MID(TEXT(E12,"0.000"),FIND(".",TEXT(E12,"0.000"))+1,2))+VALUE(RIGHT(TEXT(E12,"0.000"),1))/8)/32 -> 99.671875 | H12: =COUPPCD(Settle,B12,2,1) -> 46157 | I12: =COUPNCD(Settle,B12,2,1) -> 46341 | J12: =Settle-H12 -> 116 | K12: =I12-H12 -> 184 | L12: =C12/2*J12/K12 -> 0.63043478 | M12: =G12+L12 -> 100.30231 | N12: =YIELD(Settle,B12,C12/100,G12,100,2,1)*100 -> 3.7643553 | O12: =(N12-F12)*100 -> -2.264472 | P12: =MDURATION(Settle,B12,C12/100,N12/100,2,1) -> 0.18136892 | Q12: =COUPNUM(Settle,B12,2,1) -> 1 | R12: =(B12-Settle)/365 -> 0.18630137 | S12: =IF(R12>=MinYears,1,0) -> 0 | T12: =SUM(CashFlows!DX12:GE12) -> 100.29561 | U12: =T12-L12 -> 99.665179 | V12: =U12-G12 -> -0.0066963481 | W12: =YIELD(Settle,B12,C12/100,U12,100,2,1)*100 -> 3.8007389 | X12: =(W12-N12)*100 -> 3.638358 | Y12: =1/P12 -> 5.5136237 | Z12: =Y12*(T12-M12) -> -0.036921144 | AA12: =S12*Z12^2 -> 0
A13: 10 | B13: =Data!A12 -> 46341 | C13: =Data!B12 -> 4.625 | D13: =Data!C12 -> 100.04 | E13: =Data!D12 -> 100.05 | F13: =Data!F12 -> 3.741 | G13: =INT(E13)+(VALUE(MID(TEXT(E13,"0.000"),FIND(".",TEXT(E13,"0.000"))+1,2))+VALUE(RIGHT(TEXT(E13,"0.000"),1))/8)/32 -> 100.15625 | H13: =COUPPCD(Settle,B13,2,1) -> 46157 | I13: =COUPNCD(Settle,B13,2,1) -> 46341 | J13: =Settle-H13 -> 116 | K13: =I13-H13 -> 184 | L13: =C13/2*J13/K13 -> 1.4578804 | M13: =G13+L13 -> 101.61413 | N13: =YIELD(Settle,B13,C13/100,G13,100,2,1)*100 -> 3.7193762 | O13: =(N13-F13)*100 -> -2.1623818 | P13: =MDURATION(Settle,B13,C13/100,N13/100,2,1) -> 0.18140897 | Q13: =COUPNUM(Settle,B13,2,1) -> 1 | R13: =(B13-Settle)/365 -> 0.18630137 | S13: =IF(R13>=MinYears,1,0) -> 0 | T13: =SUM(CashFlows!DX13:GE13) -> 101.59896 | U13: =T13-L13 -> 100.14108 | V13: =U13-G13 -> -0.015170539 | W13: =YIELD(Settle,B13,C13/100,U13,100,2,1)*100 -> 3.8007389 | X13: =(W13-N13)*100 -> 8.1362678 | Y13: =1/P13 -> 5.5124066 | Z13: =Y13*(T13-M13) -> -0.083626178 | AA13: =S13*Z13^2 -> 0
A14: 11 | B14: =Data!A13 -> 46341 | C14: =Data!B13 -> 6.5 | D14: =Data!C13 -> 100.13 | E14: =Data!D13 -> 100.14 | F14: =Data!F13 -> 4.058 | G14: =INT(E14)+(VALUE(MID(TEXT(E14,"0.000"),FIND(".",TEXT(E14,"0.000"))+1,2))+VALUE(RIGHT(TEXT(E14,"0.000"),1))/8)/32 -> 100.4375 | H14: =COUPPCD(Settle,B14,2,1) -> 46157 | I14: =COUPNCD(Settle,B14,2,1) -> 46341 | J14: =Settle-H14 -> 116 | K14: =I14-H14 -> 184 | L14: =C14/2*J14/K14 -> 2.048913 | M14: =G14+L14 -> 102.48641 | N14: =YIELD(Settle,B14,C14/100,G14,100,2,1)*100 -> 4.0320983 | O14: =(N14-F14)*100 -> -2.5901677 | P14: =MDURATION(Settle,B14,C14/100,N14/100,2,1) -> 0.18113092 | Q14: =COUPNUM(Settle,B14,2,1) -> 1 | R14: =(B14-Settle)/365 -> 0.18630137 | S14: =IF(R14>=MinYears,1,0) -> 0 | T14: =SUM(CashFlows!DX14:GE14) -> 102.52992 | U14: =T14-L14 -> 100.48101 | V14: =U14-G14 -> 0.043508611 | W14: =YIELD(Settle,B14,C14/100,U14,100,2,1)*100 -> 3.8007389 | X14: =(W14-N14)*100 -> -23.135946 | Y14: =1/P14 -> 5.5208685 | Z14: =Y14*(T14-M14) -> 0.24020532 | AA14: =S14*Z14^2 -> 0
A15: 12 | B15: =Data!A14 -> 46356 | C15: =Data!B14 -> 1.25 | D15: =Data!C14 -> 99.126 | E15: =Data!D14 -> 99.136 | F15: =Data!F14 -> 3.793 | G15: =INT(E15)+(VALUE(MID(TEXT(E15,"0.000"),FIND(".",TEXT(E15,"0.000"))+1,2))+VALUE(RIGHT(TEXT(E15,"0.000"),1))/8)/32 -> 99.429688 | H15: =COUPPCD(Settle,B15,2,1) -> 46173 | I15: =COUPNCD(Settle,B15,2,1) -> 46356 | J15: =Settle-H15 -> 100 | K15: =I15-H15 -> 183 | L15: =C15/2*J15/K15 -> 0.34153005 | M15: =G15+L15 -> 99.771218 | N15: =YIELD(Settle,B15,C15/100,G15,100,2,1)*100 -> 3.7735051 | O15: =(N15-F15)*100 -> -1.9494895 | P15: =MDURATION(Settle,B15,C15/100,N15/100,2,1) -> 0.22257649 | Q15: =COUPNUM(Settle,B15,2,1) -> 1 | R15: =(B15-Settle)/365 -> 0.22739726 | S15: =IF(R15>=MinYears,1,0) -> 0 | T15: =SUM(CashFlows!DX15:GE15) -> 99.763218 | U15: =T15-L15 -> 99.421688 | V15: =U15-G15 -> -0.0079994508 | W15: =YIELD(Settle,B15,C15/100,U15,100,2,1)*100 -> 3.8091661 | X15: =(W15-N15)*100 -> 3.5660985 | Y15: =1/P15 -> 4.4928375 | Z15: =Y15*(T15-M15) -> -0.035940233 | AA15: =S15*Z15^2 -> 0
... A356: 353 | B356: =Data!A355 -> 57207 | C356: =Data!B355 -> 5.125 | D356: =Data!C355 -> 98.06 | E356: =Data!D355 -> 98.08 | F356: =Data!F355 -> 5.241 | G356: =INT(E356)+(VALUE(MID(TEXT(E356,"0.000"),FIND(".",TEXT(E356,"0.000"))+1,2))+VALUE(RIGHT(TEXT(E356,"0.000"),1))/8)/32 -> 98.25 | H356: =COUPPCD(Settle,B356,2,1) -> 46249 | I356: =COUPNCD(Settle,B356,2,1) -> 46433 | J356: =Settle-H356 -> 24 | K356: =I356-H356 -> 184 | L356: =C356/2*J356/K356 -> 0.33423913 | M356: =G356+L356 -> 98.584239 | N356: =YIELD(Settle,B356,C356/100,G356,100,2,1)*100 -> 5.2412244 | O356: =(N356-F356)*100 -> 0.02244479 | P356: =MDURATION(Settle,B356,C356/100,N356/100,2,1) -> 15.042795 | Q356: =COUPNUM(Settle,B356,2,1) -> 60 | R356: =(B356-Settle)/365 -> 29.956164 | S356: =IF(R356>=MinYears,1,0) -> 1 | T356: =SUM(CashFlows!DX356:GE356) -> 98.324946 | U356: =T356-L356 -> 97.990707 | V356: =U356-G356 -> -0.25929283 | W356: =YIELD(Settle,B356,C356/100,U356,100,2,1)*100 -> 5.2587434 | X356: =(W356-N356)*100 -> 1.7518997 | Y356: =1/P356 -> 0.06647701 | Z356: =Y356*(T356-M356) -> -0.017237012 | AA356: =S356*Z356^2 -> 0.00029711457

Sheet CashFlows
A1: Every remaining payment of every bond. Block 1: payment dates (k-th coupon after settlement). Block 2: Svensson zero rate r(t_k). Block 3: present value = amount x exp(-r t). Model dirty price = row sum of block 3.
F2: Payment dates | BO2: Zero rates (continuous, decimal) | DX2: Present values (per 100 face)
A3: # | B3: Maturity | C3: Coupon % | D3: Remaining flows N | E3: Month-end (1/0) | F3: Date 1 | G3: Date 2 | H3: Date 3 | I3: Date 4 | J3: Date 5 | K3: Date 6 | L3: Date 7 | M3: Date 8 | N3: Date 9 | O3: Date 10 | P3: Date 11 | Q3: Date 12 | R3: Date 13 | S3: Date 14 | T3: Date 15 | U3: Date 16 | V3: Date 17 | W3: Date 18 | X3: Date 19 | Y3: Date 20 | Z3: Date 21 | AA3: Date 22 | AB3: Date 23 | AC3: Date 24 | AD3: Date 25 | AE3: Date 26 | AF3: Date 27 | AG3: Date 28 | AH3: Date 29 | AI3: Date 30 | AJ3: Date 31 | AK3: Date 32 | AL3: Date 33 | AM3: Date 34 | AN3: Date 35 | AO3: Date 36 | AP3: Date 37 | AQ3: Date 38 | AR3: Date 39 | AS3: Date 40 | AT3: Date 41 | AU3: Date 42 | AV3: Date 43 | AW3: Date 44 | AX3: Date 45 | AY3: Date 46 | AZ3: Date 47 | BA3: Date 48 | BB3: Date 49 | BC3: Date 50 | BD3: Date 51 | BE3: Date 52 | BF3: Date 53 | BG3: Date 54 | BH3: Date 55 | BI3: Date 56 | BJ3: Date 57 | BK3: Date 58 | BL3: Date 59 | BM3: Date 60 | BO3: r(t) 1 | BP3: r(t) 2 | BQ3: r(t) 3 | BR3: r(t) 4 | BS3: r(t) 5 | BT3: r(t) 6 | BU3: r(t) 7 | BV3: r(t) 8 | BW3: r(t) 9 | BX3: r(t) 10 | BY3: r(t) 11 | BZ3: r(t) 12 | CA3: r(t) 13 | CB3: r(t) 14 | CC3: r(t) 15 | CD3: r(t) 16 | CE3: r(t) 17 | CF3: r(t) 18 | CG3: r(t) 19 | CH3: r(t) 20 | CI3: r(t) 21 | CJ3: r(t) 22 | CK3: r(t) 23 | CL3: r(t) 24 | CM3: r(t) 25 | CN3: r(t) 26 | CO3: r(t) 27 | CP3: r(t) 28 | CQ3: r(t) 29 | CR3: r(t) 30 | CS3: r(t) 31 | CT3: r(t) 32 | CU3: r(t) 33 | CV3: r(t) 34 | CW3: r(t) 35 | CX3: r(t) 36 | CY3: r(t) 37 | CZ3: r(t) 38 | DA3: r(t) 39 | DB3: r(t) 40 | DC3: r(t) 41 | DD3: r(t) 42 | DE3: r(t) 43 | DF3: r(t) 44 | DG3: r(t) 45 | DH3: r(t) 46 | DI3: r(t) 47 | DJ3: r(t) 48 | DK3: r(t) 49 | DL3: r(t) 50 | DM3: r(t) 51 | DN3: r(t) 52 | DO3: r(t) 53 | DP3: r(t) 54 | DQ3: r(t) 55 | DR3: r(t) 56 | DS3: r(t) 57 | DT3: r(t) 58 | DU3: r(t) 59 | DV3: r(t) 60 | DX3: PV 1 | DY3: PV 2 | DZ3: PV 3 | EA3: PV 4 | EB3: PV 5 | EC3: PV 6 | ED3: PV 7 | EE3: PV 8 | EF3: PV 9 | EG3: PV 10 | EH3: PV 11 | EI3: PV 12 | EJ3: PV 13 | EK3: PV 14 | EL3: PV 15 | EM3: PV 16 | EN3: PV 17 | EO3: PV 18 | EP3: PV 19 | EQ3: PV 20 | ER3: PV 21 | ES3: PV 22 | ET3: PV 23 | EU3: PV 24 | EV3: PV 25 | EW3: PV 26 | EX3: PV 27 | EY3: PV 28 | EZ3: PV 29 | FA3: PV 30 | FB3: PV 31 | FC3: PV 32 | FD3: PV 33 | FE3: PV 34 | FF3: PV 35 | FG3: PV 36 | FH3: PV 37 | FI3: PV 38 | FJ3: PV 39 | FK3: PV 40 | FL3: PV 41 | FM3: PV 42 | FN3: PV 43 | FO3: PV 44 | FP3: PV 45 | FQ3: PV 46 | FR3: PV 47 | FS3: PV 48 | FT3: PV 49 | FU3: PV 50 | FV3: PV 51 | FW3: PV 52 | FX3: PV 53 | FY3: PV 54 | FZ3: PV 55 | GA3: PV 56 | GB3: PV 57 | GC3: PV 58 | GD3: PV 59 | GE3: PV 60
A4: 1 | B4: =Bonds!B4 -> 46280 | C4: =Bonds!C4 -> 4.625 | D4: =Bonds!Q4 -> 1 | E4: =IF(DAY(B4)=DAY(EOMONTH(B4,0)),1,0) -> 0 | F4: =IF(1>$D4,"",IF($E4=1,EOMONTH(EDATE(Bonds!$I4,6*(1-1)),0),EDATE(Bonds!$I4,6*(1-1)))) -> 46280 | G4: =IF(2>$D4,"",IF($E4=1,EOMONTH(EDATE(Bonds!$I4,6*(2-1)),0),EDATE(Bonds!$I4,6*(2-1)))) | H4: =IF(3>$D4,"",IF($E4=1,EOMONTH(EDATE(Bonds!$I4,6*(3-1)),0),EDATE(Bonds!$I4,6*(3-1)))) | I4: =IF(4>$D4,"",IF($E4=1,EOMONTH(EDATE(Bonds!$I4,6*(4-1)),0),EDATE(Bonds!$I4,6*(4-1)))) | J4: =IF(5>$D4,"",IF($E4=1,EOMONTH(EDATE(Bonds!$I4,6*(5-1)),0),EDATE(Bonds!$I4,6*(5-1)))) | K4: =IF(6>$D4,"",IF($E4=1,EOMONTH(EDATE(Bonds!$I4,6*(6-1)),0),EDATE(Bonds!$I4,6*(6-1)))) | L4: =IF(7>$D4,"",IF($E4=1,EOMONTH(EDATE(Bonds!$I4,6*(7-1)),0),EDATE(Bonds!$I4,6*(7-1)))) | M4: =IF(8>$D4,"",IF($E4=1,EOMONTH(EDATE(Bonds!$I4,6*(8-1)),0),EDATE(Bonds!$I4,6*(8-1)))) | N4: =IF(9>$D4,"",IF($E4=1,EOMONTH(EDATE(Bonds!$I4,6*(9-1)),0),EDATE(Bonds!$I4,6*(9-1)))) | O4: =IF(10>$D4,"",IF($E4=1,EOMONTH(EDATE(Bonds!$I4,6*(10-1)),0),EDATE(Bonds!$I4,6*(10-1)))) | P4: =IF(11>$D4,"",IF($E4=1,EOMONTH(EDATE(Bonds!$I4,6*(11-1)),0),EDATE(Bonds!$I4,6*(11-1)))) | Q4: =IF(12>$D4,"",IF($E4=1,EOMONTH(EDATE(Bonds!$I4,6*(12-1)),0),EDATE(Bonds!$I4,6*(12-1)))) | R4: =IF(13>$D4,"",IF($E4=1,EOMONTH(EDATE(Bonds!$I4,6*(13-1)),0),EDATE(Bonds!$I4,6*(13-1)))) | S4: =IF(14>$D4,"",IF($E4=1,EOMONTH(EDATE(Bonds!$I4,6*(14-1)),0),EDATE(Bonds!$I4,6*(14-1)))) | T4: =IF(15>$D4,"",IF($E4=1,EOMONTH(EDATE(Bonds!$I4,6*(15-1)),0),EDATE(Bonds!$I4,6*(15-1)))) | U4: =IF(16>$D4,"",IF($E4=1,EOMONTH(EDATE(Bonds!$I4,6*(16-1)),0),EDATE(Bonds!$I4,6*(16-1)))) | V4: =IF(17>$D4,"",IF($E4=1,EOMONTH(EDATE(Bonds!$I4,6*(17-1)),0),EDATE(Bonds!$I4,6*(17-1)))) | W4: =IF(18>$D4,"",IF($E4=1,EOMONTH(EDATE(Bonds!$I4,6*(18-1)),0),EDATE(Bonds!$I4,6*(18-1)))) | X4: =IF(19>$D4,"",IF($E4=1,EOMONTH(EDATE(Bonds!$I4,6*(19-1)),0),EDATE(Bonds!$I4,6*(19-1)))) | Y4: =IF(20>$D4,"",IF($E4=1,EOMONTH(EDATE(Bonds!$I4,6*(20-1)),0),EDATE(Bonds!$I4,6*(20-1)))) | Z4: =IF(21>$D4,"",IF($E4=1,EOMONTH(EDATE(Bonds!$I4,6*(21-1)),0),EDATE(Bonds!$I4,6*(21-1)))) | AA4: =IF(22>$D4,"",IF($E4=1,EOMONTH(EDATE(Bonds!$I4,6*(22-1)),0),EDATE(Bonds!$I4,6*(22-1)))) | AB4: =IF(23>$D4,"",IF($E4=1,EOMONTH(EDATE(Bonds!$I4,6*(23-1)),0),EDATE(Bonds!$I4,6*(23-1)))) | AC4: =IF(24>$D4,"",IF($E4=1,EOMONTH(EDATE(Bonds!$I4,6*(24-1)),0),EDATE(Bonds!$I4,6*(24-1)))) | AD4: =IF(25>$D4,"",IF($E4=1,EOMONTH(EDATE(Bonds!$I4,6*(25-1)),0),EDATE(Bonds!$I4,6*(25-1)))) | AE4: =IF(26>$D4,"",IF($E4=1,EOMONTH(EDATE(Bonds!$I4,6*(26-1)),0),EDATE(Bonds!$I4,6*(26-1)))) | AF4: =IF(27>$D4,"",IF($E4=1,EOMONTH(EDATE(Bonds!$I4,6*(27-1)),0),EDATE(Bonds!$I4,6*(27-1)))) | AG4: =IF(28>$D4,"",IF($E4=1,EOMONTH(EDATE(Bonds!$I4,6*(28-1)),0),EDATE(Bonds!$I4,6*(28-1)))) | AH4: =IF(29>$D4,"",IF($E4=1,EOMONTH(EDATE(Bonds!$I4,6*(29-1)),0),EDATE(Bonds!$I4,6*(29-1)))) | AI4: =IF(30>$D4,"",IF($E4=1,EOMONTH(EDATE(Bonds!$I4,6*(30-1)),0),EDATE(Bonds!$I4,6*(30-1)))) | AJ4: =IF(31>$D4,"",IF($E4=1,EOMONTH(EDATE(Bonds!$I4,6*(31-1)),0),EDATE(Bonds!$I4,6*(31-1)))) | AK4: =IF(32>$D4,"",IF($E4=1,EOMONTH(EDATE(Bonds!$I4,6*(32-1)),0),EDATE(Bonds!$I4,6*(32-1)))) | AL4: =IF(33>$D4,"",IF($E4=1,EOMONTH(EDATE(Bonds!$I4,6*(33-1)),0),EDATE(Bonds!$I4,6*(33-1)))) | AM4: =IF(34>$D4,"",IF($E4=1,EOMONTH(EDATE(Bonds!$I4,6*(34-1)),0),EDATE(Bonds!$I4,6*(34-1)))) | AN4: =IF(35>$D4,"",IF($E4=1,EOMONTH(EDATE(Bonds!$I4,6*(35-1)),0),EDATE(Bonds!$I4,6*(35-1)))) | AO4: =IF(36>$D4,"",IF($E4=1,EOMONTH(EDATE(Bonds!$I4,6*(36-1)),0),EDATE(Bonds!$I4,6*(36-1)))) | AP4: =IF(37>$D4,"",IF($E4=1,EOMONTH(EDATE(Bonds!$I4,6*(37-1)),0),EDATE(Bonds!$I4,6*(37-1)))) | AQ4: =IF(38>$D4,"",IF($E4=1,EOMONTH(EDATE(Bonds!$I4,6*(38-1)),0),EDATE(Bonds!$I4,6*(38-1)))) | AR4: =IF(39>$D4,"",IF($E4=1,EOMONTH(EDATE(Bonds!$I4,6*(39-1)),0),EDATE(Bonds!$I4,6*(39-1)))) | AS4: =IF(40>$D4,"",IF($E4=1,EOMONTH(EDATE(Bonds!$I4,6*(40-1)),0),EDATE(Bonds!$I4,6*(40-1)))) | AT4: =IF(41>$D4,"",IF($E4=1,EOMONTH(EDATE(Bonds!$I4,6*(41-1)),0),EDATE(Bonds!$I4,6*(41-1)))) | AU4: =IF(42>$D4,"",IF($E4=1,EOMONTH(EDATE(Bonds!$I4,6*(42-1)),0),EDATE(Bonds!$I4,6*(42-1)))) | AV4: =IF(43>$D4,"",IF($E4=1,EOMONTH(EDATE(Bonds!$I4,6*(43-1)),0),EDATE(Bonds!$I4,6*(43-1)))) | AW4: =IF(44>$D4,"",IF($E4=1,EOMONTH(EDATE(Bonds!$I4,6*(44-1)),0),EDATE(Bonds!$I4,6*(44-1)))) | AX4: =IF(45>$D4,"",IF($E4=1,EOMONTH(EDATE(Bonds!$I4,6*(45-1)),0),EDATE(Bonds!$I4,6*(45-1)))) | AY4: =IF(46>$D4,"",IF($E4=1,EOMONTH(EDATE(Bonds!$I4,6*(46-1)),0),EDATE(Bonds!$I4,6*(46-1)))) | AZ4: =IF(47>$D4,"",IF($E4=1,EOMONTH(EDATE(Bonds!$I4,6*(47-1)),0),EDATE(Bonds!$I4,6*(47-1)))) | BA4: =IF(48>$D4,"",IF($E4=1,EOMONTH(EDATE(Bonds!$I4,6*(48-1)),0),EDATE(Bonds!$I4,6*(48-1)))) | BB4: =IF(49>$D4,"",IF($E4=1,EOMONTH(EDATE(Bonds!$I4,6*(49-1)),0),EDATE(Bonds!$I4,6*(49-1)))) | BC4: =IF(50>$D4,"",IF($E4=1,EOMONTH(EDATE(Bonds!$I4,6*(50-1)),0),EDATE(Bonds!$I4,6*(50-1)))) | BD4: =IF(51>$D4,"",IF($E4=1,EOMONTH(EDATE(Bonds!$I4,6*(51-1)),0),EDATE(Bonds!$I4,6*(51-1)))) | BE4: =IF(52>$D4,"",IF($E4=1,EOMONTH(EDATE(Bonds!$I4,6*(52-1)),0),EDATE(Bonds!$I4,6*(52-1)))) | BF4: =IF(53>$D4,"",IF($E4=1,EOMONTH(EDATE(Bonds!$I4,6*(53-1)),0),EDATE(Bonds!$I4,6*(53-1)))) | BG4: =IF(54>$D4,"",IF($E4=1,EOMONTH(EDATE(Bonds!$I4,6*(54-1)),0),EDATE(Bonds!$I4,6*(54-1)))) | BH4: =IF(55>$D4,"",IF($E4=1,EOMONTH(EDATE(Bonds!$I4,6*(55-1)),0),EDATE(Bonds!$I4,6*(55-1)))) | BI4: =IF(56>$D4,"",IF($E4=1,EOMONTH(EDATE(Bonds!$I4,6*(56-1)),0),EDATE(Bonds!$I4,6*(56-1)))) | BJ4: =IF(57>$D4,"",IF($E4=1,EOMONTH(EDATE(Bonds!$I4,6*(57-1)),0),EDATE(Bonds!$I4,6*(57-1)))) | BK4: =IF(58>$D4,"",IF($E4=1,EOMONTH(EDATE(Bonds!$I4,6*(58-1)),0),EDATE(Bonds!$I4,6*(58-1)))) | BL4: =IF(59>$D4,"",IF($E4=1,EOMONTH(EDATE(Bonds!$I4,6*(59-1)),0),EDATE(Bonds!$I4,6*(59-1)))) | BM4: =IF(60>$D4,"",IF($E4=1,EOMONTH(EDATE(Bonds!$I4,6*(60-1)),0),EDATE(Bonds!$I4,6*(60-1)))) | BO4: =IF(F4="","",Sv_beta0+Sv_beta1*(1-EXP(-((F4-Settle)/365)/Sv_tau1))/(((F4-Settle)/365)/Sv_tau1)+Sv_beta2*((1-EXP(-((F4-Settle)/365)/Sv_tau1))/(((F4-Settle)/365)/Sv_tau1)-EXP(-((F4-Settle)/365)/Sv_tau1))+Sv_beta3*((1-EXP(-((F4-Settle)/365)/Sv_tau2))/(((F4-Settle)/365)/Sv_tau2)-EXP(-((F4-Settle)/365)/Sv_tau2))) -> 0.036418324 | BP4: =IF(G4="","",Sv_beta0+Sv_beta1*(1-EXP(-((G4-Settle)/365)/Sv_tau1))/(((G4-Settle)/365)/Sv_tau1)+Sv_beta2*((1-EXP(-((G4-Settle)/365)/Sv_tau1))/(((G4-Settle)/365)/Sv_tau1)-EXP(-((G4-Settle)/365)/Sv_tau1))+Sv_beta3*((1-EXP(-((G4-Settle)/365)/Sv_tau2))/(((G4-Settle)/365)/Sv_tau2)-EXP(-((G4-Settle)/365)/Sv_tau2))) | BQ4: =IF(H4="","",Sv_beta0+Sv_beta1*(1-EXP(-((H4-Settle)/365)/Sv_tau1))/(((H4-Settle)/365)/Sv_tau1)+Sv_beta2*((1-EXP(-((H4-Settle)/365)/Sv_tau1))/(((H4-Settle)/365)/Sv_tau1)-EXP(-((H4-Settle)/365)/Sv_tau1))+Sv_beta3*((1-EXP(-((H4-Settle)/365)/Sv_tau2))/(((H4-Settle)/365)/Sv_tau2)-EXP(-((H4-Settle)/365)/Sv_tau2))) | BR4: =IF(I4="","",Sv_beta0+Sv_beta1*(1-EXP(-((I4-Settle)/365)/Sv_tau1))/(((I4-Settle)/365)/Sv_tau1)+Sv_beta2*((1-EXP(-((I4-Settle)/365)/Sv_tau1))/(((I4-Settle)/365)/Sv_tau1)-EXP(-((I4-Settle)/365)/Sv_tau1))+Sv_beta3*((1-EXP(-((I4-Settle)/365)/Sv_tau2))/(((I4-Settle)/365)/Sv_tau2)-EXP(-((I4-Settle)/365)/Sv_tau2))) | BS4: =IF(J4="","",Sv_beta0+Sv_beta1*(1-EXP(-((J4-Settle)/365)/Sv_tau1))/(((J4-Settle)/365)/Sv_tau1)+Sv_beta2*((1-EXP(-((J4-Settle)/365)/Sv_tau1))/(((J4-Settle)/365)/Sv_tau1)-EXP(-((J4-Settle)/365)/Sv_tau1))+Sv_beta3*((1-EXP(-((J4-Settle)/365)/Sv_tau2))/(((J4-Settle)/365)/Sv_tau2)-EXP(-((J4-Settle)/365)/Sv_tau2))) | BT4: =IF(K4="","",Sv_beta0+Sv_beta1*(1-EXP(-((K4-Settle)/365)/Sv_tau1))/(((K4-Settle)/365)/Sv_tau1)+Sv_beta2*((1-EXP(-((K4-Settle)/365)/Sv_tau1))/(((K4-Settle)/365)/Sv_tau1)-EXP(-((K4-Settle)/365)/Sv_tau1))+Sv_beta3*((1-EXP(-((K4-Settle)/365)/Sv_tau2))/(((K4-Settle)/365)/Sv_tau2)-EXP(-((K4-Settle)/365)/Sv_tau2))) | BU4: =IF(L4="","",Sv_beta0+Sv_beta1*(1-EXP(-((L4-Settle)/365)/Sv_tau1))/(((L4-Settle)/365)/Sv_tau1)+Sv_beta2*((1-EXP(-((L4-Settle)/365)/Sv_tau1))/(((L4-Settle)/365)/Sv_tau1)-EXP(-((L4-Settle)/365)/Sv_tau1))+Sv_beta3*((1-EXP(-((L4-Settle)/365)/Sv_tau2))/(((L4-Settle)/365)/Sv_tau2)-EXP(-((L4-Settle)/365)/Sv_tau2))) | BV4: =IF(M4="","",Sv_beta0+Sv_beta1*(1-EXP(-((M4-Settle)/365)/Sv_tau1))/(((M4-Settle)/365)/Sv_tau1)+Sv_beta2*((1-EXP(-((M4-Settle)/365)/Sv_tau1))/(((M4-Settle)/365)/Sv_tau1)-EXP(-((M4-Settle)/365)/Sv_tau1))+Sv_beta3*((1-EXP(-((M4-Settle)/365)/Sv_tau2))/(((M4-Settle)/365)/Sv_tau2)-EXP(-((M4-Settle)/365)/Sv_tau2))) | ... DV4: =IF(BM4="","",Sv_beta0+Sv_beta1*(1-EXP(-((BM4-Settle)/365)/Sv_tau1))/(((BM4-Settle)/365)/Sv_tau1)+Sv_beta2*((1-EXP(-((BM4-Settle)/365)/Sv_tau1))/(((BM4-Settle)/365)/Sv_tau1)-EXP(-((BM4-Settle)/365)/Sv_tau1))+Sv_beta3*((1-EXP(-((BM4-Settle)/365)/Sv_tau2))/(((BM4-Settle)/365)/Sv_tau2)-EXP(-((BM4-Settle)/365)/Sv_tau2))) | DX4: =IF(F4="",0,($C4/2+IF(1=$D4,100,0))*EXP(-BO4*((F4-Settle)/365))) -> 102.24107 | DY4: =IF(G4="",0,($C4/2+IF(2=$D4,100,0))*EXP(-BP4*((G4-Settle)/365))) -> 0 | DZ4: =IF(H4="",0,($C4/2+IF(3=$D4,100,0))*EXP(-BQ4*((H4-Settle)/365))) -> 0 | EA4: =IF(I4="",0,($C4/2+IF(4=$D4,100,0))*EXP(-BR4*((I4-Settle)/365))) -> 0 | EB4: =IF(J4="",0,($C4/2+IF(5=$D4,100,0))*EXP(-BS4*((J4-Settle)/365))) -> 0 | EC4: =IF(K4="",0,($C4/2+IF(6=$D4,100,0))*EXP(-BT4*((K4-Settle)/365))) -> 0 | ED4: =IF(L4="",0,($C4/2+IF(7=$D4,100,0))*EXP(-BU4*((L4-Settle)/365))) -> 0 | EE4: =IF(M4="",0,($C4/2+IF(8=$D4,100,0))*EXP(-BV4*((M4-Settle)/365))) -> 0 | EF4: =IF(N4="",0,($C4/2+IF(9=$D4,100,0))*EXP(-BW4*((N4-Settle)/365))) -> 0 | EG4: =IF(O4="",0,($C4/2+IF(10=$D4,100,0))*EXP(-BX4*((O4-Settle)/365))) -> 0 | EH4: =IF(P4="",0,($C4/2+IF(11=$D4,100,0))*EXP(-BY4*((P4-Settle)/365))) -> 0 | EI4: =IF(Q4="",0,($C4/2+IF(12=$D4,100,0))*EXP(-BZ4*((Q4-Settle)/365))) -> 0 | EJ4: =IF(R4="",0,($C4/2+IF(13=$D4,100,0))*EXP(-CA4*((R4-Settle)/365))) -> 0 | EK4: =IF(S4="",0,($C4/2+IF(14=$D4,100,0))*EXP(-CB4*((S4-Settle)/365))) -> 0 | EL4: =IF(T4="",0,($C4/2+IF(15=$D4,100,0))*EXP(-CC4*((T4-Settle)/365))) -> 0 | EM4: =IF(U4="",0,($C4/2+IF(16=$D4,100,0))*EXP(-CD4*((U4-Settle)/365))) -> 0 | EN4: =IF(V4="",0,($C4/2+IF(17=$D4,100,0))*EXP(-CE4*((V4-Settle)/365))) -> 0 | EO4: =IF(W4="",0,($C4/2+IF(18=$D4,100,0))*EXP(-CF4*((W4-Settle)/365))) -> 0 | EP4: =IF(X4="",0,($C4/2+IF(19=$D4,100,0))*EXP(-CG4*((X4-Settle)/365))) -> 0 | EQ4: =IF(Y4="",0,($C4/2+IF(20=$D4,100,0))*EXP(-CH4*((Y4-Settle)/365))) -> 0 | ER4: =IF(Z4="",0,($C4/2+IF(21=$D4,100,0))*EXP(-CI4*((Z4-Settle)/365))) -> 0 | ES4: =IF(AA4="",0,($C4/2+IF(22=$D4,100,0))*EXP(-CJ4*((AA4-Settle)/365))) -> 0 | ET4: =IF(AB4="",0,($C4/2+IF(23=$D4,100,0))*EXP(-CK4*((AB4-Settle)/365))) -> 0 | EU4: =IF(AC4="",0,($C4/2+IF(24=$D4,100,0))*EXP(-CL4*((AC4-Settle)/365))) -> 0 | EV4: =IF(AD4="",0,($C4/2+IF(25=$D4,100,0))*EXP(-CM4*((AD4-Settle)/365))) -> 0 | EW4: =IF(AE4="",0,($C4/2+IF(26=$D4,100,0))*EXP(-CN4*((AE4-Settle)/365))) -> 0 | EX4: =IF(AF4="",0,($C4/2+IF(27=$D4,100,0))*EXP(-CO4*((AF4-Settle)/365))) -> 0 | EY4: =IF(AG4="",0,($C4/2+IF(28=$D4,100,0))*EXP(-CP4*((AG4-Settle)/365))) -> 0 | EZ4: =IF(AH4="",0,($C4/2+IF(29=$D4,100,0))*EXP(-CQ4*((AH4-Settle)/365))) -> 0 | FA4: =IF(AI4="",0,($C4/2+IF(30=$D4,100,0))*EXP(-CR4*((AI4-Settle)/365))) -> 0 | FB4: =IF(AJ4="",0,($C4/2+IF(31=$D4,100,0))*EXP(-CS4*((AJ4-Settle)/365))) -> 0 | FC4: =IF(AK4="",0,($C4/2+IF(32=$D4,100,0))*EXP(-CT4*((AK4-Settle)/365))) -> 0 | FD4: =IF(AL4="",0,($C4/2+IF(33=$D4,100,0))*EXP(-CU4*((AL4-Settle)/365))) -> 0 | FE4: =IF(AM4="",0,($C4/2+IF(34=$D4,100,0))*EXP(-CV4*((AM4-Settle)/365))) -> 0 | FF4: =IF(AN4="",0,($C4/2+IF(35=$D4,100,0))*EXP(-CW4*((AN4-Settle)/365))) -> 0 | FG4: =IF(AO4="",0,($C4/2+IF(36=$D4,100,0))*EXP(-CX4*((AO4-Settle)/365))) -> 0 | FH4: =IF(AP4="",0,($C4/2+IF(37=$D4,100,0))*EXP(-CY4*((AP4-Settle)/365))) -> 0 | FI4: =IF(AQ4="",0,($C4/2+IF(38=$D4,100,0))*EXP(-CZ4*((AQ4-Settle)/365))) -> 0 | FJ4: =IF(AR4="",0,($C4/2+IF(39=$D4,100,0))*EXP(-DA4*((AR4-Settle)/365))) -> 0 | FK4: =IF(AS4="",0,($C4/2+IF(40=$D4,100,0))*EXP(-DB4*((AS4-Settle)/365))) -> 0 | FL4: =IF(AT4="",0,($C4/2+IF(41=$D4,100,0))*EXP(-DC4*((AT4-Settle)/365))) -> 0 | FM4: =IF(AU4="",0,($C4/2+IF(42=$D4,100,0))*EXP(-DD4*((AU4-Settle)/365))) -> 0 | FN4: =IF(AV4="",0,($C4/2+IF(43=$D4,100,0))*EXP(-DE4*((AV4-Settle)/365))) -> 0 | FO4: =IF(AW4="",0,($C4/2+IF(44=$D4,100,0))*EXP(-DF4*((AW4-Settle)/365))) -> 0 | FP4: =IF(AX4="",0,($C4/2+IF(45=$D4,100,0))*EXP(-DG4*((AX4-Settle)/365))) -> 0 | FQ4: =IF(AY4="",0,($C4/2+IF(46=$D4,100,0))*EXP(-DH4*((AY4-Settle)/365))) -> 0 | FR4: =IF(AZ4="",0,($C4/2+IF(47=$D4,100,0))*EXP(-DI4*((AZ4-Settle)/365))) -> 0 | FS4: =IF(BA4="",0,($C4/2+IF(48=$D4,100,0))*EXP(-DJ4*((BA4-Settle)/365))) -> 0 | FT4: =IF(BB4="",0,($C4/2+IF(49=$D4,100,0))*EXP(-DK4*((BB4-Settle)/365))) -> 0 | FU4: =IF(BC4="",0,($C4/2+IF(50=$D4,100,0))*EXP(-DL4*((BC4-Settle)/365))) -> 0 | FV4: =IF(BD4="",0,($C4/2+IF(51=$D4,100,0))*EXP(-DM4*((BD4-Settle)/365))) -> 0 | FW4: =IF(BE4="",0,($C4/2+IF(52=$D4,100,0))*EXP(-DN4*((BE4-Settle)/365))) -> 0 | FX4: =IF(BF4="",0,($C4/2+IF(53=$D4,100,0))*EXP(-DO4*((BF4-Settle)/365))) -> 0 | FY4: =IF(BG4="",0,($C4/2+IF(54=$D4,100,0))*EXP(-DP4*((BG4-Settle)/365))) -> 0 | FZ4: =IF(BH4="",0,($C4/2+IF(55=$D4,100,0))*EXP(-DQ4*((BH4-Settle)/365))) -> 0 | GA4: =IF(BI4="",0,($C4/2+IF(56=$D4,100,0))*EXP(-DR4*((BI4-Settle)/365))) -> 0 | GB4: =IF(BJ4="",0,($C4/2+IF(57=$D4,100,0))*EXP(-DS4*((BJ4-Settle)/365))) -> 0 | GC4: =IF(BK4="",0,($C4/2+IF(58=$D4,100,0))*EXP(-DT4*((BK4-Settle)/365))) -> 0 | GD4: =IF(BL4="",0,($C4/2+IF(59=$D4,100,0))*EXP(-DU4*((BL4-Settle)/365))) -> 0 | GE4: =IF(BM4="",0,($C4/2+IF(60=$D4,100,0))*EXP(-DV4*((BM4-Settle)/365))) -> 0
A5: 2 | B5: =Bonds!B5 -> 46295 | C5: =Bonds!C5 -> 0.875 | D5: =Bonds!Q5 -> 1 | E5: =IF(DAY(B5)=DAY(EOMONTH(B5,0)),1,0) -> 1 | F5: =IF(1>$D5,"",IF($E5=1,EOMONTH(EDATE(Bonds!$I5,6*(1-1)),0),EDATE(Bonds!$I5,6*(1-1)))) -> 46295 | G5: =IF(2>$D5,"",IF($E5=1,EOMONTH(EDATE(Bonds!$I5,6*(2-1)),0),EDATE(Bonds!$I5,6*(2-1)))) | H5: =IF(3>$D5,"",IF($E5=1,EOMONTH(EDATE(Bonds!$I5,6*(3-1)),0),EDATE(Bonds!$I5,6*(3-1)))) | I5: =IF(4>$D5,"",IF($E5=1,EOMONTH(EDATE(Bonds!$I5,6*(4-1)),0),EDATE(Bonds!$I5,6*(4-1)))) | J5: =IF(5>$D5,"",IF($E5=1,EOMONTH(EDATE(Bonds!$I5,6*(5-1)),0),EDATE(Bonds!$I5,6*(5-1)))) | K5: =IF(6>$D5,"",IF($E5=1,EOMONTH(EDATE(Bonds!$I5,6*(6-1)),0),EDATE(Bonds!$I5,6*(6-1)))) | L5: =IF(7>$D5,"",IF($E5=1,EOMONTH(EDATE(Bonds!$I5,6*(7-1)),0),EDATE(Bonds!$I5,6*(7-1)))) | M5: =IF(8>$D5,"",IF($E5=1,EOMONTH(EDATE(Bonds!$I5,6*(8-1)),0),EDATE(Bonds!$I5,6*(8-1)))) | N5: =IF(9>$D5,"",IF($E5=1,EOMONTH(EDATE(Bonds!$I5,6*(9-1)),0),EDATE(Bonds!$I5,6*(9-1)))) | O5: =IF(10>$D5,"",IF($E5=1,EOMONTH(EDATE(Bonds!$I5,6*(10-1)),0),EDATE(Bonds!$I5,6*(10-1)))) | P5: =IF(11>$D5,"",IF($E5=1,EOMONTH(EDATE(Bonds!$I5,6*(11-1)),0),EDATE(Bonds!$I5,6*(11-1)))) | Q5: =IF(12>$D5,"",IF($E5=1,EOMONTH(EDATE(Bonds!$I5,6*(12-1)),0),EDATE(Bonds!$I5,6*(12-1)))) | R5: =IF(13>$D5,"",IF($E5=1,EOMONTH(EDATE(Bonds!$I5,6*(13-1)),0),EDATE(Bonds!$I5,6*(13-1)))) | S5: =IF(14>$D5,"",IF($E5=1,EOMONTH(EDATE(Bonds!$I5,6*(14-1)),0),EDATE(Bonds!$I5,6*(14-1)))) | T5: =IF(15>$D5,"",IF($E5=1,EOMONTH(EDATE(Bonds!$I5,6*(15-1)),0),EDATE(Bonds!$I5,6*(15-1)))) | U5: =IF(16>$D5,"",IF($E5=1,EOMONTH(EDATE(Bonds!$I5,6*(16-1)),0),EDATE(Bonds!$I5,6*(16-1)))) | V5: =IF(17>$D5,"",IF($E5=1,EOMONTH(EDATE(Bonds!$I5,6*(17-1)),0),EDATE(Bonds!$I5,6*(17-1)))) | W5: =IF(18>$D5,"",IF($E5=1,EOMONTH(EDATE(Bonds!$I5,6*(18-1)),0),EDATE(Bonds!$I5,6*(18-1)))) | X5: =IF(19>$D5,"",IF($E5=1,EOMONTH(EDATE(Bonds!$I5,6*(19-1)),0),EDATE(Bonds!$I5,6*(19-1)))) | Y5: =IF(20>$D5,"",IF($E5=1,EOMONTH(EDATE(Bonds!$I5,6*(20-1)),0),EDATE(Bonds!$I5,6*(20-1)))) | Z5: =IF(21>$D5,"",IF($E5=1,EOMONTH(EDATE(Bonds!$I5,6*(21-1)),0),EDATE(Bonds!$I5,6*(21-1)))) | AA5: =IF(22>$D5,"",IF($E5=1,EOMONTH(EDATE(Bonds!$I5,6*(22-1)),0),EDATE(Bonds!$I5,6*(22-1)))) | AB5: =IF(23>$D5,"",IF($E5=1,EOMONTH(EDATE(Bonds!$I5,6*(23-1)),0),EDATE(Bonds!$I5,6*(23-1)))) | AC5: =IF(24>$D5,"",IF($E5=1,EOMONTH(EDATE(Bonds!$I5,6*(24-1)),0),EDATE(Bonds!$I5,6*(24-1)))) | AD5: =IF(25>$D5,"",IF($E5=1,EOMONTH(EDATE(Bonds!$I5,6*(25-1)),0),EDATE(Bonds!$I5,6*(25-1)))) | AE5: =IF(26>$D5,"",IF($E5=1,EOMONTH(EDATE(Bonds!$I5,6*(26-1)),0),EDATE(Bonds!$I5,6*(26-1)))) | AF5: =IF(27>$D5,"",IF($E5=1,EOMONTH(EDATE(Bonds!$I5,6*(27-1)),0),EDATE(Bonds!$I5,6*(27-1)))) | AG5: =IF(28>$D5,"",IF($E5=1,EOMONTH(EDATE(Bonds!$I5,6*(28-1)),0),EDATE(Bonds!$I5,6*(28-1)))) | AH5: =IF(29>$D5,"",IF($E5=1,EOMONTH(EDATE(Bonds!$I5,6*(29-1)),0),EDATE(Bonds!$I5,6*(29-1)))) | AI5: =IF(30>$D5,"",IF($E5=1,EOMONTH(EDATE(Bonds!$I5,6*(30-1)),0),EDATE(Bonds!$I5,6*(30-1)))) | AJ5: =IF(31>$D5,"",IF($E5=1,EOMONTH(EDATE(Bonds!$I5,6*(31-1)),0),EDATE(Bonds!$I5,6*(31-1)))) | AK5: =IF(32>$D5,"",IF($E5=1,EOMONTH(EDATE(Bonds!$I5,6*(32-1)),0),EDATE(Bonds!$I5,6*(32-1)))) | AL5: =IF(33>$D5,"",IF($E5=1,EOMONTH(EDATE(Bonds!$I5,6*(33-1)),0),EDATE(Bonds!$I5,6*(33-1)))) | AM5: =IF(34>$D5,"",IF($E5=1,EOMONTH(EDATE(Bonds!$I5,6*(34-1)),0),EDATE(Bonds!$I5,6*(34-1)))) | AN5: =IF(35>$D5,"",IF($E5=1,EOMONTH(EDATE(Bonds!$I5,6*(35-1)),0),EDATE(Bonds!$I5,6*(35-1)))) | AO5: =IF(36>$D5,"",IF($E5=1,EOMONTH(EDATE(Bonds!$I5,6*(36-1)),0),EDATE(Bonds!$I5,6*(36-1)))) | AP5: =IF(37>$D5,"",IF($E5=1,EOMONTH(EDATE(Bonds!$I5,6*(37-1)),0),EDATE(Bonds!$I5,6*(37-1)))) | AQ5: =IF(38>$D5,"",IF($E5=1,EOMONTH(EDATE(Bonds!$I5,6*(38-1)),0),EDATE(Bonds!$I5,6*(38-1)))) | AR5: =IF(39>$D5,"",IF($E5=1,EOMONTH(EDATE(Bonds!$I5,6*(39-1)),0),EDATE(Bonds!$I5,6*(39-1)))) | AS5: =IF(40>$D5,"",IF($E5=1,EOMONTH(EDATE(Bonds!$I5,6*(40-1)),0),EDATE(Bonds!$I5,6*(40-1)))) | AT5: =IF(41>$D5,"",IF($E5=1,EOMONTH(EDATE(Bonds!$I5,6*(41-1)),0),EDATE(Bonds!$I5,6*(41-1)))) | AU5: =IF(42>$D5,"",IF($E5=1,EOMONTH(EDATE(Bonds!$I5,6*(42-1)),0),EDATE(Bonds!$I5,6*(42-1)))) | AV5: =IF(43>$D5,"",IF($E5=1,EOMONTH(EDATE(Bonds!$I5,6*(43-1)),0),EDATE(Bonds!$I5,6*(43-1)))) | AW5: =IF(44>$D5,"",IF($E5=1,EOMONTH(EDATE(Bonds!$I5,6*(44-1)),0),EDATE(Bonds!$I5,6*(44-1)))) | AX5: =IF(45>$D5,"",IF($E5=1,EOMONTH(EDATE(Bonds!$I5,6*(45-1)),0),EDATE(Bonds!$I5,6*(45-1)))) | AY5: =IF(46>$D5,"",IF($E5=1,EOMONTH(EDATE(Bonds!$I5,6*(46-1)),0),EDATE(Bonds!$I5,6*(46-1)))) | AZ5: =IF(47>$D5,"",IF($E5=1,EOMONTH(EDATE(Bonds!$I5,6*(47-1)),0),EDATE(Bonds!$I5,6*(47-1)))) | BA5: =IF(48>$D5,"",IF($E5=1,EOMONTH(EDATE(Bonds!$I5,6*(48-1)),0),EDATE(Bonds!$I5,6*(48-1)))) | BB5: =IF(49>$D5,"",IF($E5=1,EOMONTH(EDATE(Bonds!$I5,6*(49-1)),0),EDATE(Bonds!$I5,6*(49-1)))) | BC5: =IF(50>$D5,"",IF($E5=1,EOMONTH(EDATE(Bonds!$I5,6*(50-1)),0),EDATE(Bonds!$I5,6*(50-1)))) | BD5: =IF(51>$D5,"",IF($E5=1,EOMONTH(EDATE(Bonds!$I5,6*(51-1)),0),EDATE(Bonds!$I5,6*(51-1)))) | BE5: =IF(52>$D5,"",IF($E5=1,EOMONTH(EDATE(Bonds!$I5,6*(52-1)),0),EDATE(Bonds!$I5,6*(52-1)))) | BF5: =IF(53>$D5,"",IF($E5=1,EOMONTH(EDATE(Bonds!$I5,6*(53-1)),0),EDATE(Bonds!$I5,6*(53-1)))) | BG5: =IF(54>$D5,"",IF($E5=1,EOMONTH(EDATE(Bonds!$I5,6*(54-1)),0),EDATE(Bonds!$I5,6*(54-1)))) | BH5: =IF(55>$D5,"",IF($E5=1,EOMONTH(EDATE(Bonds!$I5,6*(55-1)),0),EDATE(Bonds!$I5,6*(55-1)))) | BI5: =IF(56>$D5,"",IF($E5=1,EOMONTH(EDATE(Bonds!$I5,6*(56-1)),0),EDATE(Bonds!$I5,6*(56-1)))) | BJ5: =IF(57>$D5,"",IF($E5=1,EOMONTH(EDATE(Bonds!$I5,6*(57-1)),0),EDATE(Bonds!$I5,6*(57-1)))) | BK5: =IF(58>$D5,"",IF($E5=1,EOMONTH(EDATE(Bonds!$I5,6*(58-1)),0),EDATE(Bonds!$I5,6*(58-1)))) | BL5: =IF(59>$D5,"",IF($E5=1,EOMONTH(EDATE(Bonds!$I5,6*(59-1)),0),EDATE(Bonds!$I5,6*(59-1)))) | BM5: =IF(60>$D5,"",IF($E5=1,EOMONTH(EDATE(Bonds!$I5,6*(60-1)),0),EDATE(Bonds!$I5,6*(60-1)))) | BO5: =IF(F5="","",Sv_beta0+Sv_beta1*(1-EXP(-((F5-Settle)/365)/Sv_tau1))/(((F5-Settle)/365)/Sv_tau1)+Sv_beta2*((1-EXP(-((F5-Settle)/365)/Sv_tau1))/(((F5-Settle)/365)/Sv_tau1)-EXP(-((F5-Settle)/365)/Sv_tau1))+Sv_beta3*((1-EXP(-((F5-Settle)/365)/Sv_tau2))/(((F5-Settle)/365)/Sv_tau2)-EXP(-((F5-Settle)/365)/Sv_tau2))) -> 0.036715304 | BP5: =IF(G5="","",Sv_beta0+Sv_beta1*(1-EXP(-((G5-Settle)/365)/Sv_tau1))/(((G5-Settle)/365)/Sv_tau1)+Sv_beta2*((1-EXP(-((G5-Settle)/365)/Sv_tau1))/(((G5-Settle)/365)/Sv_tau1)-EXP(-((G5-Settle)/365)/Sv_tau1))+Sv_beta3*((1-EXP(-((G5-Settle)/365)/Sv_tau2))/(((G5-Settle)/365)/Sv_tau2)-EXP(-((G5-Settle)/365)/Sv_tau2))) | BQ5: =IF(H5="","",Sv_beta0+Sv_beta1*(1-EXP(-((H5-Settle)/365)/Sv_tau1))/(((H5-Settle)/365)/Sv_tau1)+Sv_beta2*((1-EXP(-((H5-Settle)/365)/Sv_tau1))/(((H5-Settle)/365)/Sv_tau1)-EXP(-((H5-Settle)/365)/Sv_tau1))+Sv_beta3*((1-EXP(-((H5-Settle)/365)/Sv_tau2))/(((H5-Settle)/365)/Sv_tau2)-EXP(-((H5-Settle)/365)/Sv_tau2))) | BR5: =IF(I5="","",Sv_beta0+Sv_beta1*(1-EXP(-((I5-Settle)/365)/Sv_tau1))/(((I5-Settle)/365)/Sv_tau1)+Sv_beta2*((1-EXP(-((I5-Settle)/365)/Sv_tau1))/(((I5-Settle)/365)/Sv_tau1)-EXP(-((I5-Settle)/365)/Sv_tau1))+Sv_beta3*((1-EXP(-((I5-Settle)/365)/Sv_tau2))/(((I5-Settle)/365)/Sv_tau2)-EXP(-((I5-Settle)/365)/Sv_tau2))) | BS5: =IF(J5="","",Sv_beta0+Sv_beta1*(1-EXP(-((J5-Settle)/365)/Sv_tau1))/(((J5-Settle)/365)/Sv_tau1)+Sv_beta2*((1-EXP(-((J5-Settle)/365)/Sv_tau1))/(((J5-Settle)/365)/Sv_tau1)-EXP(-((J5-Settle)/365)/Sv_tau1))+Sv_beta3*((1-EXP(-((J5-Settle)/365)/Sv_tau2))/(((J5-Settle)/365)/Sv_tau2)-EXP(-((J5-Settle)/365)/Sv_tau2))) | BT5: =IF(K5="","",Sv_beta0+Sv_beta1*(1-EXP(-((K5-Settle)/365)/Sv_tau1))/(((K5-Settle)/365)/Sv_tau1)+Sv_beta2*((1-EXP(-((K5-Settle)/365)/Sv_tau1))/(((K5-Settle)/365)/Sv_tau1)-EXP(-((K5-Settle)/365)/Sv_tau1))+Sv_beta3*((1-EXP(-((K5-Settle)/365)/Sv_tau2))/(((K5-Settle)/365)/Sv_tau2)-EXP(-((K5-Settle)/365)/Sv_tau2))) | BU5: =IF(L5="","",Sv_beta0+Sv_beta1*(1-EXP(-((L5-Settle)/365)/Sv_tau1))/(((L5-Settle)/365)/Sv_tau1)+Sv_beta2*((1-EXP(-((L5-Settle)/365)/Sv_tau1))/(((L5-Settle)/365)/Sv_tau1)-EXP(-((L5-Settle)/365)/Sv_tau1))+Sv_beta3*((1-EXP(-((L5-Settle)/365)/Sv_tau2))/(((L5-Settle)/365)/Sv_tau2)-EXP(-((L5-Settle)/365)/Sv_tau2))) | BV5: =IF(M5="","",Sv_beta0+Sv_beta1*(1-EXP(-((M5-Settle)/365)/Sv_tau1))/(((M5-Settle)/365)/Sv_tau1)+Sv_beta2*((1-EXP(-((M5-Settle)/365)/Sv_tau1))/(((M5-Settle)/365)/Sv_tau1)-EXP(-((M5-Settle)/365)/Sv_tau1))+Sv_beta3*((1-EXP(-((M5-Settle)/365)/Sv_tau2))/(((M5-Settle)/365)/Sv_tau2)-EXP(-((M5-Settle)/365)/Sv_tau2))) | ... DV5: =IF(BM5="","",Sv_beta0+Sv_beta1*(1-EXP(-((BM5-Settle)/365)/Sv_tau1))/(((BM5-Settle)/365)/Sv_tau1)+Sv_beta2*((1-EXP(-((BM5-Settle)/365)/Sv_tau1))/(((BM5-Settle)/365)/Sv_tau1)-EXP(-((BM5-Settle)/365)/Sv_tau1))+Sv_beta3*((1-EXP(-((BM5-Settle)/365)/Sv_tau2))/(((BM5-Settle)/365)/Sv_tau2)-EXP(-((BM5-Settle)/365)/Sv_tau2))) | DX5: =IF(F5="",0,($C5/2+IF(1=$D5,100,0))*EXP(-BO5*((F5-Settle)/365))) -> 100.21548 | DY5: =IF(G5="",0,($C5/2+IF(2=$D5,100,0))*EXP(-BP5*((G5-Settle)/365))) -> 0 | DZ5: =IF(H5="",0,($C5/2+IF(3=$D5,100,0))*EXP(-BQ5*((H5-Settle)/365))) -> 0 | EA5: =IF(I5="",0,($C5/2+IF(4=$D5,100,0))*EXP(-BR5*((I5-Settle)/365))) -> 0 | EB5: =IF(J5="",0,($C5/2+IF(5=$D5,100,0))*EXP(-BS5*((J5-Settle)/365))) -> 0 | EC5: =IF(K5="",0,($C5/2+IF(6=$D5,100,0))*EXP(-BT5*((K5-Settle)/365))) -> 0 | ED5: =IF(L5="",0,($C5/2+IF(7=$D5,100,0))*EXP(-BU5*((L5-Settle)/365))) -> 0 | EE5: =IF(M5="",0,($C5/2+IF(8=$D5,100,0))*EXP(-BV5*((M5-Settle)/365))) -> 0 | EF5: =IF(N5="",0,($C5/2+IF(9=$D5,100,0))*EXP(-BW5*((N5-Settle)/365))) -> 0 | EG5: =IF(O5="",0,($C5/2+IF(10=$D5,100,0))*EXP(-BX5*((O5-Settle)/365))) -> 0 | EH5: =IF(P5="",0,($C5/2+IF(11=$D5,100,0))*EXP(-BY5*((P5-Settle)/365))) -> 0 | EI5: =IF(Q5="",0,($C5/2+IF(12=$D5,100,0))*EXP(-BZ5*((Q5-Settle)/365))) -> 0 | EJ5: =IF(R5="",0,($C5/2+IF(13=$D5,100,0))*EXP(-CA5*((R5-Settle)/365))) -> 0 | EK5: =IF(S5="",0,($C5/2+IF(14=$D5,100,0))*EXP(-CB5*((S5-Settle)/365))) -> 0 | EL5: =IF(T5="",0,($C5/2+IF(15=$D5,100,0))*EXP(-CC5*((T5-Settle)/365))) -> 0 | EM5: =IF(U5="",0,($C5/2+IF(16=$D5,100,0))*EXP(-CD5*((U5-Settle)/365))) -> 0 | EN5: =IF(V5="",0,($C5/2+IF(17=$D5,100,0))*EXP(-CE5*((V5-Settle)/365))) -> 0 | EO5: =IF(W5="",0,($C5/2+IF(18=$D5,100,0))*EXP(-CF5*((W5-Settle)/365))) -> 0 | EP5: =IF(X5="",0,($C5/2+IF(19=$D5,100,0))*EXP(-CG5*((X5-Settle)/365))) -> 0 | EQ5: =IF(Y5="",0,($C5/2+IF(20=$D5,100,0))*EXP(-CH5*((Y5-Settle)/365))) -> 0 | ER5: =IF(Z5="",0,($C5/2+IF(21=$D5,100,0))*EXP(-CI5*((Z5-Settle)/365))) -> 0 | ES5: =IF(AA5="",0,($C5/2+IF(22=$D5,100,0))*EXP(-CJ5*((AA5-Settle)/365))) -> 0 | ET5: =IF(AB5="",0,($C5/2+IF(23=$D5,100,0))*EXP(-CK5*((AB5-Settle)/365))) -> 0 | EU5: =IF(AC5="",0,($C5/2+IF(24=$D5,100,0))*EXP(-CL5*((AC5-Settle)/365))) -> 0 | EV5: =IF(AD5="",0,($C5/2+IF(25=$D5,100,0))*EXP(-CM5*((AD5-Settle)/365))) -> 0 | EW5: =IF(AE5="",0,($C5/2+IF(26=$D5,100,0))*EXP(-CN5*((AE5-Settle)/365))) -> 0 | EX5: =IF(AF5="",0,($C5/2+IF(27=$D5,100,0))*EXP(-CO5*((AF5-Settle)/365))) -> 0 | EY5: =IF(AG5="",0,($C5/2+IF(28=$D5,100,0))*EXP(-CP5*((AG5-Settle)/365))) -> 0 | EZ5: =IF(AH5="",0,($C5/2+IF(29=$D5,100,0))*EXP(-CQ5*((AH5-Settle)/365))) -> 0 | FA5: =IF(AI5="",0,($C5/2+IF(30=$D5,100,0))*EXP(-CR5*((AI5-Settle)/365))) -> 0 | FB5: =IF(AJ5="",0,($C5/2+IF(31=$D5,100,0))*EXP(-CS5*((AJ5-Settle)/365))) -> 0 | FC5: =IF(AK5="",0,($C5/2+IF(32=$D5,100,0))*EXP(-CT5*((AK5-Settle)/365))) -> 0 | FD5: =IF(AL5="",0,($C5/2+IF(33=$D5,100,0))*EXP(-CU5*((AL5-Settle)/365))) -> 0 | FE5: =IF(AM5="",0,($C5/2+IF(34=$D5,100,0))*EXP(-CV5*((AM5-Settle)/365))) -> 0 | FF5: =IF(AN5="",0,($C5/2+IF(35=$D5,100,0))*EXP(-CW5*((AN5-Settle)/365))) -> 0 | FG5: =IF(AO5="",0,($C5/2+IF(36=$D5,100,0))*EXP(-CX5*((AO5-Settle)/365))) -> 0 | FH5: =IF(AP5="",0,($C5/2+IF(37=$D5,100,0))*EXP(-CY5*((AP5-Settle)/365))) -> 0 | FI5: =IF(AQ5="",0,($C5/2+IF(38=$D5,100,0))*EXP(-CZ5*((AQ5-Settle)/365))) -> 0 | FJ5: =IF(AR5="",0,($C5/2+IF(39=$D5,100,0))*EXP(-DA5*((AR5-Settle)/365))) -> 0 | FK5: =IF(AS5="",0,($C5/2+IF(40=$D5,100,0))*EXP(-DB5*((AS5-Settle)/365))) -> 0 | FL5: =IF(AT5="",0,($C5/2+IF(41=$D5,100,0))*EXP(-DC5*((AT5-Settle)/365))) -> 0 | FM5: =IF(AU5="",0,($C5/2+IF(42=$D5,100,0))*EXP(-DD5*((AU5-Settle)/365))) -> 0 | FN5: =IF(AV5="",0,($C5/2+IF(43=$D5,100,0))*EXP(-DE5*((AV5-Settle)/365))) -> 0 | FO5: =IF(AW5="",0,($C5/2+IF(44=$D5,100,0))*EXP(-DF5*((AW5-Settle)/365))) -> 0 | FP5: =IF(AX5="",0,($C5/2+IF(45=$D5,100,0))*EXP(-DG5*((AX5-Settle)/365))) -> 0 | FQ5: =IF(AY5="",0,($C5/2+IF(46=$D5,100,0))*EXP(-DH5*((AY5-Settle)/365))) -> 0 | FR5: =IF(AZ5="",0,($C5/2+IF(47=$D5,100,0))*EXP(-DI5*((AZ5-Settle)/365))) -> 0 | FS5: =IF(BA5="",0,($C5/2+IF(48=$D5,100,0))*EXP(-DJ5*((BA5-Settle)/365))) -> 0 | FT5: =IF(BB5="",0,($C5/2+IF(49=$D5,100,0))*EXP(-DK5*((BB5-Settle)/365))) -> 0 | FU5: =IF(BC5="",0,($C5/2+IF(50=$D5,100,0))*EXP(-DL5*((BC5-Settle)/365))) -> 0 | FV5: =IF(BD5="",0,($C5/2+IF(51=$D5,100,0))*EXP(-DM5*((BD5-Settle)/365))) -> 0 | FW5: =IF(BE5="",0,($C5/2+IF(52=$D5,100,0))*EXP(-DN5*((BE5-Settle)/365))) -> 0 | FX5: =IF(BF5="",0,($C5/2+IF(53=$D5,100,0))*EXP(-DO5*((BF5-Settle)/365))) -> 0 | FY5: =IF(BG5="",0,($C5/2+IF(54=$D5,100,0))*EXP(-DP5*((BG5-Settle)/365))) -> 0 | FZ5: =IF(BH5="",0,($C5/2+IF(55=$D5,100,0))*EXP(-DQ5*((BH5-Settle)/365))) -> 0 | GA5: =IF(BI5="",0,($C5/2+IF(56=$D5,100,0))*EXP(-DR5*((BI5-Settle)/365))) -> 0 | GB5: =IF(BJ5="",0,($C5/2+IF(57=$D5,100,0))*EXP(-DS5*((BJ5-Settle)/365))) -> 0 | GC5: =IF(BK5="",0,($C5/2+IF(58=$D5,100,0))*EXP(-DT5*((BK5-Settle)/365))) -> 0 | GD5: =IF(BL5="",0,($C5/2+IF(59=$D5,100,0))*EXP(-DU5*((BL5-Settle)/365))) -> 0 | GE5: =IF(BM5="",0,($C5/2+IF(60=$D5,100,0))*EXP(-DV5*((BM5-Settle)/365))) -> 0
A6: 3 | B6: =Bonds!B6 -> 46295 | C6: =Bonds!C6 -> 1.625 | D6: =Bonds!Q6 -> 1 | E6: =IF(DAY(B6)=DAY(EOMONTH(B6,0)),1,0) -> 1 | F6: =IF(1>$D6,"",IF($E6=1,EOMONTH(EDATE(Bonds!$I6,6*(1-1)),0),EDATE(Bonds!$I6,6*(1-1)))) -> 46295 | G6: =IF(2>$D6,"",IF($E6=1,EOMONTH(EDATE(Bonds!$I6,6*(2-1)),0),EDATE(Bonds!$I6,6*(2-1)))) | H6: =IF(3>$D6,"",IF($E6=1,EOMONTH(EDATE(Bonds!$I6,6*(3-1)),0),EDATE(Bonds!$I6,6*(3-1)))) | I6: =IF(4>$D6,"",IF($E6=1,EOMONTH(EDATE(Bonds!$I6,6*(4-1)),0),EDATE(Bonds!$I6,6*(4-1)))) | J6: =IF(5>$D6,"",IF($E6=1,EOMONTH(EDATE(Bonds!$I6,6*(5-1)),0),EDATE(Bonds!$I6,6*(5-1)))) | K6: =IF(6>$D6,"",IF($E6=1,EOMONTH(EDATE(Bonds!$I6,6*(6-1)),0),EDATE(Bonds!$I6,6*(6-1)))) | L6: =IF(7>$D6,"",IF($E6=1,EOMONTH(EDATE(Bonds!$I6,6*(7-1)),0),EDATE(Bonds!$I6,6*(7-1)))) | M6: =IF(8>$D6,"",IF($E6=1,EOMONTH(EDATE(Bonds!$I6,6*(8-1)),0),EDATE(Bonds!$I6,6*(8-1)))) | N6: =IF(9>$D6,"",IF($E6=1,EOMONTH(EDATE(Bonds!$I6,6*(9-1)),0),EDATE(Bonds!$I6,6*(9-1)))) | O6: =IF(10>$D6,"",IF($E6=1,EOMONTH(EDATE(Bonds!$I6,6*(10-1)),0),EDATE(Bonds!$I6,6*(10-1)))) | P6: =IF(11>$D6,"",IF($E6=1,EOMONTH(EDATE(Bonds!$I6,6*(11-1)),0),EDATE(Bonds!$I6,6*(11-1)))) | Q6: =IF(12>$D6,"",IF($E6=1,EOMONTH(EDATE(Bonds!$I6,6*(12-1)),0),EDATE(Bonds!$I6,6*(12-1)))) | R6: =IF(13>$D6,"",IF($E6=1,EOMONTH(EDATE(Bonds!$I6,6*(13-1)),0),EDATE(Bonds!$I6,6*(13-1)))) | S6: =IF(14>$D6,"",IF($E6=1,EOMONTH(EDATE(Bonds!$I6,6*(14-1)),0),EDATE(Bonds!$I6,6*(14-1)))) | T6: =IF(15>$D6,"",IF($E6=1,EOMONTH(EDATE(Bonds!$I6,6*(15-1)),0),EDATE(Bonds!$I6,6*(15-1)))) | U6: =IF(16>$D6,"",IF($E6=1,EOMONTH(EDATE(Bonds!$I6,6*(16-1)),0),EDATE(Bonds!$I6,6*(16-1)))) | V6: =IF(17>$D6,"",IF($E6=1,EOMONTH(EDATE(Bonds!$I6,6*(17-1)),0),EDATE(Bonds!$I6,6*(17-1)))) | W6: =IF(18>$D6,"",IF($E6=1,EOMONTH(EDATE(Bonds!$I6,6*(18-1)),0),EDATE(Bonds!$I6,6*(18-1)))) | X6: =IF(19>$D6,"",IF($E6=1,EOMONTH(EDATE(Bonds!$I6,6*(19-1)),0),EDATE(Bonds!$I6,6*(19-1)))) | Y6: =IF(20>$D6,"",IF($E6=1,EOMONTH(EDATE(Bonds!$I6,6*(20-1)),0),EDATE(Bonds!$I6,6*(20-1)))) | Z6: =IF(21>$D6,"",IF($E6=1,EOMONTH(EDATE(Bonds!$I6,6*(21-1)),0),EDATE(Bonds!$I6,6*(21-1)))) | AA6: =IF(22>$D6,"",IF($E6=1,EOMONTH(EDATE(Bonds!$I6,6*(22-1)),0),EDATE(Bonds!$I6,6*(22-1)))) | AB6: =IF(23>$D6,"",IF($E6=1,EOMONTH(EDATE(Bonds!$I6,6*(23-1)),0),EDATE(Bonds!$I6,6*(23-1)))) | AC6: =IF(24>$D6,"",IF($E6=1,EOMONTH(EDATE(Bonds!$I6,6*(24-1)),0),EDATE(Bonds!$I6,6*(24-1)))) | AD6: =IF(25>$D6,"",IF($E6=1,EOMONTH(EDATE(Bonds!$I6,6*(25-1)),0),EDATE(Bonds!$I6,6*(25-1)))) | AE6: =IF(26>$D6,"",IF($E6=1,EOMONTH(EDATE(Bonds!$I6,6*(26-1)),0),EDATE(Bonds!$I6,6*(26-1)))) | AF6: =IF(27>$D6,"",IF($E6=1,EOMONTH(EDATE(Bonds!$I6,6*(27-1)),0),EDATE(Bonds!$I6,6*(27-1)))) | AG6: =IF(28>$D6,"",IF($E6=1,EOMONTH(EDATE(Bonds!$I6,6*(28-1)),0),EDATE(Bonds!$I6,6*(28-1)))) | AH6: =IF(29>$D6,"",IF($E6=1,EOMONTH(EDATE(Bonds!$I6,6*(29-1)),0),EDATE(Bonds!$I6,6*(29-1)))) | AI6: =IF(30>$D6,"",IF($E6=1,EOMONTH(EDATE(Bonds!$I6,6*(30-1)),0),EDATE(Bonds!$I6,6*(30-1)))) | AJ6: =IF(31>$D6,"",IF($E6=1,EOMONTH(EDATE(Bonds!$I6,6*(31-1)),0),EDATE(Bonds!$I6,6*(31-1)))) | AK6: =IF(32>$D6,"",IF($E6=1,EOMONTH(EDATE(Bonds!$I6,6*(32-1)),0),EDATE(Bonds!$I6,6*(32-1)))) | AL6: =IF(33>$D6,"",IF($E6=1,EOMONTH(EDATE(Bonds!$I6,6*(33-1)),0),EDATE(Bonds!$I6,6*(33-1)))) | AM6: =IF(34>$D6,"",IF($E6=1,EOMONTH(EDATE(Bonds!$I6,6*(34-1)),0),EDATE(Bonds!$I6,6*(34-1)))) | AN6: =IF(35>$D6,"",IF($E6=1,EOMONTH(EDATE(Bonds!$I6,6*(35-1)),0),EDATE(Bonds!$I6,6*(35-1)))) | AO6: =IF(36>$D6,"",IF($E6=1,EOMONTH(EDATE(Bonds!$I6,6*(36-1)),0),EDATE(Bonds!$I6,6*(36-1)))) | AP6: =IF(37>$D6,"",IF($E6=1,EOMONTH(EDATE(Bonds!$I6,6*(37-1)),0),EDATE(Bonds!$I6,6*(37-1)))) | AQ6: =IF(38>$D6,"",IF($E6=1,EOMONTH(EDATE(Bonds!$I6,6*(38-1)),0),EDATE(Bonds!$I6,6*(38-1)))) | AR6: =IF(39>$D6,"",IF($E6=1,EOMONTH(EDATE(Bonds!$I6,6*(39-1)),0),EDATE(Bonds!$I6,6*(39-1)))) | AS6: =IF(40>$D6,"",IF($E6=1,EOMONTH(EDATE(Bonds!$I6,6*(40-1)),0),EDATE(Bonds!$I6,6*(40-1)))) | AT6: =IF(41>$D6,"",IF($E6=1,EOMONTH(EDATE(Bonds!$I6,6*(41-1)),0),EDATE(Bonds!$I6,6*(41-1)))) | AU6: =IF(42>$D6,"",IF($E6=1,EOMONTH(EDATE(Bonds!$I6,6*(42-1)),0),EDATE(Bonds!$I6,6*(42-1)))) | AV6: =IF(43>$D6,"",IF($E6=1,EOMONTH(EDATE(Bonds!$I6,6*(43-1)),0),EDATE(Bonds!$I6,6*(43-1)))) | AW6: =IF(44>$D6,"",IF($E6=1,EOMONTH(EDATE(Bonds!$I6,6*(44-1)),0),EDATE(Bonds!$I6,6*(44-1)))) | AX6: =IF(45>$D6,"",IF($E6=1,EOMONTH(EDATE(Bonds!$I6,6*(45-1)),0),EDATE(Bonds!$I6,6*(45-1)))) | AY6: =IF(46>$D6,"",IF($E6=1,EOMONTH(EDATE(Bonds!$I6,6*(46-1)),0),EDATE(Bonds!$I6,6*(46-1)))) | AZ6: =IF(47>$D6,"",IF($E6=1,EOMONTH(EDATE(Bonds!$I6,6*(47-1)),0),EDATE(Bonds!$I6,6*(47-1)))) | BA6: =IF(48>$D6,"",IF($E6=1,EOMONTH(EDATE(Bonds!$I6,6*(48-1)),0),EDATE(Bonds!$I6,6*(48-1)))) | BB6: =IF(49>$D6,"",IF($E6=1,EOMONTH(EDATE(Bonds!$I6,6*(49-1)),0),EDATE(Bonds!$I6,6*(49-1)))) | BC6: =IF(50>$D6,"",IF($E6=1,EOMONTH(EDATE(Bonds!$I6,6*(50-1)),0),EDATE(Bonds!$I6,6*(50-1)))) | BD6: =IF(51>$D6,"",IF($E6=1,EOMONTH(EDATE(Bonds!$I6,6*(51-1)),0),EDATE(Bonds!$I6,6*(51-1)))) | BE6: =IF(52>$D6,"",IF($E6=1,EOMONTH(EDATE(Bonds!$I6,6*(52-1)),0),EDATE(Bonds!$I6,6*(52-1)))) | BF6: =IF(53>$D6,"",IF($E6=1,EOMONTH(EDATE(Bonds!$I6,6*(53-1)),0),EDATE(Bonds!$I6,6*(53-1)))) | BG6: =IF(54>$D6,"",IF($E6=1,EOMONTH(EDATE(Bonds!$I6,6*(54-1)),0),EDATE(Bonds!$I6,6*(54-1)))) | BH6: =IF(55>$D6,"",IF($E6=1,EOMONTH(EDATE(Bonds!$I6,6*(55-1)),0),EDATE(Bonds!$I6,6*(55-1)))) | BI6: =IF(56>$D6,"",IF($E6=1,EOMONTH(EDATE(Bonds!$I6,6*(56-1)),0),EDATE(Bonds!$I6,6*(56-1)))) | BJ6: =IF(57>$D6,"",IF($E6=1,EOMONTH(EDATE(Bonds!$I6,6*(57-1)),0),EDATE(Bonds!$I6,6*(57-1)))) | BK6: =IF(58>$D6,"",IF($E6=1,EOMONTH(EDATE(Bonds!$I6,6*(58-1)),0),EDATE(Bonds!$I6,6*(58-1)))) | BL6: =IF(59>$D6,"",IF($E6=1,EOMONTH(EDATE(Bonds!$I6,6*(59-1)),0),EDATE(Bonds!$I6,6*(59-1)))) | BM6: =IF(60>$D6,"",IF($E6=1,EOMONTH(EDATE(Bonds!$I6,6*(60-1)),0),EDATE(Bonds!$I6,6*(60-1)))) | BO6: =IF(F6="","",Sv_beta0+Sv_beta1*(1-EXP(-((F6-Settle)/365)/Sv_tau1))/(((F6-Settle)/365)/Sv_tau1)+Sv_beta2*((1-EXP(-((F6-Settle)/365)/Sv_tau1))/(((F6-Settle)/365)/Sv_tau1)-EXP(-((F6-Settle)/365)/Sv_tau1))+Sv_beta3*((1-EXP(-((F6-Settle)/365)/Sv_tau2))/(((F6-Settle)/365)/Sv_tau2)-EXP(-((F6-Settle)/365)/Sv_tau2))) -> 0.036715304 | BP6: =IF(G6="","",Sv_beta0+Sv_beta1*(1-EXP(-((G6-Settle)/365)/Sv_tau1))/(((G6-Settle)/365)/Sv_tau1)+Sv_beta2*((1-EXP(-((G6-Settle)/365)/Sv_tau1))/(((G6-Settle)/365)/Sv_tau1)-EXP(-((G6-Settle)/365)/Sv_tau1))+Sv_beta3*((1-EXP(-((G6-Settle)/365)/Sv_tau2))/(((G6-Settle)/365)/Sv_tau2)-EXP(-((G6-Settle)/365)/Sv_tau2))) | BQ6: =IF(H6="","",Sv_beta0+Sv_beta1*(1-EXP(-((H6-Settle)/365)/Sv_tau1))/(((H6-Settle)/365)/Sv_tau1)+Sv_beta2*((1-EXP(-((H6-Settle)/365)/Sv_tau1))/(((H6-Settle)/365)/Sv_tau1)-EXP(-((H6-Settle)/365)/Sv_tau1))+Sv_beta3*((1-EXP(-((H6-Settle)/365)/Sv_tau2))/(((H6-Settle)/365)/Sv_tau2)-EXP(-((H6-Settle)/365)/Sv_tau2))) | BR6: =IF(I6="","",Sv_beta0+Sv_beta1*(1-EXP(-((I6-Settle)/365)/Sv_tau1))/(((I6-Settle)/365)/Sv_tau1)+Sv_beta2*((1-EXP(-((I6-Settle)/365)/Sv_tau1))/(((I6-Settle)/365)/Sv_tau1)-EXP(-((I6-Settle)/365)/Sv_tau1))+Sv_beta3*((1-EXP(-((I6-Settle)/365)/Sv_tau2))/(((I6-Settle)/365)/Sv_tau2)-EXP(-((I6-Settle)/365)/Sv_tau2))) | BS6: =IF(J6="","",Sv_beta0+Sv_beta1*(1-EXP(-((J6-Settle)/365)/Sv_tau1))/(((J6-Settle)/365)/Sv_tau1)+Sv_beta2*((1-EXP(-((J6-Settle)/365)/Sv_tau1))/(((J6-Settle)/365)/Sv_tau1)-EXP(-((J6-Settle)/365)/Sv_tau1))+Sv_beta3*((1-EXP(-((J6-Settle)/365)/Sv_tau2))/(((J6-Settle)/365)/Sv_tau2)-EXP(-((J6-Settle)/365)/Sv_tau2))) | BT6: =IF(K6="","",Sv_beta0+Sv_beta1*(1-EXP(-((K6-Settle)/365)/Sv_tau1))/(((K6-Settle)/365)/Sv_tau1)+Sv_beta2*((1-EXP(-((K6-Settle)/365)/Sv_tau1))/(((K6-Settle)/365)/Sv_tau1)-EXP(-((K6-Settle)/365)/Sv_tau1))+Sv_beta3*((1-EXP(-((K6-Settle)/365)/Sv_tau2))/(((K6-Settle)/365)/Sv_tau2)-EXP(-((K6-Settle)/365)/Sv_tau2))) | BU6: =IF(L6="","",Sv_beta0+Sv_beta1*(1-EXP(-((L6-Settle)/365)/Sv_tau1))/(((L6-Settle)/365)/Sv_tau1)+Sv_beta2*((1-EXP(-((L6-Settle)/365)/Sv_tau1))/(((L6-Settle)/365)/Sv_tau1)-EXP(-((L6-Settle)/365)/Sv_tau1))+Sv_beta3*((1-EXP(-((L6-Settle)/365)/Sv_tau2))/(((L6-Settle)/365)/Sv_tau2)-EXP(-((L6-Settle)/365)/Sv_tau2))) | BV6: =IF(M6="","",Sv_beta0+Sv_beta1*(1-EXP(-((M6-Settle)/365)/Sv_tau1))/(((M6-Settle)/365)/Sv_tau1)+Sv_beta2*((1-EXP(-((M6-Settle)/365)/Sv_tau1))/(((M6-Settle)/365)/Sv_tau1)-EXP(-((M6-Settle)/365)/Sv_tau1))+Sv_beta3*((1-EXP(-((M6-Settle)/365)/Sv_tau2))/(((M6-Settle)/365)/Sv_tau2)-EXP(-((M6-Settle)/365)/Sv_tau2))) | ... DV6: =IF(BM6="","",Sv_beta0+Sv_beta1*(1-EXP(-((BM6-Settle)/365)/Sv_tau1))/(((BM6-Settle)/365)/Sv_tau1)+Sv_beta2*((1-EXP(-((BM6-Settle)/365)/Sv_tau1))/(((BM6-Settle)/365)/Sv_tau1)-EXP(-((BM6-Settle)/365)/Sv_tau1))+Sv_beta3*((1-EXP(-((BM6-Settle)/365)/Sv_tau2))/(((BM6-Settle)/365)/Sv_tau2)-EXP(-((BM6-Settle)/365)/Sv_tau2))) | DX6: =IF(F6="",0,($C6/2+IF(1=$D6,100,0))*EXP(-BO6*((F6-Settle)/365))) -> 100.58965 | DY6: =IF(G6="",0,($C6/2+IF(2=$D6,100,0))*EXP(-BP6*((G6-Settle)/365))) -> 0 | DZ6: =IF(H6="",0,($C6/2+IF(3=$D6,100,0))*EXP(-BQ6*((H6-Settle)/365))) -> 0 | EA6: =IF(I6="",0,($C6/2+IF(4=$D6,100,0))*EXP(-BR6*((I6-Settle)/365))) -> 0 | EB6: =IF(J6="",0,($C6/2+IF(5=$D6,100,0))*EXP(-BS6*((J6-Settle)/365))) -> 0 | EC6: =IF(K6="",0,($C6/2+IF(6=$D6,100,0))*EXP(-BT6*((K6-Settle)/365))) -> 0 | ED6: =IF(L6="",0,($C6/2+IF(7=$D6,100,0))*EXP(-BU6*((L6-Settle)/365))) -> 0 | EE6: =IF(M6="",0,($C6/2+IF(8=$D6,100,0))*EXP(-BV6*((M6-Settle)/365))) -> 0 | EF6: =IF(N6="",0,($C6/2+IF(9=$D6,100,0))*EXP(-BW6*((N6-Settle)/365))) -> 0 | EG6: =IF(O6="",0,($C6/2+IF(10=$D6,100,0))*EXP(-BX6*((O6-Settle)/365))) -> 0 | EH6: =IF(P6="",0,($C6/2+IF(11=$D6,100,0))*EXP(-BY6*((P6-Settle)/365))) -> 0 | EI6: =IF(Q6="",0,($C6/2+IF(12=$D6,100,0))*EXP(-BZ6*((Q6-Settle)/365))) -> 0 | EJ6: =IF(R6="",0,($C6/2+IF(13=$D6,100,0))*EXP(-CA6*((R6-Settle)/365))) -> 0 | EK6: =IF(S6="",0,($C6/2+IF(14=$D6,100,0))*EXP(-CB6*((S6-Settle)/365))) -> 0 | EL6: =IF(T6="",0,($C6/2+IF(15=$D6,100,0))*EXP(-CC6*((T6-Settle)/365))) -> 0 | EM6: =IF(U6="",0,($C6/2+IF(16=$D6,100,0))*EXP(-CD6*((U6-Settle)/365))) -> 0 | EN6: =IF(V6="",0,($C6/2+IF(17=$D6,100,0))*EXP(-CE6*((V6-Settle)/365))) -> 0 | EO6: =IF(W6="",0,($C6/2+IF(18=$D6,100,0))*EXP(-CF6*((W6-Settle)/365))) -> 0 | EP6: =IF(X6="",0,($C6/2+IF(19=$D6,100,0))*EXP(-CG6*((X6-Settle)/365))) -> 0 | EQ6: =IF(Y6="",0,($C6/2+IF(20=$D6,100,0))*EXP(-CH6*((Y6-Settle)/365))) -> 0 | ER6: =IF(Z6="",0,($C6/2+IF(21=$D6,100,0))*EXP(-CI6*((Z6-Settle)/365))) -> 0 | ES6: =IF(AA6="",0,($C6/2+IF(22=$D6,100,0))*EXP(-CJ6*((AA6-Settle)/365))) -> 0 | ET6: =IF(AB6="",0,($C6/2+IF(23=$D6,100,0))*EXP(-CK6*((AB6-Settle)/365))) -> 0 | EU6: =IF(AC6="",0,($C6/2+IF(24=$D6,100,0))*EXP(-CL6*((AC6-Settle)/365))) -> 0 | EV6: =IF(AD6="",0,($C6/2+IF(25=$D6,100,0))*EXP(-CM6*((AD6-Settle)/365))) -> 0 | EW6: =IF(AE6="",0,($C6/2+IF(26=$D6,100,0))*EXP(-CN6*((AE6-Settle)/365))) -> 0 | EX6: =IF(AF6="",0,($C6/2+IF(27=$D6,100,0))*EXP(-CO6*((AF6-Settle)/365))) -> 0 | EY6: =IF(AG6="",0,($C6/2+IF(28=$D6,100,0))*EXP(-CP6*((AG6-Settle)/365))) -> 0 | EZ6: =IF(AH6="",0,($C6/2+IF(29=$D6,100,0))*EXP(-CQ6*((AH6-Settle)/365))) -> 0 | FA6: =IF(AI6="",0,($C6/2+IF(30=$D6,100,0))*EXP(-CR6*((AI6-Settle)/365))) -> 0 | FB6: =IF(AJ6="",0,($C6/2+IF(31=$D6,100,0))*EXP(-CS6*((AJ6-Settle)/365))) -> 0 | FC6: =IF(AK6="",0,($C6/2+IF(32=$D6,100,0))*EXP(-CT6*((AK6-Settle)/365))) -> 0 | FD6: =IF(AL6="",0,($C6/2+IF(33=$D6,100,0))*EXP(-CU6*((AL6-Settle)/365))) -> 0 | FE6: =IF(AM6="",0,($C6/2+IF(34=$D6,100,0))*EXP(-CV6*((AM6-Settle)/365))) -> 0 | FF6: =IF(AN6="",0,($C6/2+IF(35=$D6,100,0))*EXP(-CW6*((AN6-Settle)/365))) -> 0 | FG6: =IF(AO6="",0,($C6/2+IF(36=$D6,100,0))*EXP(-CX6*((AO6-Settle)/365))) -> 0 | FH6: =IF(AP6="",0,($C6/2+IF(37=$D6,100,0))*EXP(-CY6*((AP6-Settle)/365))) -> 0 | FI6: =IF(AQ6="",0,($C6/2+IF(38=$D6,100,0))*EXP(-CZ6*((AQ6-Settle)/365))) -> 0 | FJ6: =IF(AR6="",0,($C6/2+IF(39=$D6,100,0))*EXP(-DA6*((AR6-Settle)/365))) -> 0 | FK6: =IF(AS6="",0,($C6/2+IF(40=$D6,100,0))*EXP(-DB6*((AS6-Settle)/365))) -> 0 | FL6: =IF(AT6="",0,($C6/2+IF(41=$D6,100,0))*EXP(-DC6*((AT6-Settle)/365))) -> 0 | FM6: =IF(AU6="",0,($C6/2+IF(42=$D6,100,0))*EXP(-DD6*((AU6-Settle)/365))) -> 0 | FN6: =IF(AV6="",0,($C6/2+IF(43=$D6,100,0))*EXP(-DE6*((AV6-Settle)/365))) -> 0 | FO6: =IF(AW6="",0,($C6/2+IF(44=$D6,100,0))*EXP(-DF6*((AW6-Settle)/365))) -> 0 | FP6: =IF(AX6="",0,($C6/2+IF(45=$D6,100,0))*EXP(-DG6*((AX6-Settle)/365))) -> 0 | FQ6: =IF(AY6="",0,($C6/2+IF(46=$D6,100,0))*EXP(-DH6*((AY6-Settle)/365))) -> 0 | FR6: =IF(AZ6="",0,($C6/2+IF(47=$D6,100,0))*EXP(-DI6*((AZ6-Settle)/365))) -> 0 | FS6: =IF(BA6="",0,($C6/2+IF(48=$D6,100,0))*EXP(-DJ6*((BA6-Settle)/365))) -> 0 | FT6: =IF(BB6="",0,($C6/2+IF(49=$D6,100,0))*EXP(-DK6*((BB6-Settle)/365))) -> 0 | FU6: =IF(BC6="",0,($C6/2+IF(50=$D6,100,0))*EXP(-DL6*((BC6-Settle)/365))) -> 0 | FV6: =IF(BD6="",0,($C6/2+IF(51=$D6,100,0))*EXP(-DM6*((BD6-Settle)/365))) -> 0 | FW6: =IF(BE6="",0,($C6/2+IF(52=$D6,100,0))*EXP(-DN6*((BE6-Settle)/365))) -> 0 | FX6: =IF(BF6="",0,($C6/2+IF(53=$D6,100,0))*EXP(-DO6*((BF6-Settle)/365))) -> 0 | FY6: =IF(BG6="",0,($C6/2+IF(54=$D6,100,0))*EXP(-DP6*((BG6-Settle)/365))) -> 0 | FZ6: =IF(BH6="",0,($C6/2+IF(55=$D6,100,0))*EXP(-DQ6*((BH6-Settle)/365))) -> 0 | GA6: =IF(BI6="",0,($C6/2+IF(56=$D6,100,0))*EXP(-DR6*((BI6-Settle)/365))) -> 0 | GB6: =IF(BJ6="",0,($C6/2+IF(57=$D6,100,0))*EXP(-DS6*((BJ6-Settle)/365))) -> 0 | GC6: =IF(BK6="",0,($C6/2+IF(58=$D6,100,0))*EXP(-DT6*((BK6-Settle)/365))) -> 0 | GD6: =IF(BL6="",0,($C6/2+IF(59=$D6,100,0))*EXP(-DU6*((BL6-Settle)/365))) -> 0 | GE6: =IF(BM6="",0,($C6/2+IF(60=$D6,100,0))*EXP(-DV6*((BM6-Settle)/365))) -> 0
A7: 4 | B7: =Bonds!B7 -> 46295 | C7: =Bonds!C7 -> 3.5 | D7: =Bonds!Q7 -> 1 | E7: =IF(DAY(B7)=DAY(EOMONTH(B7,0)),1,0) -> 1 | F7: =IF(1>$D7,"",IF($E7=1,EOMONTH(EDATE(Bonds!$I7,6*(1-1)),0),EDATE(Bonds!$I7,6*(1-1)))) -> 46295 | G7: =IF(2>$D7,"",IF($E7=1,EOMONTH(EDATE(Bonds!$I7,6*(2-1)),0),EDATE(Bonds!$I7,6*(2-1)))) | H7: =IF(3>$D7,"",IF($E7=1,EOMONTH(EDATE(Bonds!$I7,6*(3-1)),0),EDATE(Bonds!$I7,6*(3-1)))) | I7: =IF(4>$D7,"",IF($E7=1,EOMONTH(EDATE(Bonds!$I7,6*(4-1)),0),EDATE(Bonds!$I7,6*(4-1)))) | J7: =IF(5>$D7,"",IF($E7=1,EOMONTH(EDATE(Bonds!$I7,6*(5-1)),0),EDATE(Bonds!$I7,6*(5-1)))) | K7: =IF(6>$D7,"",IF($E7=1,EOMONTH(EDATE(Bonds!$I7,6*(6-1)),0),EDATE(Bonds!$I7,6*(6-1)))) | L7: =IF(7>$D7,"",IF($E7=1,EOMONTH(EDATE(Bonds!$I7,6*(7-1)),0),EDATE(Bonds!$I7,6*(7-1)))) | M7: =IF(8>$D7,"",IF($E7=1,EOMONTH(EDATE(Bonds!$I7,6*(8-1)),0),EDATE(Bonds!$I7,6*(8-1)))) | N7: =IF(9>$D7,"",IF($E7=1,EOMONTH(EDATE(Bonds!$I7,6*(9-1)),0),EDATE(Bonds!$I7,6*(9-1)))) | O7: =IF(10>$D7,"",IF($E7=1,EOMONTH(EDATE(Bonds!$I7,6*(10-1)),0),EDATE(Bonds!$I7,6*(10-1)))) | P7: =IF(11>$D7,"",IF($E7=1,EOMONTH(EDATE(Bonds!$I7,6*(11-1)),0),EDATE(Bonds!$I7,6*(11-1)))) | Q7: =IF(12>$D7,"",IF($E7=1,EOMONTH(EDATE(Bonds!$I7,6*(12-1)),0),EDATE(Bonds!$I7,6*(12-1)))) | R7: =IF(13>$D7,"",IF($E7=1,EOMONTH(EDATE(Bonds!$I7,6*(13-1)),0),EDATE(Bonds!$I7,6*(13-1)))) | S7: =IF(14>$D7,"",IF($E7=1,EOMONTH(EDATE(Bonds!$I7,6*(14-1)),0),EDATE(Bonds!$I7,6*(14-1)))) | T7: =IF(15>$D7,"",IF($E7=1,EOMONTH(EDATE(Bonds!$I7,6*(15-1)),0),EDATE(Bonds!$I7,6*(15-1)))) | U7: =IF(16>$D7,"",IF($E7=1,EOMONTH(EDATE(Bonds!$I7,6*(16-1)),0),EDATE(Bonds!$I7,6*(16-1)))) | V7: =IF(17>$D7,"",IF($E7=1,EOMONTH(EDATE(Bonds!$I7,6*(17-1)),0),EDATE(Bonds!$I7,6*(17-1)))) | W7: =IF(18>$D7,"",IF($E7=1,EOMONTH(EDATE(Bonds!$I7,6*(18-1)),0),EDATE(Bonds!$I7,6*(18-1)))) | X7: =IF(19>$D7,"",IF($E7=1,EOMONTH(EDATE(Bonds!$I7,6*(19-1)),0),EDATE(Bonds!$I7,6*(19-1)))) | Y7: =IF(20>$D7,"",IF($E7=1,EOMONTH(EDATE(Bonds!$I7,6*(20-1)),0),EDATE(Bonds!$I7,6*(20-1)))) | Z7: =IF(21>$D7,"",IF($E7=1,EOMONTH(EDATE(Bonds!$I7,6*(21-1)),0),EDATE(Bonds!$I7,6*(21-1)))) | AA7: =IF(22>$D7,"",IF($E7=1,EOMONTH(EDATE(Bonds!$I7,6*(22-1)),0),EDATE(Bonds!$I7,6*(22-1)))) | AB7: =IF(23>$D7,"",IF($E7=1,EOMONTH(EDATE(Bonds!$I7,6*(23-1)),0),EDATE(Bonds!$I7,6*(23-1)))) | AC7: =IF(24>$D7,"",IF($E7=1,EOMONTH(EDATE(Bonds!$I7,6*(24-1)),0),EDATE(Bonds!$I7,6*(24-1)))) | AD7: =IF(25>$D7,"",IF($E7=1,EOMONTH(EDATE(Bonds!$I7,6*(25-1)),0),EDATE(Bonds!$I7,6*(25-1)))) | AE7: =IF(26>$D7,"",IF($E7=1,EOMONTH(EDATE(Bonds!$I7,6*(26-1)),0),EDATE(Bonds!$I7,6*(26-1)))) | AF7: =IF(27>$D7,"",IF($E7=1,EOMONTH(EDATE(Bonds!$I7,6*(27-1)),0),EDATE(Bonds!$I7,6*(27-1)))) | AG7: =IF(28>$D7,"",IF($E7=1,EOMONTH(EDATE(Bonds!$I7,6*(28-1)),0),EDATE(Bonds!$I7,6*(28-1)))) | AH7: =IF(29>$D7,"",IF($E7=1,EOMONTH(EDATE(Bonds!$I7,6*(29-1)),0),EDATE(Bonds!$I7,6*(29-1)))) | AI7: =IF(30>$D7,"",IF($E7=1,EOMONTH(EDATE(Bonds!$I7,6*(30-1)),0),EDATE(Bonds!$I7,6*(30-1)))) | AJ7: =IF(31>$D7,"",IF($E7=1,EOMONTH(EDATE(Bonds!$I7,6*(31-1)),0),EDATE(Bonds!$I7,6*(31-1)))) | AK7: =IF(32>$D7,"",IF($E7=1,EOMONTH(EDATE(Bonds!$I7,6*(32-1)),0),EDATE(Bonds!$I7,6*(32-1)))) | AL7: =IF(33>$D7,"",IF($E7=1,EOMONTH(EDATE(Bonds!$I7,6*(33-1)),0),EDATE(Bonds!$I7,6*(33-1)))) | AM7: =IF(34>$D7,"",IF($E7=1,EOMONTH(EDATE(Bonds!$I7,6*(34-1)),0),EDATE(Bonds!$I7,6*(34-1)))) | AN7: =IF(35>$D7,"",IF($E7=1,EOMONTH(EDATE(Bonds!$I7,6*(35-1)),0),EDATE(Bonds!$I7,6*(35-1)))) | AO7: =IF(36>$D7,"",IF($E7=1,EOMONTH(EDATE(Bonds!$I7,6*(36-1)),0),EDATE(Bonds!$I7,6*(36-1)))) | AP7: =IF(37>$D7,"",IF($E7=1,EOMONTH(EDATE(Bonds!$I7,6*(37-1)),0),EDATE(Bonds!$I7,6*(37-1)))) | AQ7: =IF(38>$D7,"",IF($E7=1,EOMONTH(EDATE(Bonds!$I7,6*(38-1)),0),EDATE(Bonds!$I7,6*(38-1)))) | AR7: =IF(39>$D7,"",IF($E7=1,EOMONTH(EDATE(Bonds!$I7,6*(39-1)),0),EDATE(Bonds!$I7,6*(39-1)))) | AS7: =IF(40>$D7,"",IF($E7=1,EOMONTH(EDATE(Bonds!$I7,6*(40-1)),0),EDATE(Bonds!$I7,6*(40-1)))) | AT7: =IF(41>$D7,"",IF($E7=1,EOMONTH(EDATE(Bonds!$I7,6*(41-1)),0),EDATE(Bonds!$I7,6*(41-1)))) | AU7: =IF(42>$D7,"",IF($E7=1,EOMONTH(EDATE(Bonds!$I7,6*(42-1)),0),EDATE(Bonds!$I7,6*(42-1)))) | AV7: =IF(43>$D7,"",IF($E7=1,EOMONTH(EDATE(Bonds!$I7,6*(43-1)),0),EDATE(Bonds!$I7,6*(43-1)))) | AW7: =IF(44>$D7,"",IF($E7=1,EOMONTH(EDATE(Bonds!$I7,6*(44-1)),0),EDATE(Bonds!$I7,6*(44-1)))) | AX7: =IF(45>$D7,"",IF($E7=1,EOMONTH(EDATE(Bonds!$I7,6*(45-1)),0),EDATE(Bonds!$I7,6*(45-1)))) | AY7: =IF(46>$D7,"",IF($E7=1,EOMONTH(EDATE(Bonds!$I7,6*(46-1)),0),EDATE(Bonds!$I7,6*(46-1)))) | AZ7: =IF(47>$D7,"",IF($E7=1,EOMONTH(EDATE(Bonds!$I7,6*(47-1)),0),EDATE(Bonds!$I7,6*(47-1)))) | BA7: =IF(48>$D7,"",IF($E7=1,EOMONTH(EDATE(Bonds!$I7,6*(48-1)),0),EDATE(Bonds!$I7,6*(48-1)))) | BB7: =IF(49>$D7,"",IF($E7=1,EOMONTH(EDATE(Bonds!$I7,6*(49-1)),0),EDATE(Bonds!$I7,6*(49-1)))) | BC7: =IF(50>$D7,"",IF($E7=1,EOMONTH(EDATE(Bonds!$I7,6*(50-1)),0),EDATE(Bonds!$I7,6*(50-1)))) | BD7: =IF(51>$D7,"",IF($E7=1,EOMONTH(EDATE(Bonds!$I7,6*(51-1)),0),EDATE(Bonds!$I7,6*(51-1)))) | BE7: =IF(52>$D7,"",IF($E7=1,EOMONTH(EDATE(Bonds!$I7,6*(52-1)),0),EDATE(Bonds!$I7,6*(52-1)))) | BF7: =IF(53>$D7,"",IF($E7=1,EOMONTH(EDATE(Bonds!$I7,6*(53-1)),0),EDATE(Bonds!$I7,6*(53-1)))) | BG7: =IF(54>$D7,"",IF($E7=1,EOMONTH(EDATE(Bonds!$I7,6*(54-1)),0),EDATE(Bonds!$I7,6*(54-1)))) | BH7: =IF(55>$D7,"",IF($E7=1,EOMONTH(EDATE(Bonds!$I7,6*(55-1)),0),EDATE(Bonds!$I7,6*(55-1)))) | BI7: =IF(56>$D7,"",IF($E7=1,EOMONTH(EDATE(Bonds!$I7,6*(56-1)),0),EDATE(Bonds!$I7,6*(56-1)))) | BJ7: =IF(57>$D7,"",IF($E7=1,EOMONTH(EDATE(Bonds!$I7,6*(57-1)),0),EDATE(Bonds!$I7,6*(57-1)))) | BK7: =IF(58>$D7,"",IF($E7=1,EOMONTH(EDATE(Bonds!$I7,6*(58-1)),0),EDATE(Bonds!$I7,6*(58-1)))) | BL7: =IF(59>$D7,"",IF($E7=1,EOMONTH(EDATE(Bonds!$I7,6*(59-1)),0),EDATE(Bonds!$I7,6*(59-1)))) | BM7: =IF(60>$D7,"",IF($E7=1,EOMONTH(EDATE(Bonds!$I7,6*(60-1)),0),EDATE(Bonds!$I7,6*(60-1)))) | BO7: =IF(F7="","",Sv_beta0+Sv_beta1*(1-EXP(-((F7-Settle)/365)/Sv_tau1))/(((F7-Settle)/365)/Sv_tau1)+Sv_beta2*((1-EXP(-((F7-Settle)/365)/Sv_tau1))/(((F7-Settle)/365)/Sv_tau1)-EXP(-((F7-Settle)/365)/Sv_tau1))+Sv_beta3*((1-EXP(-((F7-Settle)/365)/Sv_tau2))/(((F7-Settle)/365)/Sv_tau2)-EXP(-((F7-Settle)/365)/Sv_tau2))) -> 0.036715304 | BP7: =IF(G7="","",Sv_beta0+Sv_beta1*(1-EXP(-((G7-Settle)/365)/Sv_tau1))/(((G7-Settle)/365)/Sv_tau1)+Sv_beta2*((1-EXP(-((G7-Settle)/365)/Sv_tau1))/(((G7-Settle)/365)/Sv_tau1)-EXP(-((G7-Settle)/365)/Sv_tau1))+Sv_beta3*((1-EXP(-((G7-Settle)/365)/Sv_tau2))/(((G7-Settle)/365)/Sv_tau2)-EXP(-((G7-Settle)/365)/Sv_tau2))) | BQ7: =IF(H7="","",Sv_beta0+Sv_beta1*(1-EXP(-((H7-Settle)/365)/Sv_tau1))/(((H7-Settle)/365)/Sv_tau1)+Sv_beta2*((1-EXP(-((H7-Settle)/365)/Sv_tau1))/(((H7-Settle)/365)/Sv_tau1)-EXP(-((H7-Settle)/365)/Sv_tau1))+Sv_beta3*((1-EXP(-((H7-Settle)/365)/Sv_tau2))/(((H7-Settle)/365)/Sv_tau2)-EXP(-((H7-Settle)/365)/Sv_tau2))) | BR7: =IF(I7="","",Sv_beta0+Sv_beta1*(1-EXP(-((I7-Settle)/365)/Sv_tau1))/(((I7-Settle)/365)/Sv_tau1)+Sv_beta2*((1-EXP(-((I7-Settle)/365)/Sv_tau1))/(((I7-Settle)/365)/Sv_tau1)-EXP(-((I7-Settle)/365)/Sv_tau1))+Sv_beta3*((1-EXP(-((I7-Settle)/365)/Sv_tau2))/(((I7-Settle)/365)/Sv_tau2)-EXP(-((I7-Settle)/365)/Sv_tau2))) | BS7: =IF(J7="","",Sv_beta0+Sv_beta1*(1-EXP(-((J7-Settle)/365)/Sv_tau1))/(((J7-Settle)/365)/Sv_tau1)+Sv_beta2*((1-EXP(-((J7-Settle)/365)/Sv_tau1))/(((J7-Settle)/365)/Sv_tau1)-EXP(-((J7-Settle)/365)/Sv_tau1))+Sv_beta3*((1-EXP(-((J7-Settle)/365)/Sv_tau2))/(((J7-Settle)/365)/Sv_tau2)-EXP(-((J7-Settle)/365)/Sv_tau2))) | BT7: =IF(K7="","",Sv_beta0+Sv_beta1*(1-EXP(-((K7-Settle)/365)/Sv_tau1))/(((K7-Settle)/365)/Sv_tau1)+Sv_beta2*((1-EXP(-((K7-Settle)/365)/Sv_tau1))/(((K7-Settle)/365)/Sv_tau1)-EXP(-((K7-Settle)/365)/Sv_tau1))+Sv_beta3*((1-EXP(-((K7-Settle)/365)/Sv_tau2))/(((K7-Settle)/365)/Sv_tau2)-EXP(-((K7-Settle)/365)/Sv_tau2))) | BU7: =IF(L7="","",Sv_beta0+Sv_beta1*(1-EXP(-((L7-Settle)/365)/Sv_tau1))/(((L7-Settle)/365)/Sv_tau1)+Sv_beta2*((1-EXP(-((L7-Settle)/365)/Sv_tau1))/(((L7-Settle)/365)/Sv_tau1)-EXP(-((L7-Settle)/365)/Sv_tau1))+Sv_beta3*((1-EXP(-((L7-Settle)/365)/Sv_tau2))/(((L7-Settle)/365)/Sv_tau2)-EXP(-((L7-Settle)/365)/Sv_tau2))) | BV7: =IF(M7="","",Sv_beta0+Sv_beta1*(1-EXP(-((M7-Settle)/365)/Sv_tau1))/(((M7-Settle)/365)/Sv_tau1)+Sv_beta2*((1-EXP(-((M7-Settle)/365)/Sv_tau1))/(((M7-Settle)/365)/Sv_tau1)-EXP(-((M7-Settle)/365)/Sv_tau1))+Sv_beta3*((1-EXP(-((M7-Settle)/365)/Sv_tau2))/(((M7-Settle)/365)/Sv_tau2)-EXP(-((M7-Settle)/365)/Sv_tau2))) | ... DV7: =IF(BM7="","",Sv_beta0+Sv_beta1*(1-EXP(-((BM7-Settle)/365)/Sv_tau1))/(((BM7-Settle)/365)/Sv_tau1)+Sv_beta2*((1-EXP(-((BM7-Settle)/365)/Sv_tau1))/(((BM7-Settle)/365)/Sv_tau1)-EXP(-((BM7-Settle)/365)/Sv_tau1))+Sv_beta3*((1-EXP(-((BM7-Settle)/365)/Sv_tau2))/(((BM7-Settle)/365)/Sv_tau2)-EXP(-((BM7-Settle)/365)/Sv_tau2))) | DX7: =IF(F7="",0,($C7/2+IF(1=$D7,100,0))*EXP(-BO7*((F7-Settle)/365))) -> 101.52508 | DY7: =IF(G7="",0,($C7/2+IF(2=$D7,100,0))*EXP(-BP7*((G7-Settle)/365))) -> 0 | DZ7: =IF(H7="",0,($C7/2+IF(3=$D7,100,0))*EXP(-BQ7*((H7-Settle)/365))) -> 0 | EA7: =IF(I7="",0,($C7/2+IF(4=$D7,100,0))*EXP(-BR7*((I7-Settle)/365))) -> 0 | EB7: =IF(J7="",0,($C7/2+IF(5=$D7,100,0))*EXP(-BS7*((J7-Settle)/365))) -> 0 | EC7: =IF(K7="",0,($C7/2+IF(6=$D7,100,0))*EXP(-BT7*((K7-Settle)/365))) -> 0 | ED7: =IF(L7="",0,($C7/2+IF(7=$D7,100,0))*EXP(-BU7*((L7-Settle)/365))) -> 0 | EE7: =IF(M7="",0,($C7/2+IF(8=$D7,100,0))*EXP(-BV7*((M7-Settle)/365))) -> 0 | EF7: =IF(N7="",0,($C7/2+IF(9=$D7,100,0))*EXP(-BW7*((N7-Settle)/365))) -> 0 | EG7: =IF(O7="",0,($C7/2+IF(10=$D7,100,0))*EXP(-BX7*((O7-Settle)/365))) -> 0 | EH7: =IF(P7="",0,($C7/2+IF(11=$D7,100,0))*EXP(-BY7*((P7-Settle)/365))) -> 0 | EI7: =IF(Q7="",0,($C7/2+IF(12=$D7,100,0))*EXP(-BZ7*((Q7-Settle)/365))) -> 0 | EJ7: =IF(R7="",0,($C7/2+IF(13=$D7,100,0))*EXP(-CA7*((R7-Settle)/365))) -> 0 | EK7: =IF(S7="",0,($C7/2+IF(14=$D7,100,0))*EXP(-CB7*((S7-Settle)/365))) -> 0 | EL7: =IF(T7="",0,($C7/2+IF(15=$D7,100,0))*EXP(-CC7*((T7-Settle)/365))) -> 0 | EM7: =IF(U7="",0,($C7/2+IF(16=$D7,100,0))*EXP(-CD7*((U7-Settle)/365))) -> 0 | EN7: =IF(V7="",0,($C7/2+IF(17=$D7,100,0))*EXP(-CE7*((V7-Settle)/365))) -> 0 | EO7: =IF(W7="",0,($C7/2+IF(18=$D7,100,0))*EXP(-CF7*((W7-Settle)/365))) -> 0 | EP7: =IF(X7="",0,($C7/2+IF(19=$D7,100,0))*EXP(-CG7*((X7-Settle)/365))) -> 0 | EQ7: =IF(Y7="",0,($C7/2+IF(20=$D7,100,0))*EXP(-CH7*((Y7-Settle)/365))) -> 0 | ER7: =IF(Z7="",0,($C7/2+IF(21=$D7,100,0))*EXP(-CI7*((Z7-Settle)/365))) -> 0 | ES7: =IF(AA7="",0,($C7/2+IF(22=$D7,100,0))*EXP(-CJ7*((AA7-Settle)/365))) -> 0 | ET7: =IF(AB7="",0,($C7/2+IF(23=$D7,100,0))*EXP(-CK7*((AB7-Settle)/365))) -> 0 | EU7: =IF(AC7="",0,($C7/2+IF(24=$D7,100,0))*EXP(-CL7*((AC7-Settle)/365))) -> 0 | EV7: =IF(AD7="",0,($C7/2+IF(25=$D7,100,0))*EXP(-CM7*((AD7-Settle)/365))) -> 0 | EW7: =IF(AE7="",0,($C7/2+IF(26=$D7,100,0))*EXP(-CN7*((AE7-Settle)/365))) -> 0 | EX7: =IF(AF7="",0,($C7/2+IF(27=$D7,100,0))*EXP(-CO7*((AF7-Settle)/365))) -> 0 | EY7: =IF(AG7="",0,($C7/2+IF(28=$D7,100,0))*EXP(-CP7*((AG7-Settle)/365))) -> 0 | EZ7: =IF(AH7="",0,($C7/2+IF(29=$D7,100,0))*EXP(-CQ7*((AH7-Settle)/365))) -> 0 | FA7: =IF(AI7="",0,($C7/2+IF(30=$D7,100,0))*EXP(-CR7*((AI7-Settle)/365))) -> 0 | FB7: =IF(AJ7="",0,($C7/2+IF(31=$D7,100,0))*EXP(-CS7*((AJ7-Settle)/365))) -> 0 | FC7: =IF(AK7="",0,($C7/2+IF(32=$D7,100,0))*EXP(-CT7*((AK7-Settle)/365))) -> 0 | FD7: =IF(AL7="",0,($C7/2+IF(33=$D7,100,0))*EXP(-CU7*((AL7-Settle)/365))) -> 0 | FE7: =IF(AM7="",0,($C7/2+IF(34=$D7,100,0))*EXP(-CV7*((AM7-Settle)/365))) -> 0 | FF7: =IF(AN7="",0,($C7/2+IF(35=$D7,100,0))*EXP(-CW7*((AN7-Settle)/365))) -> 0 | FG7: =IF(AO7="",0,($C7/2+IF(36=$D7,100,0))*EXP(-CX7*((AO7-Settle)/365))) -> 0 | FH7: =IF(AP7="",0,($C7/2+IF(37=$D7,100,0))*EXP(-CY7*((AP7-Settle)/365))) -> 0 | FI7: =IF(AQ7="",0,($C7/2+IF(38=$D7,100,0))*EXP(-CZ7*((AQ7-Settle)/365))) -> 0 | FJ7: =IF(AR7="",0,($C7/2+IF(39=$D7,100,0))*EXP(-DA7*((AR7-Settle)/365))) -> 0 | FK7: =IF(AS7="",0,($C7/2+IF(40=$D7,100,0))*EXP(-DB7*((AS7-Settle)/365))) -> 0 | FL7: =IF(AT7="",0,($C7/2+IF(41=$D7,100,0))*EXP(-DC7*((AT7-Settle)/365))) -> 0 | FM7: =IF(AU7="",0,($C7/2+IF(42=$D7,100,0))*EXP(-DD7*((AU7-Settle)/365))) -> 0 | FN7: =IF(AV7="",0,($C7/2+IF(43=$D7,100,0))*EXP(-DE7*((AV7-Settle)/365))) -> 0 | FO7: =IF(AW7="",0,($C7/2+IF(44=$D7,100,0))*EXP(-DF7*((AW7-Settle)/365))) -> 0 | FP7: =IF(AX7="",0,($C7/2+IF(45=$D7,100,0))*EXP(-DG7*((AX7-Settle)/365))) -> 0 | FQ7: =IF(AY7="",0,($C7/2+IF(46=$D7,100,0))*EXP(-DH7*((AY7-Settle)/365))) -> 0 | FR7: =IF(AZ7="",0,($C7/2+IF(47=$D7,100,0))*EXP(-DI7*((AZ7-Settle)/365))) -> 0 | FS7: =IF(BA7="",0,($C7/2+IF(48=$D7,100,0))*EXP(-DJ7*((BA7-Settle)/365))) -> 0 | FT7: =IF(BB7="",0,($C7/2+IF(49=$D7,100,0))*EXP(-DK7*((BB7-Settle)/365))) -> 0 | FU7: =IF(BC7="",0,($C7/2+IF(50=$D7,100,0))*EXP(-DL7*((BC7-Settle)/365))) -> 0 | FV7: =IF(BD7="",0,($C7/2+IF(51=$D7,100,0))*EXP(-DM7*((BD7-Settle)/365))) -> 0 | FW7: =IF(BE7="",0,($C7/2+IF(52=$D7,100,0))*EXP(-DN7*((BE7-Settle)/365))) -> 0 | FX7: =IF(BF7="",0,($C7/2+IF(53=$D7,100,0))*EXP(-DO7*((BF7-Settle)/365))) -> 0 | FY7: =IF(BG7="",0,($C7/2+IF(54=$D7,100,0))*EXP(-DP7*((BG7-Settle)/365))) -> 0 | FZ7: =IF(BH7="",0,($C7/2+IF(55=$D7,100,0))*EXP(-DQ7*((BH7-Settle)/365))) -> 0 | GA7: =IF(BI7="",0,($C7/2+IF(56=$D7,100,0))*EXP(-DR7*((BI7-Settle)/365))) -> 0 | GB7: =IF(BJ7="",0,($C7/2+IF(57=$D7,100,0))*EXP(-DS7*((BJ7-Settle)/365))) -> 0 | GC7: =IF(BK7="",0,($C7/2+IF(58=$D7,100,0))*EXP(-DT7*((BK7-Settle)/365))) -> 0 | GD7: =IF(BL7="",0,($C7/2+IF(59=$D7,100,0))*EXP(-DU7*((BL7-Settle)/365))) -> 0 | GE7: =IF(BM7="",0,($C7/2+IF(60=$D7,100,0))*EXP(-DV7*((BM7-Settle)/365))) -> 0
A8: 5 | B8: =Bonds!B8 -> 46310 | C8: =Bonds!C8 -> 4.625 | D8: =Bonds!Q8 -> 1 | E8: =IF(DAY(B8)=DAY(EOMONTH(B8,0)),1,0) -> 0 | F8: =IF(1>$D8,"",IF($E8=1,EOMONTH(EDATE(Bonds!$I8,6*(1-1)),0),EDATE(Bonds!$I8,6*(1-1)))) -> 46310 | G8: =IF(2>$D8,"",IF($E8=1,EOMONTH(EDATE(Bonds!$I8,6*(2-1)),0),EDATE(Bonds!$I8,6*(2-1)))) | H8: =IF(3>$D8,"",IF($E8=1,EOMONTH(EDATE(Bonds!$I8,6*(3-1)),0),EDATE(Bonds!$I8,6*(3-1)))) | I8: =IF(4>$D8,"",IF($E8=1,EOMONTH(EDATE(Bonds!$I8,6*(4-1)),0),EDATE(Bonds!$I8,6*(4-1)))) | J8: =IF(5>$D8,"",IF($E8=1,EOMONTH(EDATE(Bonds!$I8,6*(5-1)),0),EDATE(Bonds!$I8,6*(5-1)))) | K8: =IF(6>$D8,"",IF($E8=1,EOMONTH(EDATE(Bonds!$I8,6*(6-1)),0),EDATE(Bonds!$I8,6*(6-1)))) | L8: =IF(7>$D8,"",IF($E8=1,EOMONTH(EDATE(Bonds!$I8,6*(7-1)),0),EDATE(Bonds!$I8,6*(7-1)))) | M8: =IF(8>$D8,"",IF($E8=1,EOMONTH(EDATE(Bonds!$I8,6*(8-1)),0),EDATE(Bonds!$I8,6*(8-1)))) | N8: =IF(9>$D8,"",IF($E8=1,EOMONTH(EDATE(Bonds!$I8,6*(9-1)),0),EDATE(Bonds!$I8,6*(9-1)))) | O8: =IF(10>$D8,"",IF($E8=1,EOMONTH(EDATE(Bonds!$I8,6*(10-1)),0),EDATE(Bonds!$I8,6*(10-1)))) | P8: =IF(11>$D8,"",IF($E8=1,EOMONTH(EDATE(Bonds!$I8,6*(11-1)),0),EDATE(Bonds!$I8,6*(11-1)))) | Q8: =IF(12>$D8,"",IF($E8=1,EOMONTH(EDATE(Bonds!$I8,6*(12-1)),0),EDATE(Bonds!$I8,6*(12-1)))) | R8: =IF(13>$D8,"",IF($E8=1,EOMONTH(EDATE(Bonds!$I8,6*(13-1)),0),EDATE(Bonds!$I8,6*(13-1)))) | S8: =IF(14>$D8,"",IF($E8=1,EOMONTH(EDATE(Bonds!$I8,6*(14-1)),0),EDATE(Bonds!$I8,6*(14-1)))) | T8: =IF(15>$D8,"",IF($E8=1,EOMONTH(EDATE(Bonds!$I8,6*(15-1)),0),EDATE(Bonds!$I8,6*(15-1)))) | U8: =IF(16>$D8,"",IF($E8=1,EOMONTH(EDATE(Bonds!$I8,6*(16-1)),0),EDATE(Bonds!$I8,6*(16-1)))) | V8: =IF(17>$D8,"",IF($E8=1,EOMONTH(EDATE(Bonds!$I8,6*(17-1)),0),EDATE(Bonds!$I8,6*(17-1)))) | W8: =IF(18>$D8,"",IF($E8=1,EOMONTH(EDATE(Bonds!$I8,6*(18-1)),0),EDATE(Bonds!$I8,6*(18-1)))) | X8: =IF(19>$D8,"",IF($E8=1,EOMONTH(EDATE(Bonds!$I8,6*(19-1)),0),EDATE(Bonds!$I8,6*(19-1)))) | Y8: =IF(20>$D8,"",IF($E8=1,EOMONTH(EDATE(Bonds!$I8,6*(20-1)),0),EDATE(Bonds!$I8,6*(20-1)))) | Z8: =IF(21>$D8,"",IF($E8=1,EOMONTH(EDATE(Bonds!$I8,6*(21-1)),0),EDATE(Bonds!$I8,6*(21-1)))) | AA8: =IF(22>$D8,"",IF($E8=1,EOMONTH(EDATE(Bonds!$I8,6*(22-1)),0),EDATE(Bonds!$I8,6*(22-1)))) | AB8: =IF(23>$D8,"",IF($E8=1,EOMONTH(EDATE(Bonds!$I8,6*(23-1)),0),EDATE(Bonds!$I8,6*(23-1)))) | AC8: =IF(24>$D8,"",IF($E8=1,EOMONTH(EDATE(Bonds!$I8,6*(24-1)),0),EDATE(Bonds!$I8,6*(24-1)))) | AD8: =IF(25>$D8,"",IF($E8=1,EOMONTH(EDATE(Bonds!$I8,6*(25-1)),0),EDATE(Bonds!$I8,6*(25-1)))) | AE8: =IF(26>$D8,"",IF($E8=1,EOMONTH(EDATE(Bonds!$I8,6*(26-1)),0),EDATE(Bonds!$I8,6*(26-1)))) | AF8: =IF(27>$D8,"",IF($E8=1,EOMONTH(EDATE(Bonds!$I8,6*(27-1)),0),EDATE(Bonds!$I8,6*(27-1)))) | AG8: =IF(28>$D8,"",IF($E8=1,EOMONTH(EDATE(Bonds!$I8,6*(28-1)),0),EDATE(Bonds!$I8,6*(28-1)))) | AH8: =IF(29>$D8,"",IF($E8=1,EOMONTH(EDATE(Bonds!$I8,6*(29-1)),0),EDATE(Bonds!$I8,6*(29-1)))) | AI8: =IF(30>$D8,"",IF($E8=1,EOMONTH(EDATE(Bonds!$I8,6*(30-1)),0),EDATE(Bonds!$I8,6*(30-1)))) | AJ8: =IF(31>$D8,"",IF($E8=1,EOMONTH(EDATE(Bonds!$I8,6*(31-1)),0),EDATE(Bonds!$I8,6*(31-1)))) | AK8: =IF(32>$D8,"",IF($E8=1,EOMONTH(EDATE(Bonds!$I8,6*(32-1)),0),EDATE(Bonds!$I8,6*(32-1)))) | AL8: =IF(33>$D8,"",IF($E8=1,EOMONTH(EDATE(Bonds!$I8,6*(33-1)),0),EDATE(Bonds!$I8,6*(33-1)))) | AM8: =IF(34>$D8,"",IF($E8=1,EOMONTH(EDATE(Bonds!$I8,6*(34-1)),0),EDATE(Bonds!$I8,6*(34-1)))) | AN8: =IF(35>$D8,"",IF($E8=1,EOMONTH(EDATE(Bonds!$I8,6*(35-1)),0),EDATE(Bonds!$I8,6*(35-1)))) | AO8: =IF(36>$D8,"",IF($E8=1,EOMONTH(EDATE(Bonds!$I8,6*(36-1)),0),EDATE(Bonds!$I8,6*(36-1)))) | AP8: =IF(37>$D8,"",IF($E8=1,EOMONTH(EDATE(Bonds!$I8,6*(37-1)),0),EDATE(Bonds!$I8,6*(37-1)))) | AQ8: =IF(38>$D8,"",IF($E8=1,EOMONTH(EDATE(Bonds!$I8,6*(38-1)),0),EDATE(Bonds!$I8,6*(38-1)))) | AR8: =IF(39>$D8,"",IF($E8=1,EOMONTH(EDATE(Bonds!$I8,6*(39-1)),0),EDATE(Bonds!$I8,6*(39-1)))) | AS8: =IF(40>$D8,"",IF($E8=1,EOMONTH(EDATE(Bonds!$I8,6*(40-1)),0),EDATE(Bonds!$I8,6*(40-1)))) | AT8: =IF(41>$D8,"",IF($E8=1,EOMONTH(EDATE(Bonds!$I8,6*(41-1)),0),EDATE(Bonds!$I8,6*(41-1)))) | AU8: =IF(42>$D8,"",IF($E8=1,EOMONTH(EDATE(Bonds!$I8,6*(42-1)),0),EDATE(Bonds!$I8,6*(42-1)))) | AV8: =IF(43>$D8,"",IF($E8=1,EOMONTH(EDATE(Bonds!$I8,6*(43-1)),0),EDATE(Bonds!$I8,6*(43-1)))) | AW8: =IF(44>$D8,"",IF($E8=1,EOMONTH(EDATE(Bonds!$I8,6*(44-1)),0),EDATE(Bonds!$I8,6*(44-1)))) | AX8: =IF(45>$D8,"",IF($E8=1,EOMONTH(EDATE(Bonds!$I8,6*(45-1)),0),EDATE(Bonds!$I8,6*(45-1)))) | AY8: =IF(46>$D8,"",IF($E8=1,EOMONTH(EDATE(Bonds!$I8,6*(46-1)),0),EDATE(Bonds!$I8,6*(46-1)))) | AZ8: =IF(47>$D8,"",IF($E8=1,EOMONTH(EDATE(Bonds!$I8,6*(47-1)),0),EDATE(Bonds!$I8,6*(47-1)))) | BA8: =IF(48>$D8,"",IF($E8=1,EOMONTH(EDATE(Bonds!$I8,6*(48-1)),0),EDATE(Bonds!$I8,6*(48-1)))) | BB8: =IF(49>$D8,"",IF($E8=1,EOMONTH(EDATE(Bonds!$I8,6*(49-1)),0),EDATE(Bonds!$I8,6*(49-1)))) | BC8: =IF(50>$D8,"",IF($E8=1,EOMONTH(EDATE(Bonds!$I8,6*(50-1)),0),EDATE(Bonds!$I8,6*(50-1)))) | BD8: =IF(51>$D8,"",IF($E8=1,EOMONTH(EDATE(Bonds!$I8,6*(51-1)),0),EDATE(Bonds!$I8,6*(51-1)))) | BE8: =IF(52>$D8,"",IF($E8=1,EOMONTH(EDATE(Bonds!$I8,6*(52-1)),0),EDATE(Bonds!$I8,6*(52-1)))) | BF8: =IF(53>$D8,"",IF($E8=1,EOMONTH(EDATE(Bonds!$I8,6*(53-1)),0),EDATE(Bonds!$I8,6*(53-1)))) | BG8: =IF(54>$D8,"",IF($E8=1,EOMONTH(EDATE(Bonds!$I8,6*(54-1)),0),EDATE(Bonds!$I8,6*(54-1)))) | BH8: =IF(55>$D8,"",IF($E8=1,EOMONTH(EDATE(Bonds!$I8,6*(55-1)),0),EDATE(Bonds!$I8,6*(55-1)))) | BI8: =IF(56>$D8,"",IF($E8=1,EOMONTH(EDATE(Bonds!$I8,6*(56-1)),0),EDATE(Bonds!$I8,6*(56-1)))) | BJ8: =IF(57>$D8,"",IF($E8=1,EOMONTH(EDATE(Bonds!$I8,6*(57-1)),0),EDATE(Bonds!$I8,6*(57-1)))) | BK8: =IF(58>$D8,"",IF($E8=1,EOMONTH(EDATE(Bonds!$I8,6*(58-1)),0),EDATE(Bonds!$I8,6*(58-1)))) | BL8: =IF(59>$D8,"",IF($E8=1,EOMONTH(EDATE(Bonds!$I8,6*(59-1)),0),EDATE(Bonds!$I8,6*(59-1)))) | BM8: =IF(60>$D8,"",IF($E8=1,EOMONTH(EDATE(Bonds!$I8,6*(60-1)),0),EDATE(Bonds!$I8,6*(60-1)))) | BO8: =IF(F8="","",Sv_beta0+Sv_beta1*(1-EXP(-((F8-Settle)/365)/Sv_tau1))/(((F8-Settle)/365)/Sv_tau1)+Sv_beta2*((1-EXP(-((F8-Settle)/365)/Sv_tau1))/(((F8-Settle)/365)/Sv_tau1)-EXP(-((F8-Settle)/365)/Sv_tau1))+Sv_beta3*((1-EXP(-((F8-Settle)/365)/Sv_tau2))/(((F8-Settle)/365)/Sv_tau2)-EXP(-((F8-Settle)/365)/Sv_tau2))) -> 0.037002419 | BP8: =IF(G8="","",Sv_beta0+Sv_beta1*(1-EXP(-((G8-Settle)/365)/Sv_tau1))/(((G8-Settle)/365)/Sv_tau1)+Sv_beta2*((1-EXP(-((G8-Settle)/365)/Sv_tau1))/(((G8-Settle)/365)/Sv_tau1)-EXP(-((G8-Settle)/365)/Sv_tau1))+Sv_beta3*((1-EXP(-((G8-Settle)/365)/Sv_tau2))/(((G8-Settle)/365)/Sv_tau2)-EXP(-((G8-Settle)/365)/Sv_tau2))) | BQ8: =IF(H8="","",Sv_beta0+Sv_beta1*(1-EXP(-((H8-Settle)/365)/Sv_tau1))/(((H8-Settle)/365)/Sv_tau1)+Sv_beta2*((1-EXP(-((H8-Settle)/365)/Sv_tau1))/(((H8-Settle)/365)/Sv_tau1)-EXP(-((H8-Settle)/365)/Sv_tau1))+Sv_beta3*((1-EXP(-((H8-Settle)/365)/Sv_tau2))/(((H8-Settle)/365)/Sv_tau2)-EXP(-((H8-Settle)/365)/Sv_tau2))) | BR8: =IF(I8="","",Sv_beta0+Sv_beta1*(1-EXP(-((I8-Settle)/365)/Sv_tau1))/(((I8-Settle)/365)/Sv_tau1)+Sv_beta2*((1-EXP(-((I8-Settle)/365)/Sv_tau1))/(((I8-Settle)/365)/Sv_tau1)-EXP(-((I8-Settle)/365)/Sv_tau1))+Sv_beta3*((1-EXP(-((I8-Settle)/365)/Sv_tau2))/(((I8-Settle)/365)/Sv_tau2)-EXP(-((I8-Settle)/365)/Sv_tau2))) | BS8: =IF(J8="","",Sv_beta0+Sv_beta1*(1-EXP(-((J8-Settle)/365)/Sv_tau1))/(((J8-Settle)/365)/Sv_tau1)+Sv_beta2*((1-EXP(-((J8-Settle)/365)/Sv_tau1))/(((J8-Settle)/365)/Sv_tau1)-EXP(-((J8-Settle)/365)/Sv_tau1))+Sv_beta3*((1-EXP(-((J8-Settle)/365)/Sv_tau2))/(((J8-Settle)/365)/Sv_tau2)-EXP(-((J8-Settle)/365)/Sv_tau2))) | BT8: =IF(K8="","",Sv_beta0+Sv_beta1*(1-EXP(-((K8-Settle)/365)/Sv_tau1))/(((K8-Settle)/365)/Sv_tau1)+Sv_beta2*((1-EXP(-((K8-Settle)/365)/Sv_tau1))/(((K8-Settle)/365)/Sv_tau1)-EXP(-((K8-Settle)/365)/Sv_tau1))+Sv_beta3*((1-EXP(-((K8-Settle)/365)/Sv_tau2))/(((K8-Settle)/365)/Sv_tau2)-EXP(-((K8-Settle)/365)/Sv_tau2))) | BU8: =IF(L8="","",Sv_beta0+Sv_beta1*(1-EXP(-((L8-Settle)/365)/Sv_tau1))/(((L8-Settle)/365)/Sv_tau1)+Sv_beta2*((1-EXP(-((L8-Settle)/365)/Sv_tau1))/(((L8-Settle)/365)/Sv_tau1)-EXP(-((L8-Settle)/365)/Sv_tau1))+Sv_beta3*((1-EXP(-((L8-Settle)/365)/Sv_tau2))/(((L8-Settle)/365)/Sv_tau2)-EXP(-((L8-Settle)/365)/Sv_tau2))) | BV8: =IF(M8="","",Sv_beta0+Sv_beta1*(1-EXP(-((M8-Settle)/365)/Sv_tau1))/(((M8-Settle)/365)/Sv_tau1)+Sv_beta2*((1-EXP(-((M8-Settle)/365)/Sv_tau1))/(((M8-Settle)/365)/Sv_tau1)-EXP(-((M8-Settle)/365)/Sv_tau1))+Sv_beta3*((1-EXP(-((M8-Settle)/365)/Sv_tau2))/(((M8-Settle)/365)/Sv_tau2)-EXP(-((M8-Settle)/365)/Sv_tau2))) | ... DV8: =IF(BM8="","",Sv_beta0+Sv_beta1*(1-EXP(-((BM8-Settle)/365)/Sv_tau1))/(((BM8-Settle)/365)/Sv_tau1)+Sv_beta2*((1-EXP(-((BM8-Settle)/365)/Sv_tau1))/(((BM8-Settle)/365)/Sv_tau1)-EXP(-((BM8-Settle)/365)/Sv_tau1))+Sv_beta3*((1-EXP(-((BM8-Settle)/365)/Sv_tau2))/(((BM8-Settle)/365)/Sv_tau2)-EXP(-((BM8-Settle)/365)/Sv_tau2))) | DX8: =IF(F8="",0,($C8/2+IF(1=$D8,100,0))*EXP(-BO8*((F8-Settle)/365))) -> 101.92945 | DY8: =IF(G8="",0,($C8/2+IF(2=$D8,100,0))*EXP(-BP8*((G8-Settle)/365))) -> 0 | DZ8: =IF(H8="",0,($C8/2+IF(3=$D8,100,0))*EXP(-BQ8*((H8-Settle)/365))) -> 0 | EA8: =IF(I8="",0,($C8/2+IF(4=$D8,100,0))*EXP(-BR8*((I8-Settle)/365))) -> 0 | EB8: =IF(J8="",0,($C8/2+IF(5=$D8,100,0))*EXP(-BS8*((J8-Settle)/365))) -> 0 | EC8: =IF(K8="",0,($C8/2+IF(6=$D8,100,0))*EXP(-BT8*((K8-Settle)/365))) -> 0 | ED8: =IF(L8="",0,($C8/2+IF(7=$D8,100,0))*EXP(-BU8*((L8-Settle)/365))) -> 0 | EE8: =IF(M8="",0,($C8/2+IF(8=$D8,100,0))*EXP(-BV8*((M8-Settle)/365))) -> 0 | EF8: =IF(N8="",0,($C8/2+IF(9=$D8,100,0))*EXP(-BW8*((N8-Settle)/365))) -> 0 | EG8: =IF(O8="",0,($C8/2+IF(10=$D8,100,0))*EXP(-BX8*((O8-Settle)/365))) -> 0 | EH8: =IF(P8="",0,($C8/2+IF(11=$D8,100,0))*EXP(-BY8*((P8-Settle)/365))) -> 0 | EI8: =IF(Q8="",0,($C8/2+IF(12=$D8,100,0))*EXP(-BZ8*((Q8-Settle)/365))) -> 0 | EJ8: =IF(R8="",0,($C8/2+IF(13=$D8,100,0))*EXP(-CA8*((R8-Settle)/365))) -> 0 | EK8: =IF(S8="",0,($C8/2+IF(14=$D8,100,0))*EXP(-CB8*((S8-Settle)/365))) -> 0 | EL8: =IF(T8="",0,($C8/2+IF(15=$D8,100,0))*EXP(-CC8*((T8-Settle)/365))) -> 0 | EM8: =IF(U8="",0,($C8/2+IF(16=$D8,100,0))*EXP(-CD8*((U8-Settle)/365))) -> 0 | EN8: =IF(V8="",0,($C8/2+IF(17=$D8,100,0))*EXP(-CE8*((V8-Settle)/365))) -> 0 | EO8: =IF(W8="",0,($C8/2+IF(18=$D8,100,0))*EXP(-CF8*((W8-Settle)/365))) -> 0 | EP8: =IF(X8="",0,($C8/2+IF(19=$D8,100,0))*EXP(-CG8*((X8-Settle)/365))) -> 0 | EQ8: =IF(Y8="",0,($C8/2+IF(20=$D8,100,0))*EXP(-CH8*((Y8-Settle)/365))) -> 0 | ER8: =IF(Z8="",0,($C8/2+IF(21=$D8,100,0))*EXP(-CI8*((Z8-Settle)/365))) -> 0 | ES8: =IF(AA8="",0,($C8/2+IF(22=$D8,100,0))*EXP(-CJ8*((AA8-Settle)/365))) -> 0 | ET8: =IF(AB8="",0,($C8/2+IF(23=$D8,100,0))*EXP(-CK8*((AB8-Settle)/365))) -> 0 | EU8: =IF(AC8="",0,($C8/2+IF(24=$D8,100,0))*EXP(-CL8*((AC8-Settle)/365))) -> 0 | EV8: =IF(AD8="",0,($C8/2+IF(25=$D8,100,0))*EXP(-CM8*((AD8-Settle)/365))) -> 0 | EW8: =IF(AE8="",0,($C8/2+IF(26=$D8,100,0))*EXP(-CN8*((AE8-Settle)/365))) -> 0 | EX8: =IF(AF8="",0,($C8/2+IF(27=$D8,100,0))*EXP(-CO8*((AF8-Settle)/365))) -> 0 | EY8: =IF(AG8="",0,($C8/2+IF(28=$D8,100,0))*EXP(-CP8*((AG8-Settle)/365))) -> 0 | EZ8: =IF(AH8="",0,($C8/2+IF(29=$D8,100,0))*EXP(-CQ8*((AH8-Settle)/365))) -> 0 | FA8: =IF(AI8="",0,($C8/2+IF(30=$D8,100,0))*EXP(-CR8*((AI8-Settle)/365))) -> 0 | FB8: =IF(AJ8="",0,($C8/2+IF(31=$D8,100,0))*EXP(-CS8*((AJ8-Settle)/365))) -> 0 | FC8: =IF(AK8="",0,($C8/2+IF(32=$D8,100,0))*EXP(-CT8*((AK8-Settle)/365))) -> 0 | FD8: =IF(AL8="",0,($C8/2+IF(33=$D8,100,0))*EXP(-CU8*((AL8-Settle)/365))) -> 0 | FE8: =IF(AM8="",0,($C8/2+IF(34=$D8,100,0))*EXP(-CV8*((AM8-Settle)/365))) -> 0 | FF8: =IF(AN8="",0,($C8/2+IF(35=$D8,100,0))*EXP(-CW8*((AN8-Settle)/365))) -> 0 | FG8: =IF(AO8="",0,($C8/2+IF(36=$D8,100,0))*EXP(-CX8*((AO8-Settle)/365))) -> 0 | FH8: =IF(AP8="",0,($C8/2+IF(37=$D8,100,0))*EXP(-CY8*((AP8-Settle)/365))) -> 0 | FI8: =IF(AQ8="",0,($C8/2+IF(38=$D8,100,0))*EXP(-CZ8*((AQ8-Settle)/365))) -> 0 | FJ8: =IF(AR8="",0,($C8/2+IF(39=$D8,100,0))*EXP(-DA8*((AR8-Settle)/365))) -> 0 | FK8: =IF(AS8="",0,($C8/2+IF(40=$D8,100,0))*EXP(-DB8*((AS8-Settle)/365))) -> 0 | FL8: =IF(AT8="",0,($C8/2+IF(41=$D8,100,0))*EXP(-DC8*((AT8-Settle)/365))) -> 0 | FM8: =IF(AU8="",0,($C8/2+IF(42=$D8,100,0))*EXP(-DD8*((AU8-Settle)/365))) -> 0 | FN8: =IF(AV8="",0,($C8/2+IF(43=$D8,100,0))*EXP(-DE8*((AV8-Settle)/365))) -> 0 | FO8: =IF(AW8="",0,($C8/2+IF(44=$D8,100,0))*EXP(-DF8*((AW8-Settle)/365))) -> 0 | FP8: =IF(AX8="",0,($C8/2+IF(45=$D8,100,0))*EXP(-DG8*((AX8-Settle)/365))) -> 0 | FQ8: =IF(AY8="",0,($C8/2+IF(46=$D8,100,0))*EXP(-DH8*((AY8-Settle)/365))) -> 0 | FR8: =IF(AZ8="",0,($C8/2+IF(47=$D8,100,0))*EXP(-DI8*((AZ8-Settle)/365))) -> 0 | FS8: =IF(BA8="",0,($C8/2+IF(48=$D8,100,0))*EXP(-DJ8*((BA8-Settle)/365))) -> 0 | FT8: =IF(BB8="",0,($C8/2+IF(49=$D8,100,0))*EXP(-DK8*((BB8-Settle)/365))) -> 0 | FU8: =IF(BC8="",0,($C8/2+IF(50=$D8,100,0))*EXP(-DL8*((BC8-Settle)/365))) -> 0 | FV8: =IF(BD8="",0,($C8/2+IF(51=$D8,100,0))*EXP(-DM8*((BD8-Settle)/365))) -> 0 | FW8: =IF(BE8="",0,($C8/2+IF(52=$D8,100,0))*EXP(-DN8*((BE8-Settle)/365))) -> 0 | FX8: =IF(BF8="",0,($C8/2+IF(53=$D8,100,0))*EXP(-DO8*((BF8-Settle)/365))) -> 0 | FY8: =IF(BG8="",0,($C8/2+IF(54=$D8,100,0))*EXP(-DP8*((BG8-Settle)/365))) -> 0 | FZ8: =IF(BH8="",0,($C8/2+IF(55=$D8,100,0))*EXP(-DQ8*((BH8-Settle)/365))) -> 0 | GA8: =IF(BI8="",0,($C8/2+IF(56=$D8,100,0))*EXP(-DR8*((BI8-Settle)/365))) -> 0 | GB8: =IF(BJ8="",0,($C8/2+IF(57=$D8,100,0))*EXP(-DS8*((BJ8-Settle)/365))) -> 0 | GC8: =IF(BK8="",0,($C8/2+IF(58=$D8,100,0))*EXP(-DT8*((BK8-Settle)/365))) -> 0 | GD8: =IF(BL8="",0,($C8/2+IF(59=$D8,100,0))*EXP(-DU8*((BL8-Settle)/365))) -> 0 | GE8: =IF(BM8="",0,($C8/2+IF(60=$D8,100,0))*EXP(-DV8*((BM8-Settle)/365))) -> 0
A9: 6 | B9: =Bonds!B9 -> 46326 | C9: =Bonds!C9 -> 1.125 | D9: =Bonds!Q9 -> 1 | E9: =IF(DAY(B9)=DAY(EOMONTH(B9,0)),1,0) -> 1 | F9: =IF(1>$D9,"",IF($E9=1,EOMONTH(EDATE(Bonds!$I9,6*(1-1)),0),EDATE(Bonds!$I9,6*(1-1)))) -> 46326 | G9: =IF(2>$D9,"",IF($E9=1,EOMONTH(EDATE(Bonds!$I9,6*(2-1)),0),EDATE(Bonds!$I9,6*(2-1)))) | H9: =IF(3>$D9,"",IF($E9=1,EOMONTH(EDATE(Bonds!$I9,6*(3-1)),0),EDATE(Bonds!$I9,6*(3-1)))) | I9: =IF(4>$D9,"",IF($E9=1,EOMONTH(EDATE(Bonds!$I9,6*(4-1)),0),EDATE(Bonds!$I9,6*(4-1)))) | J9: =IF(5>$D9,"",IF($E9=1,EOMONTH(EDATE(Bonds!$I9,6*(5-1)),0),EDATE(Bonds!$I9,6*(5-1)))) | K9: =IF(6>$D9,"",IF($E9=1,EOMONTH(EDATE(Bonds!$I9,6*(6-1)),0),EDATE(Bonds!$I9,6*(6-1)))) | L9: =IF(7>$D9,"",IF($E9=1,EOMONTH(EDATE(Bonds!$I9,6*(7-1)),0),EDATE(Bonds!$I9,6*(7-1)))) | M9: =IF(8>$D9,"",IF($E9=1,EOMONTH(EDATE(Bonds!$I9,6*(8-1)),0),EDATE(Bonds!$I9,6*(8-1)))) | N9: =IF(9>$D9,"",IF($E9=1,EOMONTH(EDATE(Bonds!$I9,6*(9-1)),0),EDATE(Bonds!$I9,6*(9-1)))) | O9: =IF(10>$D9,"",IF($E9=1,EOMONTH(EDATE(Bonds!$I9,6*(10-1)),0),EDATE(Bonds!$I9,6*(10-1)))) | P9: =IF(11>$D9,"",IF($E9=1,EOMONTH(EDATE(Bonds!$I9,6*(11-1)),0),EDATE(Bonds!$I9,6*(11-1)))) | Q9: =IF(12>$D9,"",IF($E9=1,EOMONTH(EDATE(Bonds!$I9,6*(12-1)),0),EDATE(Bonds!$I9,6*(12-1)))) | R9: =IF(13>$D9,"",IF($E9=1,EOMONTH(EDATE(Bonds!$I9,6*(13-1)),0),EDATE(Bonds!$I9,6*(13-1)))) | S9: =IF(14>$D9,"",IF($E9=1,EOMONTH(EDATE(Bonds!$I9,6*(14-1)),0),EDATE(Bonds!$I9,6*(14-1)))) | T9: =IF(15>$D9,"",IF($E9=1,EOMONTH(EDATE(Bonds!$I9,6*(15-1)),0),EDATE(Bonds!$I9,6*(15-1)))) | U9: =IF(16>$D9,"",IF($E9=1,EOMONTH(EDATE(Bonds!$I9,6*(16-1)),0),EDATE(Bonds!$I9,6*(16-1)))) | V9: =IF(17>$D9,"",IF($E9=1,EOMONTH(EDATE(Bonds!$I9,6*(17-1)),0),EDATE(Bonds!$I9,6*(17-1)))) | W9: =IF(18>$D9,"",IF($E9=1,EOMONTH(EDATE(Bonds!$I9,6*(18-1)),0),EDATE(Bonds!$I9,6*(18-1)))) | X9: =IF(19>$D9,"",IF($E9=1,EOMONTH(EDATE(Bonds!$I9,6*(19-1)),0),EDATE(Bonds!$I9,6*(19-1)))) | Y9: =IF(20>$D9,"",IF($E9=1,EOMONTH(EDATE(Bonds!$I9,6*(20-1)),0),EDATE(Bonds!$I9,6*(20-1)))) | Z9: =IF(21>$D9,"",IF($E9=1,EOMONTH(EDATE(Bonds!$I9,6*(21-1)),0),EDATE(Bonds!$I9,6*(21-1)))) | AA9: =IF(22>$D9,"",IF($E9=1,EOMONTH(EDATE(Bonds!$I9,6*(22-1)),0),EDATE(Bonds!$I9,6*(22-1)))) | AB9: =IF(23>$D9,"",IF($E9=1,EOMONTH(EDATE(Bonds!$I9,6*(23-1)),0),EDATE(Bonds!$I9,6*(23-1)))) | AC9: =IF(24>$D9,"",IF($E9=1,EOMONTH(EDATE(Bonds!$I9,6*(24-1)),0),EDATE(Bonds!$I9,6*(24-1)))) | AD9: =IF(25>$D9,"",IF($E9=1,EOMONTH(EDATE(Bonds!$I9,6*(25-1)),0),EDATE(Bonds!$I9,6*(25-1)))) | AE9: =IF(26>$D9,"",IF($E9=1,EOMONTH(EDATE(Bonds!$I9,6*(26-1)),0),EDATE(Bonds!$I9,6*(26-1)))) | AF9: =IF(27>$D9,"",IF($E9=1,EOMONTH(EDATE(Bonds!$I9,6*(27-1)),0),EDATE(Bonds!$I9,6*(27-1)))) | AG9: =IF(28>$D9,"",IF($E9=1,EOMONTH(EDATE(Bonds!$I9,6*(28-1)),0),EDATE(Bonds!$I9,6*(28-1)))) | AH9: =IF(29>$D9,"",IF($E9=1,EOMONTH(EDATE(Bonds!$I9,6*(29-1)),0),EDATE(Bonds!$I9,6*(29-1)))) | AI9: =IF(30>$D9,"",IF($E9=1,EOMONTH(EDATE(Bonds!$I9,6*(30-1)),0),EDATE(Bonds!$I9,6*(30-1)))) | AJ9: =IF(31>$D9,"",IF($E9=1,EOMONTH(EDATE(Bonds!$I9,6*(31-1)),0),EDATE(Bonds!$I9,6*(31-1)))) | AK9: =IF(32>$D9,"",IF($E9=1,EOMONTH(EDATE(Bonds!$I9,6*(32-1)),0),EDATE(Bonds!$I9,6*(32-1)))) | AL9: =IF(33>$D9,"",IF($E9=1,EOMONTH(EDATE(Bonds!$I9,6*(33-1)),0),EDATE(Bonds!$I9,6*(33-1)))) | AM9: =IF(34>$D9,"",IF($E9=1,EOMONTH(EDATE(Bonds!$I9,6*(34-1)),0),EDATE(Bonds!$I9,6*(34-1)))) | AN9: =IF(35>$D9,"",IF($E9=1,EOMONTH(EDATE(Bonds!$I9,6*(35-1)),0),EDATE(Bonds!$I9,6*(35-1)))) | AO9: =IF(36>$D9,"",IF($E9=1,EOMONTH(EDATE(Bonds!$I9,6*(36-1)),0),EDATE(Bonds!$I9,6*(36-1)))) | AP9: =IF(37>$D9,"",IF($E9=1,EOMONTH(EDATE(Bonds!$I9,6*(37-1)),0),EDATE(Bonds!$I9,6*(37-1)))) | AQ9: =IF(38>$D9,"",IF($E9=1,EOMONTH(EDATE(Bonds!$I9,6*(38-1)),0),EDATE(Bonds!$I9,6*(38-1)))) | AR9: =IF(39>$D9,"",IF($E9=1,EOMONTH(EDATE(Bonds!$I9,6*(39-1)),0),EDATE(Bonds!$I9,6*(39-1)))) | AS9: =IF(40>$D9,"",IF($E9=1,EOMONTH(EDATE(Bonds!$I9,6*(40-1)),0),EDATE(Bonds!$I9,6*(40-1)))) | AT9: =IF(41>$D9,"",IF($E9=1,EOMONTH(EDATE(Bonds!$I9,6*(41-1)),0),EDATE(Bonds!$I9,6*(41-1)))) | AU9: =IF(42>$D9,"",IF($E9=1,EOMONTH(EDATE(Bonds!$I9,6*(42-1)),0),EDATE(Bonds!$I9,6*(42-1)))) | AV9: =IF(43>$D9,"",IF($E9=1,EOMONTH(EDATE(Bonds!$I9,6*(43-1)),0),EDATE(Bonds!$I9,6*(43-1)))) | AW9: =IF(44>$D9,"",IF($E9=1,EOMONTH(EDATE(Bonds!$I9,6*(44-1)),0),EDATE(Bonds!$I9,6*(44-1)))) | AX9: =IF(45>$D9,"",IF($E9=1,EOMONTH(EDATE(Bonds!$I9,6*(45-1)),0),EDATE(Bonds!$I9,6*(45-1)))) | AY9: =IF(46>$D9,"",IF($E9=1,EOMONTH(EDATE(Bonds!$I9,6*(46-1)),0),EDATE(Bonds!$I9,6*(46-1)))) | AZ9: =IF(47>$D9,"",IF($E9=1,EOMONTH(EDATE(Bonds!$I9,6*(47-1)),0),EDATE(Bonds!$I9,6*(47-1)))) | BA9: =IF(48>$D9,"",IF($E9=1,EOMONTH(EDATE(Bonds!$I9,6*(48-1)),0),EDATE(Bonds!$I9,6*(48-1)))) | BB9: =IF(49>$D9,"",IF($E9=1,EOMONTH(EDATE(Bonds!$I9,6*(49-1)),0),EDATE(Bonds!$I9,6*(49-1)))) | BC9: =IF(50>$D9,"",IF($E9=1,EOMONTH(EDATE(Bonds!$I9,6*(50-1)),0),EDATE(Bonds!$I9,6*(50-1)))) | BD9: =IF(51>$D9,"",IF($E9=1,EOMONTH(EDATE(Bonds!$I9,6*(51-1)),0),EDATE(Bonds!$I9,6*(51-1)))) | BE9: =IF(52>$D9,"",IF($E9=1,EOMONTH(EDATE(Bonds!$I9,6*(52-1)),0),EDATE(Bonds!$I9,6*(52-1)))) | BF9: =IF(53>$D9,"",IF($E9=1,EOMONTH(EDATE(Bonds!$I9,6*(53-1)),0),EDATE(Bonds!$I9,6*(53-1)))) | BG9: =IF(54>$D9,"",IF($E9=1,EOMONTH(EDATE(Bonds!$I9,6*(54-1)),0),EDATE(Bonds!$I9,6*(54-1)))) | BH9: =IF(55>$D9,"",IF($E9=1,EOMONTH(EDATE(Bonds!$I9,6*(55-1)),0),EDATE(Bonds!$I9,6*(55-1)))) | BI9: =IF(56>$D9,"",IF($E9=1,EOMONTH(EDATE(Bonds!$I9,6*(56-1)),0),EDATE(Bonds!$I9,6*(56-1)))) | BJ9: =IF(57>$D9,"",IF($E9=1,EOMONTH(EDATE(Bonds!$I9,6*(57-1)),0),EDATE(Bonds!$I9,6*(57-1)))) | BK9: =IF(58>$D9,"",IF($E9=1,EOMONTH(EDATE(Bonds!$I9,6*(58-1)),0),EDATE(Bonds!$I9,6*(58-1)))) | BL9: =IF(59>$D9,"",IF($E9=1,EOMONTH(EDATE(Bonds!$I9,6*(59-1)),0),EDATE(Bonds!$I9,6*(59-1)))) | BM9: =IF(60>$D9,"",IF($E9=1,EOMONTH(EDATE(Bonds!$I9,6*(60-1)),0),EDATE(Bonds!$I9,6*(60-1)))) | BO9: =IF(F9="","",Sv_beta0+Sv_beta1*(1-EXP(-((F9-Settle)/365)/Sv_tau1))/(((F9-Settle)/365)/Sv_tau1)+Sv_beta2*((1-EXP(-((F9-Settle)/365)/Sv_tau1))/(((F9-Settle)/365)/Sv_tau1)-EXP(-((F9-Settle)/365)/Sv_tau1))+Sv_beta3*((1-EXP(-((F9-Settle)/365)/Sv_tau2))/(((F9-Settle)/365)/Sv_tau2)-EXP(-((F9-Settle)/365)/Sv_tau2))) -> 0.037298134 | BP9: =IF(G9="","",Sv_beta0+Sv_beta1*(1-EXP(-((G9-Settle)/365)/Sv_tau1))/(((G9-Settle)/365)/Sv_tau1)+Sv_beta2*((1-EXP(-((G9-Settle)/365)/Sv_tau1))/(((G9-Settle)/365)/Sv_tau1)-EXP(-((G9-Settle)/365)/Sv_tau1))+Sv_beta3*((1-EXP(-((G9-Settle)/365)/Sv_tau2))/(((G9-Settle)/365)/Sv_tau2)-EXP(-((G9-Settle)/365)/Sv_tau2))) | BQ9: =IF(H9="","",Sv_beta0+Sv_beta1*(1-EXP(-((H9-Settle)/365)/Sv_tau1))/(((H9-Settle)/365)/Sv_tau1)+Sv_beta2*((1-EXP(-((H9-Settle)/365)/Sv_tau1))/(((H9-Settle)/365)/Sv_tau1)-EXP(-((H9-Settle)/365)/Sv_tau1))+Sv_beta3*((1-EXP(-((H9-Settle)/365)/Sv_tau2))/(((H9-Settle)/365)/Sv_tau2)-EXP(-((H9-Settle)/365)/Sv_tau2))) | BR9: =IF(I9="","",Sv_beta0+Sv_beta1*(1-EXP(-((I9-Settle)/365)/Sv_tau1))/(((I9-Settle)/365)/Sv_tau1)+Sv_beta2*((1-EXP(-((I9-Settle)/365)/Sv_tau1))/(((I9-Settle)/365)/Sv_tau1)-EXP(-((I9-Settle)/365)/Sv_tau1))+Sv_beta3*((1-EXP(-((I9-Settle)/365)/Sv_tau2))/(((I9-Settle)/365)/Sv_tau2)-EXP(-((I9-Settle)/365)/Sv_tau2))) | BS9: =IF(J9="","",Sv_beta0+Sv_beta1*(1-EXP(-((J9-Settle)/365)/Sv_tau1))/(((J9-Settle)/365)/Sv_tau1)+Sv_beta2*((1-EXP(-((J9-Settle)/365)/Sv_tau1))/(((J9-Settle)/365)/Sv_tau1)-EXP(-((J9-Settle)/365)/Sv_tau1))+Sv_beta3*((1-EXP(-((J9-Settle)/365)/Sv_tau2))/(((J9-Settle)/365)/Sv_tau2)-EXP(-((J9-Settle)/365)/Sv_tau2))) | BT9: =IF(K9="","",Sv_beta0+Sv_beta1*(1-EXP(-((K9-Settle)/365)/Sv_tau1))/(((K9-Settle)/365)/Sv_tau1)+Sv_beta2*((1-EXP(-((K9-Settle)/365)/Sv_tau1))/(((K9-Settle)/365)/Sv_tau1)-EXP(-((K9-Settle)/365)/Sv_tau1))+Sv_beta3*((1-EXP(-((K9-Settle)/365)/Sv_tau2))/(((K9-Settle)/365)/Sv_tau2)-EXP(-((K9-Settle)/365)/Sv_tau2))) | BU9: =IF(L9="","",Sv_beta0+Sv_beta1*(1-EXP(-((L9-Settle)/365)/Sv_tau1))/(((L9-Settle)/365)/Sv_tau1)+Sv_beta2*((1-EXP(-((L9-Settle)/365)/Sv_tau1))/(((L9-Settle)/365)/Sv_tau1)-EXP(-((L9-Settle)/365)/Sv_tau1))+Sv_beta3*((1-EXP(-((L9-Settle)/365)/Sv_tau2))/(((L9-Settle)/365)/Sv_tau2)-EXP(-((L9-Settle)/365)/Sv_tau2))) | BV9: =IF(M9="","",Sv_beta0+Sv_beta1*(1-EXP(-((M9-Settle)/365)/Sv_tau1))/(((M9-Settle)/365)/Sv_tau1)+Sv_beta2*((1-EXP(-((M9-Settle)/365)/Sv_tau1))/(((M9-Settle)/365)/Sv_tau1)-EXP(-((M9-Settle)/365)/Sv_tau1))+Sv_beta3*((1-EXP(-((M9-Settle)/365)/Sv_tau2))/(((M9-Settle)/365)/Sv_tau2)-EXP(-((M9-Settle)/365)/Sv_tau2))) | ... DV9: =IF(BM9="","",Sv_beta0+Sv_beta1*(1-EXP(-((BM9-Settle)/365)/Sv_tau1))/(((BM9-Settle)/365)/Sv_tau1)+Sv_beta2*((1-EXP(-((BM9-Settle)/365)/Sv_tau1))/(((BM9-Settle)/365)/Sv_tau1)-EXP(-((BM9-Settle)/365)/Sv_tau1))+Sv_beta3*((1-EXP(-((BM9-Settle)/365)/Sv_tau2))/(((BM9-Settle)/365)/Sv_tau2)-EXP(-((BM9-Settle)/365)/Sv_tau2))) | DX9: =IF(F9="",0,($C9/2+IF(1=$D9,100,0))*EXP(-BO9*((F9-Settle)/365))) -> 100.01934 | DY9: =IF(G9="",0,($C9/2+IF(2=$D9,100,0))*EXP(-BP9*((G9-Settle)/365))) -> 0 | DZ9: =IF(H9="",0,($C9/2+IF(3=$D9,100,0))*EXP(-BQ9*((H9-Settle)/365))) -> 0 | EA9: =IF(I9="",0,($C9/2+IF(4=$D9,100,0))*EXP(-BR9*((I9-Settle)/365))) -> 0 | EB9: =IF(J9="",0,($C9/2+IF(5=$D9,100,0))*EXP(-BS9*((J9-Settle)/365))) -> 0 | EC9: =IF(K9="",0,($C9/2+IF(6=$D9,100,0))*EXP(-BT9*((K9-Settle)/365))) -> 0 | ED9: =IF(L9="",0,($C9/2+IF(7=$D9,100,0))*EXP(-BU9*((L9-Settle)/365))) -> 0 | EE9: =IF(M9="",0,($C9/2+IF(8=$D9,100,0))*EXP(-BV9*((M9-Settle)/365))) -> 0 | EF9: =IF(N9="",0,($C9/2+IF(9=$D9,100,0))*EXP(-BW9*((N9-Settle)/365))) -> 0 | EG9: =IF(O9="",0,($C9/2+IF(10=$D9,100,0))*EXP(-BX9*((O9-Settle)/365))) -> 0 | EH9: =IF(P9="",0,($C9/2+IF(11=$D9,100,0))*EXP(-BY9*((P9-Settle)/365))) -> 0 | EI9: =IF(Q9="",0,($C9/2+IF(12=$D9,100,0))*EXP(-BZ9*((Q9-Settle)/365))) -> 0 | EJ9: =IF(R9="",0,($C9/2+IF(13=$D9,100,0))*EXP(-CA9*((R9-Settle)/365))) -> 0 | EK9: =IF(S9="",0,($C9/2+IF(14=$D9,100,0))*EXP(-CB9*((S9-Settle)/365))) -> 0 | EL9: =IF(T9="",0,($C9/2+IF(15=$D9,100,0))*EXP(-CC9*((T9-Settle)/365))) -> 0 | EM9: =IF(U9="",0,($C9/2+IF(16=$D9,100,0))*EXP(-CD9*((U9-Settle)/365))) -> 0 | EN9: =IF(V9="",0,($C9/2+IF(17=$D9,100,0))*EXP(-CE9*((V9-Settle)/365))) -> 0 | EO9: =IF(W9="",0,($C9/2+IF(18=$D9,100,0))*EXP(-CF9*((W9-Settle)/365))) -> 0 | EP9: =IF(X9="",0,($C9/2+IF(19=$D9,100,0))*EXP(-CG9*((X9-Settle)/365))) -> 0 | EQ9: =IF(Y9="",0,($C9/2+IF(20=$D9,100,0))*EXP(-CH9*((Y9-Settle)/365))) -> 0 | ER9: =IF(Z9="",0,($C9/2+IF(21=$D9,100,0))*EXP(-CI9*((Z9-Settle)/365))) -> 0 | ES9: =IF(AA9="",0,($C9/2+IF(22=$D9,100,0))*EXP(-CJ9*((AA9-Settle)/365))) -> 0 | ET9: =IF(AB9="",0,($C9/2+IF(23=$D9,100,0))*EXP(-CK9*((AB9-Settle)/365))) -> 0 | EU9: =IF(AC9="",0,($C9/2+IF(24=$D9,100,0))*EXP(-CL9*((AC9-Settle)/365))) -> 0 | EV9: =IF(AD9="",0,($C9/2+IF(25=$D9,100,0))*EXP(-CM9*((AD9-Settle)/365))) -> 0 | EW9: =IF(AE9="",0,($C9/2+IF(26=$D9,100,0))*EXP(-CN9*((AE9-Settle)/365))) -> 0 | EX9: =IF(AF9="",0,($C9/2+IF(27=$D9,100,0))*EXP(-CO9*((AF9-Settle)/365))) -> 0 | EY9: =IF(AG9="",0,($C9/2+IF(28=$D9,100,0))*EXP(-CP9*((AG9-Settle)/365))) -> 0 | EZ9: =IF(AH9="",0,($C9/2+IF(29=$D9,100,0))*EXP(-CQ9*((AH9-Settle)/365))) -> 0 | FA9: =IF(AI9="",0,($C9/2+IF(30=$D9,100,0))*EXP(-CR9*((AI9-Settle)/365))) -> 0 | FB9: =IF(AJ9="",0,($C9/2+IF(31=$D9,100,0))*EXP(-CS9*((AJ9-Settle)/365))) -> 0 | FC9: =IF(AK9="",0,($C9/2+IF(32=$D9,100,0))*EXP(-CT9*((AK9-Settle)/365))) -> 0 | FD9: =IF(AL9="",0,($C9/2+IF(33=$D9,100,0))*EXP(-CU9*((AL9-Settle)/365))) -> 0 | FE9: =IF(AM9="",0,($C9/2+IF(34=$D9,100,0))*EXP(-CV9*((AM9-Settle)/365))) -> 0 | FF9: =IF(AN9="",0,($C9/2+IF(35=$D9,100,0))*EXP(-CW9*((AN9-Settle)/365))) -> 0 | FG9: =IF(AO9="",0,($C9/2+IF(36=$D9,100,0))*EXP(-CX9*((AO9-Settle)/365))) -> 0 | FH9: =IF(AP9="",0,($C9/2+IF(37=$D9,100,0))*EXP(-CY9*((AP9-Settle)/365))) -> 0 | FI9: =IF(AQ9="",0,($C9/2+IF(38=$D9,100,0))*EXP(-CZ9*((AQ9-Settle)/365))) -> 0 | FJ9: =IF(AR9="",0,($C9/2+IF(39=$D9,100,0))*EXP(-DA9*((AR9-Settle)/365))) -> 0 | FK9: =IF(AS9="",0,($C9/2+IF(40=$D9,100,0))*EXP(-DB9*((AS9-Settle)/365))) -> 0 | FL9: =IF(AT9="",0,($C9/2+IF(41=$D9,100,0))*EXP(-DC9*((AT9-Settle)/365))) -> 0 | FM9: =IF(AU9="",0,($C9/2+IF(42=$D9,100,0))*EXP(-DD9*((AU9-Settle)/365))) -> 0 | FN9: =IF(AV9="",0,($C9/2+IF(43=$D9,100,0))*EXP(-DE9*((AV9-Settle)/365))) -> 0 | FO9: =IF(AW9="",0,($C9/2+IF(44=$D9,100,0))*EXP(-DF9*((AW9-Settle)/365))) -> 0 | FP9: =IF(AX9="",0,($C9/2+IF(45=$D9,100,0))*EXP(-DG9*((AX9-Settle)/365))) -> 0 | FQ9: =IF(AY9="",0,($C9/2+IF(46=$D9,100,0))*EXP(-DH9*((AY9-Settle)/365))) -> 0 | FR9: =IF(AZ9="",0,($C9/2+IF(47=$D9,100,0))*EXP(-DI9*((AZ9-Settle)/365))) -> 0 | FS9: =IF(BA9="",0,($C9/2+IF(48=$D9,100,0))*EXP(-DJ9*((BA9-Settle)/365))) -> 0 | FT9: =IF(BB9="",0,($C9/2+IF(49=$D9,100,0))*EXP(-DK9*((BB9-Settle)/365))) -> 0 | FU9: =IF(BC9="",0,($C9/2+IF(50=$D9,100,0))*EXP(-DL9*((BC9-Settle)/365))) -> 0 | FV9: =IF(BD9="",0,($C9/2+IF(51=$D9,100,0))*EXP(-DM9*((BD9-Settle)/365))) -> 0 | FW9: =IF(BE9="",0,($C9/2+IF(52=$D9,100,0))*EXP(-DN9*((BE9-Settle)/365))) -> 0 | FX9: =IF(BF9="",0,($C9/2+IF(53=$D9,100,0))*EXP(-DO9*((BF9-Settle)/365))) -> 0 | FY9: =IF(BG9="",0,($C9/2+IF(54=$D9,100,0))*EXP(-DP9*((BG9-Settle)/365))) -> 0 | FZ9: =IF(BH9="",0,($C9/2+IF(55=$D9,100,0))*EXP(-DQ9*((BH9-Settle)/365))) -> 0 | GA9: =IF(BI9="",0,($C9/2+IF(56=$D9,100,0))*EXP(-DR9*((BI9-Settle)/365))) -> 0 | GB9: =IF(BJ9="",0,($C9/2+IF(57=$D9,100,0))*EXP(-DS9*((BJ9-Settle)/365))) -> 0 | GC9: =IF(BK9="",0,($C9/2+IF(58=$D9,100,0))*EXP(-DT9*((BK9-Settle)/365))) -> 0 | GD9: =IF(BL9="",0,($C9/2+IF(59=$D9,100,0))*EXP(-DU9*((BL9-Settle)/365))) -> 0 | GE9: =IF(BM9="",0,($C9/2+IF(60=$D9,100,0))*EXP(-DV9*((BM9-Settle)/365))) -> 0
A10: 7 | B10: =Bonds!B10 -> 46326 | C10: =Bonds!C10 -> 1.625 | D10: =Bonds!Q10 -> 1 | E10: =IF(DAY(B10)=DAY(EOMONTH(B10,0)),1,0) -> 1 | F10: =IF(1>$D10,"",IF($E10=1,EOMONTH(EDATE(Bonds!$I10,6*(1-1)),0),EDATE(Bonds!$I10,6*(1-1)))) -> 46326 | G10: =IF(2>$D10,"",IF($E10=1,EOMONTH(EDATE(Bonds!$I10,6*(2-1)),0),EDATE(Bonds!$I10,6*(2-1)))) | H10: =IF(3>$D10,"",IF($E10=1,EOMONTH(EDATE(Bonds!$I10,6*(3-1)),0),EDATE(Bonds!$I10,6*(3-1)))) | I10: =IF(4>$D10,"",IF($E10=1,EOMONTH(EDATE(Bonds!$I10,6*(4-1)),0),EDATE(Bonds!$I10,6*(4-1)))) | J10: =IF(5>$D10,"",IF($E10=1,EOMONTH(EDATE(Bonds!$I10,6*(5-1)),0),EDATE(Bonds!$I10,6*(5-1)))) | K10: =IF(6>$D10,"",IF($E10=1,EOMONTH(EDATE(Bonds!$I10,6*(6-1)),0),EDATE(Bonds!$I10,6*(6-1)))) | L10: =IF(7>$D10,"",IF($E10=1,EOMONTH(EDATE(Bonds!$I10,6*(7-1)),0),EDATE(Bonds!$I10,6*(7-1)))) | M10: =IF(8>$D10,"",IF($E10=1,EOMONTH(EDATE(Bonds!$I10,6*(8-1)),0),EDATE(Bonds!$I10,6*(8-1)))) | N10: =IF(9>$D10,"",IF($E10=1,EOMONTH(EDATE(Bonds!$I10,6*(9-1)),0),EDATE(Bonds!$I10,6*(9-1)))) | O10: =IF(10>$D10,"",IF($E10=1,EOMONTH(EDATE(Bonds!$I10,6*(10-1)),0),EDATE(Bonds!$I10,6*(10-1)))) | P10: =IF(11>$D10,"",IF($E10=1,EOMONTH(EDATE(Bonds!$I10,6*(11-1)),0),EDATE(Bonds!$I10,6*(11-1)))) | Q10: =IF(12>$D10,"",IF($E10=1,EOMONTH(EDATE(Bonds!$I10,6*(12-1)),0),EDATE(Bonds!$I10,6*(12-1)))) | R10: =IF(13>$D10,"",IF($E10=1,EOMONTH(EDATE(Bonds!$I10,6*(13-1)),0),EDATE(Bonds!$I10,6*(13-1)))) | S10: =IF(14>$D10,"",IF($E10=1,EOMONTH(EDATE(Bonds!$I10,6*(14-1)),0),EDATE(Bonds!$I10,6*(14-1)))) | T10: =IF(15>$D10,"",IF($E10=1,EOMONTH(EDATE(Bonds!$I10,6*(15-1)),0),EDATE(Bonds!$I10,6*(15-1)))) | U10: =IF(16>$D10,"",IF($E10=1,EOMONTH(EDATE(Bonds!$I10,6*(16-1)),0),EDATE(Bonds!$I10,6*(16-1)))) | V10: =IF(17>$D10,"",IF($E10=1,EOMONTH(EDATE(Bonds!$I10,6*(17-1)),0),EDATE(Bonds!$I10,6*(17-1)))) | W10: =IF(18>$D10,"",IF($E10=1,EOMONTH(EDATE(Bonds!$I10,6*(18-1)),0),EDATE(Bonds!$I10,6*(18-1)))) | X10: =IF(19>$D10,"",IF($E10=1,EOMONTH(EDATE(Bonds!$I10,6*(19-1)),0),EDATE(Bonds!$I10,6*(19-1)))) | Y10: =IF(20>$D10,"",IF($E10=1,EOMONTH(EDATE(Bonds!$I10,6*(20-1)),0),EDATE(Bonds!$I10,6*(20-1)))) | Z10: =IF(21>$D10,"",IF($E10=1,EOMONTH(EDATE(Bonds!$I10,6*(21-1)),0),EDATE(Bonds!$I10,6*(21-1)))) | AA10: =IF(22>$D10,"",IF($E10=1,EOMONTH(EDATE(Bonds!$I10,6*(22-1)),0),EDATE(Bonds!$I10,6*(22-1)))) | AB10: =IF(23>$D10,"",IF($E10=1,EOMONTH(EDATE(Bonds!$I10,6*(23-1)),0),EDATE(Bonds!$I10,6*(23-1)))) | AC10: =IF(24>$D10,"",IF($E10=1,EOMONTH(EDATE(Bonds!$I10,6*(24-1)),0),EDATE(Bonds!$I10,6*(24-1)))) | AD10: =IF(25>$D10,"",IF($E10=1,EOMONTH(EDATE(Bonds!$I10,6*(25-1)),0),EDATE(Bonds!$I10,6*(25-1)))) | AE10: =IF(26>$D10,"",IF($E10=1,EOMONTH(EDATE(Bonds!$I10,6*(26-1)),0),EDATE(Bonds!$I10,6*(26-1)))) | AF10: =IF(27>$D10,"",IF($E10=1,EOMONTH(EDATE(Bonds!$I10,6*(27-1)),0),EDATE(Bonds!$I10,6*(27-1)))) | AG10: =IF(28>$D10,"",IF($E10=1,EOMONTH(EDATE(Bonds!$I10,6*(28-1)),0),EDATE(Bonds!$I10,6*(28-1)))) | AH10: =IF(29>$D10,"",IF($E10=1,EOMONTH(EDATE(Bonds!$I10,6*(29-1)),0),EDATE(Bonds!$I10,6*(29-1)))) | AI10: =IF(30>$D10,"",IF($E10=1,EOMONTH(EDATE(Bonds!$I10,6*(30-1)),0),EDATE(Bonds!$I10,6*(30-1)))) | AJ10: =IF(31>$D10,"",IF($E10=1,EOMONTH(EDATE(Bonds!$I10,6*(31-1)),0),EDATE(Bonds!$I10,6*(31-1)))) | AK10: =IF(32>$D10,"",IF($E10=1,EOMONTH(EDATE(Bonds!$I10,6*(32-1)),0),EDATE(Bonds!$I10,6*(32-1)))) | AL10: =IF(33>$D10,"",IF($E10=1,EOMONTH(EDATE(Bonds!$I10,6*(33-1)),0),EDATE(Bonds!$I10,6*(33-1)))) | AM10: =IF(34>$D10,"",IF($E10=1,EOMONTH(EDATE(Bonds!$I10,6*(34-1)),0),EDATE(Bonds!$I10,6*(34-1)))) | AN10: =IF(35>$D10,"",IF($E10=1,EOMONTH(EDATE(Bonds!$I10,6*(35-1)),0),EDATE(Bonds!$I10,6*(35-1)))) | AO10: =IF(36>$D10,"",IF($E10=1,EOMONTH(EDATE(Bonds!$I10,6*(36-1)),0),EDATE(Bonds!$I10,6*(36-1)))) | AP10: =IF(37>$D10,"",IF($E10=1,EOMONTH(EDATE(Bonds!$I10,6*(37-1)),0),EDATE(Bonds!$I10,6*(37-1)))) | AQ10: =IF(38>$D10,"",IF($E10=1,EOMONTH(EDATE(Bonds!$I10,6*(38-1)),0),EDATE(Bonds!$I10,6*(38-1)))) | AR10: =IF(39>$D10,"",IF($E10=1,EOMONTH(EDATE(Bonds!$I10,6*(39-1)),0),EDATE(Bonds!$I10,6*(39-1)))) | AS10: =IF(40>$D10,"",IF($E10=1,EOMONTH(EDATE(Bonds!$I10,6*(40-1)),0),EDATE(Bonds!$I10,6*(40-1)))) | AT10: =IF(41>$D10,"",IF($E10=1,EOMONTH(EDATE(Bonds!$I10,6*(41-1)),0),EDATE(Bonds!$I10,6*(41-1)))) | AU10: =IF(42>$D10,"",IF($E10=1,EOMONTH(EDATE(Bonds!$I10,6*(42-1)),0),EDATE(Bonds!$I10,6*(42-1)))) | AV10: =IF(43>$D10,"",IF($E10=1,EOMONTH(EDATE(Bonds!$I10,6*(43-1)),0),EDATE(Bonds!$I10,6*(43-1)))) | AW10: =IF(44>$D10,"",IF($E10=1,EOMONTH(EDATE(Bonds!$I10,6*(44-1)),0),EDATE(Bonds!$I10,6*(44-1)))) | AX10: =IF(45>$D10,"",IF($E10=1,EOMONTH(EDATE(Bonds!$I10,6*(45-1)),0),EDATE(Bonds!$I10,6*(45-1)))) | AY10: =IF(46>$D10,"",IF($E10=1,EOMONTH(EDATE(Bonds!$I10,6*(46-1)),0),EDATE(Bonds!$I10,6*(46-1)))) | AZ10: =IF(47>$D10,"",IF($E10=1,EOMONTH(EDATE(Bonds!$I10,6*(47-1)),0),EDATE(Bonds!$I10,6*(47-1)))) | BA10: =IF(48>$D10,"",IF($E10=1,EOMONTH(EDATE(Bonds!$I10,6*(48-1)),0),EDATE(Bonds!$I10,6*(48-1)))) | BB10: =IF(49>$D10,"",IF($E10=1,EOMONTH(EDATE(Bonds!$I10,6*(49-1)),0),EDATE(Bonds!$I10,6*(49-1)))) | BC10: =IF(50>$D10,"",IF($E10=1,EOMONTH(EDATE(Bonds!$I10,6*(50-1)),0),EDATE(Bonds!$I10,6*(50-1)))) | BD10: =IF(51>$D10,"",IF($E10=1,EOMONTH(EDATE(Bonds!$I10,6*(51-1)),0),EDATE(Bonds!$I10,6*(51-1)))) | BE10: =IF(52>$D10,"",IF($E10=1,EOMONTH(EDATE(Bonds!$I10,6*(52-1)),0),EDATE(Bonds!$I10,6*(52-1)))) | BF10: =IF(53>$D10,"",IF($E10=1,EOMONTH(EDATE(Bonds!$I10,6*(53-1)),0),EDATE(Bonds!$I10,6*(53-1)))) | BG10: =IF(54>$D10,"",IF($E10=1,EOMONTH(EDATE(Bonds!$I10,6*(54-1)),0),EDATE(Bonds!$I10,6*(54-1)))) | BH10: =IF(55>$D10,"",IF($E10=1,EOMONTH(EDATE(Bonds!$I10,6*(55-1)),0),EDATE(Bonds!$I10,6*(55-1)))) | BI10: =IF(56>$D10,"",IF($E10=1,EOMONTH(EDATE(Bonds!$I10,6*(56-1)),0),EDATE(Bonds!$I10,6*(56-1)))) | BJ10: =IF(57>$D10,"",IF($E10=1,EOMONTH(EDATE(Bonds!$I10,6*(57-1)),0),EDATE(Bonds!$I10,6*(57-1)))) | BK10: =IF(58>$D10,"",IF($E10=1,EOMONTH(EDATE(Bonds!$I10,6*(58-1)),0),EDATE(Bonds!$I10,6*(58-1)))) | BL10: =IF(59>$D10,"",IF($E10=1,EOMONTH(EDATE(Bonds!$I10,6*(59-1)),0),EDATE(Bonds!$I10,6*(59-1)))) | BM10: =IF(60>$D10,"",IF($E10=1,EOMONTH(EDATE(Bonds!$I10,6*(60-1)),0),EDATE(Bonds!$I10,6*(60-1)))) | BO10: =IF(F10="","",Sv_beta0+Sv_beta1*(1-EXP(-((F10-Settle)/365)/Sv_tau1))/(((F10-Settle)/365)/Sv_tau1)+Sv_beta2*((1-EXP(-((F10-Settle)/365)/Sv_tau1))/(((F10-Settle)/365)/Sv_tau1)-EXP(-((F10-Settle)/365)/Sv_tau1))+Sv_beta3*((1-EXP(-((F10-Settle)/365)/Sv_tau2))/(((F10-Settle)/365)/Sv_tau2)-EXP(-((F10-Settle)/365)/Sv_tau2))) -> 0.037298134 | BP10: =IF(G10="","",Sv_beta0+Sv_beta1*(1-EXP(-((G10-Settle)/365)/Sv_tau1))/(((G10-Settle)/365)/Sv_tau1)+Sv_beta2*((1-EXP(-((G10-Settle)/365)/Sv_tau1))/(((G10-Settle)/365)/Sv_tau1)-EXP(-((G10-Settle)/365)/Sv_tau1))+Sv_beta3*((1-EXP(-((G10-Settle)/365)/Sv_tau2))/(((G10-Settle)/365)/Sv_tau2)-EXP(-((G10-Settle)/365)/Sv_tau2))) | BQ10: =IF(H10="","",Sv_beta0+Sv_beta1*(1-EXP(-((H10-Settle)/365)/Sv_tau1))/(((H10-Settle)/365)/Sv_tau1)+Sv_beta2*((1-EXP(-((H10-Settle)/365)/Sv_tau1))/(((H10-Settle)/365)/Sv_tau1)-EXP(-((H10-Settle)/365)/Sv_tau1))+Sv_beta3*((1-EXP(-((H10-Settle)/365)/Sv_tau2))/(((H10-Settle)/365)/Sv_tau2)-EXP(-((H10-Settle)/365)/Sv_tau2))) | BR10: =IF(I10="","",Sv_beta0+Sv_beta1*(1-EXP(-((I10-Settle)/365)/Sv_tau1))/(((I10-Settle)/365)/Sv_tau1)+Sv_beta2*((1-EXP(-((I10-Settle)/365)/Sv_tau1))/(((I10-Settle)/365)/Sv_tau1)-EXP(-((I10-Settle)/365)/Sv_tau1))+Sv_beta3*((1-EXP(-((I10-Settle)/365)/Sv_tau2))/(((I10-Settle)/365)/Sv_tau2)-EXP(-((I10-Settle)/365)/Sv_tau2))) | BS10: =IF(J10="","",Sv_beta0+Sv_beta1*(1-EXP(-((J10-Settle)/365)/Sv_tau1))/(((J10-Settle)/365)/Sv_tau1)+Sv_beta2*((1-EXP(-((J10-Settle)/365)/Sv_tau1))/(((J10-Settle)/365)/Sv_tau1)-EXP(-((J10-Settle)/365)/Sv_tau1))+Sv_beta3*((1-EXP(-((J10-Settle)/365)/Sv_tau2))/(((J10-Settle)/365)/Sv_tau2)-EXP(-((J10-Settle)/365)/Sv_tau2))) | BT10: =IF(K10="","",Sv_beta0+Sv_beta1*(1-EXP(-((K10-Settle)/365)/Sv_tau1))/(((K10-Settle)/365)/Sv_tau1)+Sv_beta2*((1-EXP(-((K10-Settle)/365)/Sv_tau1))/(((K10-Settle)/365)/Sv_tau1)-EXP(-((K10-Settle)/365)/Sv_tau1))+Sv_beta3*((1-EXP(-((K10-Settle)/365)/Sv_tau2))/(((K10-Settle)/365)/Sv_tau2)-EXP(-((K10-Settle)/365)/Sv_tau2))) | BU10: =IF(L10="","",Sv_beta0+Sv_beta1*(1-EXP(-((L10-Settle)/365)/Sv_tau1))/(((L10-Settle)/365)/Sv_tau1)+Sv_beta2*((1-EXP(-((L10-Settle)/365)/Sv_tau1))/(((L10-Settle)/365)/Sv_tau1)-EXP(-((L10-Settle)/365)/Sv_tau1))+Sv_beta3*((1-EXP(-((L10-Settle)/365)/Sv_tau2))/(((L10-Settle)/365)/Sv_tau2)-EXP(-((L10-Settle)/365)/Sv_tau2))) | BV10: =IF(M10="","",Sv_beta0+Sv_beta1*(1-EXP(-((M10-Settle)/365)/Sv_tau1))/(((M10-Settle)/365)/Sv_tau1)+Sv_beta2*((1-EXP(-((M10-Settle)/365)/Sv_tau1))/(((M10-Settle)/365)/Sv_tau1)-EXP(-((M10-Settle)/365)/Sv_tau1))+Sv_beta3*((1-EXP(-((M10-Settle)/365)/Sv_tau2))/(((M10-Settle)/365)/Sv_tau2)-EXP(-((M10-Settle)/365)/Sv_tau2))) | ... DV10: =IF(BM10="","",Sv_beta0+Sv_beta1*(1-EXP(-((BM10-Settle)/365)/Sv_tau1))/(((BM10-Settle)/365)/Sv_tau1)+Sv_beta2*((1-EXP(-((BM10-Settle)/365)/Sv_tau1))/(((BM10-Settle)/365)/Sv_tau1)-EXP(-((BM10-Settle)/365)/Sv_tau1))+Sv_beta3*((1-EXP(-((BM10-Settle)/365)/Sv_tau2))/(((BM10-Settle)/365)/Sv_tau2)-EXP(-((BM10-Settle)/365)/Sv_tau2))) | DX10: =IF(F10="",0,($C10/2+IF(1=$D10,100,0))*EXP(-BO10*((F10-Settle)/365))) -> 100.26799 | DY10: =IF(G10="",0,($C10/2+IF(2=$D10,100,0))*EXP(-BP10*((G10-Settle)/365))) -> 0 | DZ10: =IF(H10="",0,($C10/2+IF(3=$D10,100,0))*EXP(-BQ10*((H10-Settle)/365))) -> 0 | EA10: =IF(I10="",0,($C10/2+IF(4=$D10,100,0))*EXP(-BR10*((I10-Settle)/365))) -> 0 | EB10: =IF(J10="",0,($C10/2+IF(5=$D10,100,0))*EXP(-BS10*((J10-Settle)/365))) -> 0 | EC10: =IF(K10="",0,($C10/2+IF(6=$D10,100,0))*EXP(-BT10*((K10-Settle)/365))) -> 0 | ED10: =IF(L10="",0,($C10/2+IF(7=$D10,100,0))*EXP(-BU10*((L10-Settle)/365))) -> 0 | EE10: =IF(M10="",0,($C10/2+IF(8=$D10,100,0))*EXP(-BV10*((M10-Settle)/365))) -> 0 | EF10: =IF(N10="",0,($C10/2+IF(9=$D10,100,0))*EXP(-BW10*((N10-Settle)/365))) -> 0 | EG10: =IF(O10="",0,($C10/2+IF(10=$D10,100,0))*EXP(-BX10*((O10-Settle)/365))) -> 0 | EH10: =IF(P10="",0,($C10/2+IF(11=$D10,100,0))*EXP(-BY10*((P10-Settle)/365))) -> 0 | EI10: =IF(Q10="",0,($C10/2+IF(12=$D10,100,0))*EXP(-BZ10*((Q10-Settle)/365))) -> 0 | EJ10: =IF(R10="",0,($C10/2+IF(13=$D10,100,0))*EXP(-CA10*((R10-Settle)/365))) -> 0 | EK10: =IF(S10="",0,($C10/2+IF(14=$D10,100,0))*EXP(-CB10*((S10-Settle)/365))) -> 0 | EL10: =IF(T10="",0,($C10/2+IF(15=$D10,100,0))*EXP(-CC10*((T10-Settle)/365))) -> 0 | EM10: =IF(U10="",0,($C10/2+IF(16=$D10,100,0))*EXP(-CD10*((U10-Settle)/365))) -> 0 | EN10: =IF(V10="",0,($C10/2+IF(17=$D10,100,0))*EXP(-CE10*((V10-Settle)/365))) -> 0 | EO10: =IF(W10="",0,($C10/2+IF(18=$D10,100,0))*EXP(-CF10*((W10-Settle)/365))) -> 0 | EP10: =IF(X10="",0,($C10/2+IF(19=$D10,100,0))*EXP(-CG10*((X10-Settle)/365))) -> 0 | EQ10: =IF(Y10="",0,($C10/2+IF(20=$D10,100,0))*EXP(-CH10*((Y10-Settle)/365))) -> 0 | ER10: =IF(Z10="",0,($C10/2+IF(21=$D10,100,0))*EXP(-CI10*((Z10-Settle)/365))) -> 0 | ES10: =IF(AA10="",0,($C10/2+IF(22=$D10,100,0))*EXP(-CJ10*((AA10-Settle)/365))) -> 0 | ET10: =IF(AB10="",0,($C10/2+IF(23=$D10,100,0))*EXP(-CK10*((AB10-Settle)/365))) -> 0 | EU10: =IF(AC10="",0,($C10/2+IF(24=$D10,100,0))*EXP(-CL10*((AC10-Settle)/365))) -> 0 | EV10: =IF(AD10="",0,($C10/2+IF(25=$D10,100,0))*EXP(-CM10*((AD10-Settle)/365))) -> 0 | EW10: =IF(AE10="",0,($C10/2+IF(26=$D10,100,0))*EXP(-CN10*((AE10-Settle)/365))) -> 0 | EX10: =IF(AF10="",0,($C10/2+IF(27=$D10,100,0))*EXP(-CO10*((AF10-Settle)/365))) -> 0 | EY10: =IF(AG10="",0,($C10/2+IF(28=$D10,100,0))*EXP(-CP10*((AG10-Settle)/365))) -> 0 | EZ10: =IF(AH10="",0,($C10/2+IF(29=$D10,100,0))*EXP(-CQ10*((AH10-Settle)/365))) -> 0 | FA10: =IF(AI10="",0,($C10/2+IF(30=$D10,100,0))*EXP(-CR10*((AI10-Settle)/365))) -> 0 | FB10: =IF(AJ10="",0,($C10/2+IF(31=$D10,100,0))*EXP(-CS10*((AJ10-Settle)/365))) -> 0 | FC10: =IF(AK10="",0,($C10/2+IF(32=$D10,100,0))*EXP(-CT10*((AK10-Settle)/365))) -> 0 | FD10: =IF(AL10="",0,($C10/2+IF(33=$D10,100,0))*EXP(-CU10*((AL10-Settle)/365))) -> 0 | FE10: =IF(AM10="",0,($C10/2+IF(34=$D10,100,0))*EXP(-CV10*((AM10-Settle)/365))) -> 0 | FF10: =IF(AN10="",0,($C10/2+IF(35=$D10,100,0))*EXP(-CW10*((AN10-Settle)/365))) -> 0 | FG10: =IF(AO10="",0,($C10/2+IF(36=$D10,100,0))*EXP(-CX10*((AO10-Settle)/365))) -> 0 | FH10: =IF(AP10="",0,($C10/2+IF(37=$D10,100,0))*EXP(-CY10*((AP10-Settle)/365))) -> 0 | FI10: =IF(AQ10="",0,($C10/2+IF(38=$D10,100,0))*EXP(-CZ10*((AQ10-Settle)/365))) -> 0 | FJ10: =IF(AR10="",0,($C10/2+IF(39=$D10,100,0))*EXP(-DA10*((AR10-Settle)/365))) -> 0 | FK10: =IF(AS10="",0,($C10/2+IF(40=$D10,100,0))*EXP(-DB10*((AS10-Settle)/365))) -> 0 | FL10: =IF(AT10="",0,($C10/2+IF(41=$D10,100,0))*EXP(-DC10*((AT10-Settle)/365))) -> 0 | FM10: =IF(AU10="",0,($C10/2+IF(42=$D10,100,0))*EXP(-DD10*((AU10-Settle)/365))) -> 0 | FN10: =IF(AV10="",0,($C10/2+IF(43=$D10,100,0))*EXP(-DE10*((AV10-Settle)/365))) -> 0 | FO10: =IF(AW10="",0,($C10/2+IF(44=$D10,100,0))*EXP(-DF10*((AW10-Settle)/365))) -> 0 | FP10: =IF(AX10="",0,($C10/2+IF(45=$D10,100,0))*EXP(-DG10*((AX10-Settle)/365))) -> 0 | FQ10: =IF(AY10="",0,($C10/2+IF(46=$D10,100,0))*EXP(-DH10*((AY10-Settle)/365))) -> 0 | FR10: =IF(AZ10="",0,($C10/2+IF(47=$D10,100,0))*EXP(-DI10*((AZ10-Settle)/365))) -> 0 | FS10: =IF(BA10="",0,($C10/2+IF(48=$D10,100,0))*EXP(-DJ10*((BA10-Settle)/365))) -> 0 | FT10: =IF(BB10="",0,($C10/2+IF(49=$D10,100,0))*EXP(-DK10*((BB10-Settle)/365))) -> 0 | FU10: =IF(BC10="",0,($C10/2+IF(50=$D10,100,0))*EXP(-DL10*((BC10-Settle)/365))) -> 0 | FV10: =IF(BD10="",0,($C10/2+IF(51=$D10,100,0))*EXP(-DM10*((BD10-Settle)/365))) -> 0 | FW10: =IF(BE10="",0,($C10/2+IF(52=$D10,100,0))*EXP(-DN10*((BE10-Settle)/365))) -> 0 | FX10: =IF(BF10="",0,($C10/2+IF(53=$D10,100,0))*EXP(-DO10*((BF10-Settle)/365))) -> 0 | FY10: =IF(BG10="",0,($C10/2+IF(54=$D10,100,0))*EXP(-DP10*((BG10-Settle)/365))) -> 0 | FZ10: =IF(BH10="",0,($C10/2+IF(55=$D10,100,0))*EXP(-DQ10*((BH10-Settle)/365))) -> 0 | GA10: =IF(BI10="",0,($C10/2+IF(56=$D10,100,0))*EXP(-DR10*((BI10-Settle)/365))) -> 0 | GB10: =IF(BJ10="",0,($C10/2+IF(57=$D10,100,0))*EXP(-DS10*((BJ10-Settle)/365))) -> 0 | GC10: =IF(BK10="",0,($C10/2+IF(58=$D10,100,0))*EXP(-DT10*((BK10-Settle)/365))) -> 0 | GD10: =IF(BL10="",0,($C10/2+IF(59=$D10,100,0))*EXP(-DU10*((BL10-Settle)/365))) -> 0 | GE10: =IF(BM10="",0,($C10/2+IF(60=$D10,100,0))*EXP(-DV10*((BM10-Settle)/365))) -> 0
A11: 8 | B11: =Bonds!B11 -> 46326 | C11: =Bonds!C11 -> 4.125 | D11: =Bonds!Q11 -> 1 | E11: =IF(DAY(B11)=DAY(EOMONTH(B11,0)),1,0) -> 1 | F11: =IF(1>$D11,"",IF($E11=1,EOMONTH(EDATE(Bonds!$I11,6*(1-1)),0),EDATE(Bonds!$I11,6*(1-1)))) -> 46326 | G11: =IF(2>$D11,"",IF($E11=1,EOMONTH(EDATE(Bonds!$I11,6*(2-1)),0),EDATE(Bonds!$I11,6*(2-1)))) | H11: =IF(3>$D11,"",IF($E11=1,EOMONTH(EDATE(Bonds!$I11,6*(3-1)),0),EDATE(Bonds!$I11,6*(3-1)))) | I11: =IF(4>$D11,"",IF($E11=1,EOMONTH(EDATE(Bonds!$I11,6*(4-1)),0),EDATE(Bonds!$I11,6*(4-1)))) | J11: =IF(5>$D11,"",IF($E11=1,EOMONTH(EDATE(Bonds!$I11,6*(5-1)),0),EDATE(Bonds!$I11,6*(5-1)))) | K11: =IF(6>$D11,"",IF($E11=1,EOMONTH(EDATE(Bonds!$I11,6*(6-1)),0),EDATE(Bonds!$I11,6*(6-1)))) | L11: =IF(7>$D11,"",IF($E11=1,EOMONTH(EDATE(Bonds!$I11,6*(7-1)),0),EDATE(Bonds!$I11,6*(7-1)))) | M11: =IF(8>$D11,"",IF($E11=1,EOMONTH(EDATE(Bonds!$I11,6*(8-1)),0),EDATE(Bonds!$I11,6*(8-1)))) | N11: =IF(9>$D11,"",IF($E11=1,EOMONTH(EDATE(Bonds!$I11,6*(9-1)),0),EDATE(Bonds!$I11,6*(9-1)))) | O11: =IF(10>$D11,"",IF($E11=1,EOMONTH(EDATE(Bonds!$I11,6*(10-1)),0),EDATE(Bonds!$I11,6*(10-1)))) | P11: =IF(11>$D11,"",IF($E11=1,EOMONTH(EDATE(Bonds!$I11,6*(11-1)),0),EDATE(Bonds!$I11,6*(11-1)))) | Q11: =IF(12>$D11,"",IF($E11=1,EOMONTH(EDATE(Bonds!$I11,6*(12-1)),0),EDATE(Bonds!$I11,6*(12-1)))) | R11: =IF(13>$D11,"",IF($E11=1,EOMONTH(EDATE(Bonds!$I11,6*(13-1)),0),EDATE(Bonds!$I11,6*(13-1)))) | S11: =IF(14>$D11,"",IF($E11=1,EOMONTH(EDATE(Bonds!$I11,6*(14-1)),0),EDATE(Bonds!$I11,6*(14-1)))) | T11: =IF(15>$D11,"",IF($E11=1,EOMONTH(EDATE(Bonds!$I11,6*(15-1)),0),EDATE(Bonds!$I11,6*(15-1)))) | U11: =IF(16>$D11,"",IF($E11=1,EOMONTH(EDATE(Bonds!$I11,6*(16-1)),0),EDATE(Bonds!$I11,6*(16-1)))) | V11: =IF(17>$D11,"",IF($E11=1,EOMONTH(EDATE(Bonds!$I11,6*(17-1)),0),EDATE(Bonds!$I11,6*(17-1)))) | W11: =IF(18>$D11,"",IF($E11=1,EOMONTH(EDATE(Bonds!$I11,6*(18-1)),0),EDATE(Bonds!$I11,6*(18-1)))) | X11: =IF(19>$D11,"",IF($E11=1,EOMONTH(EDATE(Bonds!$I11,6*(19-1)),0),EDATE(Bonds!$I11,6*(19-1)))) | Y11: =IF(20>$D11,"",IF($E11=1,EOMONTH(EDATE(Bonds!$I11,6*(20-1)),0),EDATE(Bonds!$I11,6*(20-1)))) | Z11: =IF(21>$D11,"",IF($E11=1,EOMONTH(EDATE(Bonds!$I11,6*(21-1)),0),EDATE(Bonds!$I11,6*(21-1)))) | AA11: =IF(22>$D11,"",IF($E11=1,EOMONTH(EDATE(Bonds!$I11,6*(22-1)),0),EDATE(Bonds!$I11,6*(22-1)))) | AB11: =IF(23>$D11,"",IF($E11=1,EOMONTH(EDATE(Bonds!$I11,6*(23-1)),0),EDATE(Bonds!$I11,6*(23-1)))) | AC11: =IF(24>$D11,"",IF($E11=1,EOMONTH(EDATE(Bonds!$I11,6*(24-1)),0),EDATE(Bonds!$I11,6*(24-1)))) | AD11: =IF(25>$D11,"",IF($E11=1,EOMONTH(EDATE(Bonds!$I11,6*(25-1)),0),EDATE(Bonds!$I11,6*(25-1)))) | AE11: =IF(26>$D11,"",IF($E11=1,EOMONTH(EDATE(Bonds!$I11,6*(26-1)),0),EDATE(Bonds!$I11,6*(26-1)))) | AF11: =IF(27>$D11,"",IF($E11=1,EOMONTH(EDATE(Bonds!$I11,6*(27-1)),0),EDATE(Bonds!$I11,6*(27-1)))) | AG11: =IF(28>$D11,"",IF($E11=1,EOMONTH(EDATE(Bonds!$I11,6*(28-1)),0),EDATE(Bonds!$I11,6*(28-1)))) | AH11: =IF(29>$D11,"",IF($E11=1,EOMONTH(EDATE(Bonds!$I11,6*(29-1)),0),EDATE(Bonds!$I11,6*(29-1)))) | AI11: =IF(30>$D11,"",IF($E11=1,EOMONTH(EDATE(Bonds!$I11,6*(30-1)),0),EDATE(Bonds!$I11,6*(30-1)))) | AJ11: =IF(31>$D11,"",IF($E11=1,EOMONTH(EDATE(Bonds!$I11,6*(31-1)),0),EDATE(Bonds!$I11,6*(31-1)))) | AK11: =IF(32>$D11,"",IF($E11=1,EOMONTH(EDATE(Bonds!$I11,6*(32-1)),0),EDATE(Bonds!$I11,6*(32-1)))) | AL11: =IF(33>$D11,"",IF($E11=1,EOMONTH(EDATE(Bonds!$I11,6*(33-1)),0),EDATE(Bonds!$I11,6*(33-1)))) | AM11: =IF(34>$D11,"",IF($E11=1,EOMONTH(EDATE(Bonds!$I11,6*(34-1)),0),EDATE(Bonds!$I11,6*(34-1)))) | AN11: =IF(35>$D11,"",IF($E11=1,EOMONTH(EDATE(Bonds!$I11,6*(35-1)),0),EDATE(Bonds!$I11,6*(35-1)))) | AO11: =IF(36>$D11,"",IF($E11=1,EOMONTH(EDATE(Bonds!$I11,6*(36-1)),0),EDATE(Bonds!$I11,6*(36-1)))) | AP11: =IF(37>$D11,"",IF($E11=1,EOMONTH(EDATE(Bonds!$I11,6*(37-1)),0),EDATE(Bonds!$I11,6*(37-1)))) | AQ11: =IF(38>$D11,"",IF($E11=1,EOMONTH(EDATE(Bonds!$I11,6*(38-1)),0),EDATE(Bonds!$I11,6*(38-1)))) | AR11: =IF(39>$D11,"",IF($E11=1,EOMONTH(EDATE(Bonds!$I11,6*(39-1)),0),EDATE(Bonds!$I11,6*(39-1)))) | AS11: =IF(40>$D11,"",IF($E11=1,EOMONTH(EDATE(Bonds!$I11,6*(40-1)),0),EDATE(Bonds!$I11,6*(40-1)))) | AT11: =IF(41>$D11,"",IF($E11=1,EOMONTH(EDATE(Bonds!$I11,6*(41-1)),0),EDATE(Bonds!$I11,6*(41-1)))) | AU11: =IF(42>$D11,"",IF($E11=1,EOMONTH(EDATE(Bonds!$I11,6*(42-1)),0),EDATE(Bonds!$I11,6*(42-1)))) | AV11: =IF(43>$D11,"",IF($E11=1,EOMONTH(EDATE(Bonds!$I11,6*(43-1)),0),EDATE(Bonds!$I11,6*(43-1)))) | AW11: =IF(44>$D11,"",IF($E11=1,EOMONTH(EDATE(Bonds!$I11,6*(44-1)),0),EDATE(Bonds!$I11,6*(44-1)))) | AX11: =IF(45>$D11,"",IF($E11=1,EOMONTH(EDATE(Bonds!$I11,6*(45-1)),0),EDATE(Bonds!$I11,6*(45-1)))) | AY11: =IF(46>$D11,"",IF($E11=1,EOMONTH(EDATE(Bonds!$I11,6*(46-1)),0),EDATE(Bonds!$I11,6*(46-1)))) | AZ11: =IF(47>$D11,"",IF($E11=1,EOMONTH(EDATE(Bonds!$I11,6*(47-1)),0),EDATE(Bonds!$I11,6*(47-1)))) | BA11: =IF(48>$D11,"",IF($E11=1,EOMONTH(EDATE(Bonds!$I11,6*(48-1)),0),EDATE(Bonds!$I11,6*(48-1)))) | BB11: =IF(49>$D11,"",IF($E11=1,EOMONTH(EDATE(Bonds!$I11,6*(49-1)),0),EDATE(Bonds!$I11,6*(49-1)))) | BC11: =IF(50>$D11,"",IF($E11=1,EOMONTH(EDATE(Bonds!$I11,6*(50-1)),0),EDATE(Bonds!$I11,6*(50-1)))) | BD11: =IF(51>$D11,"",IF($E11=1,EOMONTH(EDATE(Bonds!$I11,6*(51-1)),0),EDATE(Bonds!$I11,6*(51-1)))) | BE11: =IF(52>$D11,"",IF($E11=1,EOMONTH(EDATE(Bonds!$I11,6*(52-1)),0),EDATE(Bonds!$I11,6*(52-1)))) | BF11: =IF(53>$D11,"",IF($E11=1,EOMONTH(EDATE(Bonds!$I11,6*(53-1)),0),EDATE(Bonds!$I11,6*(53-1)))) | BG11: =IF(54>$D11,"",IF($E11=1,EOMONTH(EDATE(Bonds!$I11,6*(54-1)),0),EDATE(Bonds!$I11,6*(54-1)))) | BH11: =IF(55>$D11,"",IF($E11=1,EOMONTH(EDATE(Bonds!$I11,6*(55-1)),0),EDATE(Bonds!$I11,6*(55-1)))) | BI11: =IF(56>$D11,"",IF($E11=1,EOMONTH(EDATE(Bonds!$I11,6*(56-1)),0),EDATE(Bonds!$I11,6*(56-1)))) | BJ11: =IF(57>$D11,"",IF($E11=1,EOMONTH(EDATE(Bonds!$I11,6*(57-1)),0),EDATE(Bonds!$I11,6*(57-1)))) | BK11: =IF(58>$D11,"",IF($E11=1,EOMONTH(EDATE(Bonds!$I11,6*(58-1)),0),EDATE(Bonds!$I11,6*(58-1)))) | BL11: =IF(59>$D11,"",IF($E11=1,EOMONTH(EDATE(Bonds!$I11,6*(59-1)),0),EDATE(Bonds!$I11,6*(59-1)))) | BM11: =IF(60>$D11,"",IF($E11=1,EOMONTH(EDATE(Bonds!$I11,6*(60-1)),0),EDATE(Bonds!$I11,6*(60-1)))) | BO11: =IF(F11="","",Sv_beta0+Sv_beta1*(1-EXP(-((F11-Settle)/365)/Sv_tau1))/(((F11-Settle)/365)/Sv_tau1)+Sv_beta2*((1-EXP(-((F11-Settle)/365)/Sv_tau1))/(((F11-Settle)/365)/Sv_tau1)-EXP(-((F11-Settle)/365)/Sv_tau1))+Sv_beta3*((1-EXP(-((F11-Settle)/365)/Sv_tau2))/(((F11-Settle)/365)/Sv_tau2)-EXP(-((F11-Settle)/365)/Sv_tau2))) -> 0.037298134 | BP11: =IF(G11="","",Sv_beta0+Sv_beta1*(1-EXP(-((G11-Settle)/365)/Sv_tau1))/(((G11-Settle)/365)/Sv_tau1)+Sv_beta2*((1-EXP(-((G11-Settle)/365)/Sv_tau1))/(((G11-Settle)/365)/Sv_tau1)-EXP(-((G11-Settle)/365)/Sv_tau1))+Sv_beta3*((1-EXP(-((G11-Settle)/365)/Sv_tau2))/(((G11-Settle)/365)/Sv_tau2)-EXP(-((G11-Settle)/365)/Sv_tau2))) | BQ11: =IF(H11="","",Sv_beta0+Sv_beta1*(1-EXP(-((H11-Settle)/365)/Sv_tau1))/(((H11-Settle)/365)/Sv_tau1)+Sv_beta2*((1-EXP(-((H11-Settle)/365)/Sv_tau1))/(((H11-Settle)/365)/Sv_tau1)-EXP(-((H11-Settle)/365)/Sv_tau1))+Sv_beta3*((1-EXP(-((H11-Settle)/365)/Sv_tau2))/(((H11-Settle)/365)/Sv_tau2)-EXP(-((H11-Settle)/365)/Sv_tau2))) | BR11: =IF(I11="","",Sv_beta0+Sv_beta1*(1-EXP(-((I11-Settle)/365)/Sv_tau1))/(((I11-Settle)/365)/Sv_tau1)+Sv_beta2*((1-EXP(-((I11-Settle)/365)/Sv_tau1))/(((I11-Settle)/365)/Sv_tau1)-EXP(-((I11-Settle)/365)/Sv_tau1))+Sv_beta3*((1-EXP(-((I11-Settle)/365)/Sv_tau2))/(((I11-Settle)/365)/Sv_tau2)-EXP(-((I11-Settle)/365)/Sv_tau2))) | BS11: =IF(J11="","",Sv_beta0+Sv_beta1*(1-EXP(-((J11-Settle)/365)/Sv_tau1))/(((J11-Settle)/365)/Sv_tau1)+Sv_beta2*((1-EXP(-((J11-Settle)/365)/Sv_tau1))/(((J11-Settle)/365)/Sv_tau1)-EXP(-((J11-Settle)/365)/Sv_tau1))+Sv_beta3*((1-EXP(-((J11-Settle)/365)/Sv_tau2))/(((J11-Settle)/365)/Sv_tau2)-EXP(-((J11-Settle)/365)/Sv_tau2))) | BT11: =IF(K11="","",Sv_beta0+Sv_beta1*(1-EXP(-((K11-Settle)/365)/Sv_tau1))/(((K11-Settle)/365)/Sv_tau1)+Sv_beta2*((1-EXP(-((K11-Settle)/365)/Sv_tau1))/(((K11-Settle)/365)/Sv_tau1)-EXP(-((K11-Settle)/365)/Sv_tau1))+Sv_beta3*((1-EXP(-((K11-Settle)/365)/Sv_tau2))/(((K11-Settle)/365)/Sv_tau2)-EXP(-((K11-Settle)/365)/Sv_tau2))) | BU11: =IF(L11="","",Sv_beta0+Sv_beta1*(1-EXP(-((L11-Settle)/365)/Sv_tau1))/(((L11-Settle)/365)/Sv_tau1)+Sv_beta2*((1-EXP(-((L11-Settle)/365)/Sv_tau1))/(((L11-Settle)/365)/Sv_tau1)-EXP(-((L11-Settle)/365)/Sv_tau1))+Sv_beta3*((1-EXP(-((L11-Settle)/365)/Sv_tau2))/(((L11-Settle)/365)/Sv_tau2)-EXP(-((L11-Settle)/365)/Sv_tau2))) | BV11: =IF(M11="","",Sv_beta0+Sv_beta1*(1-EXP(-((M11-Settle)/365)/Sv_tau1))/(((M11-Settle)/365)/Sv_tau1)+Sv_beta2*((1-EXP(-((M11-Settle)/365)/Sv_tau1))/(((M11-Settle)/365)/Sv_tau1)-EXP(-((M11-Settle)/365)/Sv_tau1))+Sv_beta3*((1-EXP(-((M11-Settle)/365)/Sv_tau2))/(((M11-Settle)/365)/Sv_tau2)-EXP(-((M11-Settle)/365)/Sv_tau2))) | ... DV11: =IF(BM11="","",Sv_beta0+Sv_beta1*(1-EXP(-((BM11-Settle)/365)/Sv_tau1))/(((BM11-Settle)/365)/Sv_tau1)+Sv_beta2*((1-EXP(-((BM11-Settle)/365)/Sv_tau1))/(((BM11-Settle)/365)/Sv_tau1)-EXP(-((BM11-Settle)/365)/Sv_tau1))+Sv_beta3*((1-EXP(-((BM11-Settle)/365)/Sv_tau2))/(((BM11-Settle)/365)/Sv_tau2)-EXP(-((BM11-Settle)/365)/Sv_tau2))) | DX11: =IF(F11="",0,($C11/2+IF(1=$D11,100,0))*EXP(-BO11*((F11-Settle)/365))) -> 101.51123 | DY11: =IF(G11="",0,($C11/2+IF(2=$D11,100,0))*EXP(-BP11*((G11-Settle)/365))) -> 0 | DZ11: =IF(H11="",0,($C11/2+IF(3=$D11,100,0))*EXP(-BQ11*((H11-Settle)/365))) -> 0 | EA11: =IF(I11="",0,($C11/2+IF(4=$D11,100,0))*EXP(-BR11*((I11-Settle)/365))) -> 0 | EB11: =IF(J11="",0,($C11/2+IF(5=$D11,100,0))*EXP(-BS11*((J11-Settle)/365))) -> 0 | EC11: =IF(K11="",0,($C11/2+IF(6=$D11,100,0))*EXP(-BT11*((K11-Settle)/365))) -> 0 | ED11: =IF(L11="",0,($C11/2+IF(7=$D11,100,0))*EXP(-BU11*((L11-Settle)/365))) -> 0 | EE11: =IF(M11="",0,($C11/2+IF(8=$D11,100,0))*EXP(-BV11*((M11-Settle)/365))) -> 0 | EF11: =IF(N11="",0,($C11/2+IF(9=$D11,100,0))*EXP(-BW11*((N11-Settle)/365))) -> 0 | EG11: =IF(O11="",0,($C11/2+IF(10=$D11,100,0))*EXP(-BX11*((O11-Settle)/365))) -> 0 | EH11: =IF(P11="",0,($C11/2+IF(11=$D11,100,0))*EXP(-BY11*((P11-Settle)/365))) -> 0 | EI11: =IF(Q11="",0,($C11/2+IF(12=$D11,100,0))*EXP(-BZ11*((Q11-Settle)/365))) -> 0 | EJ11: =IF(R11="",0,($C11/2+IF(13=$D11,100,0))*EXP(-CA11*((R11-Settle)/365))) -> 0 | EK11: =IF(S11="",0,($C11/2+IF(14=$D11,100,0))*EXP(-CB11*((S11-Settle)/365))) -> 0 | EL11: =IF(T11="",0,($C11/2+IF(15=$D11,100,0))*EXP(-CC11*((T11-Settle)/365))) -> 0 | EM11: =IF(U11="",0,($C11/2+IF(16=$D11,100,0))*EXP(-CD11*((U11-Settle)/365))) -> 0 | EN11: =IF(V11="",0,($C11/2+IF(17=$D11,100,0))*EXP(-CE11*((V11-Settle)/365))) -> 0 | EO11: =IF(W11="",0,($C11/2+IF(18=$D11,100,0))*EXP(-CF11*((W11-Settle)/365))) -> 0 | EP11: =IF(X11="",0,($C11/2+IF(19=$D11,100,0))*EXP(-CG11*((X11-Settle)/365))) -> 0 | EQ11: =IF(Y11="",0,($C11/2+IF(20=$D11,100,0))*EXP(-CH11*((Y11-Settle)/365))) -> 0 | ER11: =IF(Z11="",0,($C11/2+IF(21=$D11,100,0))*EXP(-CI11*((Z11-Settle)/365))) -> 0 | ES11: =IF(AA11="",0,($C11/2+IF(22=$D11,100,0))*EXP(-CJ11*((AA11-Settle)/365))) -> 0 | ET11: =IF(AB11="",0,($C11/2+IF(23=$D11,100,0))*EXP(-CK11*((AB11-Settle)/365))) -> 0 | EU11: =IF(AC11="",0,($C11/2+IF(24=$D11,100,0))*EXP(-CL11*((AC11-Settle)/365))) -> 0 | EV11: =IF(AD11="",0,($C11/2+IF(25=$D11,100,0))*EXP(-CM11*((AD11-Settle)/365))) -> 0 | EW11: =IF(AE11="",0,($C11/2+IF(26=$D11,100,0))*EXP(-CN11*((AE11-Settle)/365))) -> 0 | EX11: =IF(AF11="",0,($C11/2+IF(27=$D11,100,0))*EXP(-CO11*((AF11-Settle)/365))) -> 0 | EY11: =IF(AG11="",0,($C11/2+IF(28=$D11,100,0))*EXP(-CP11*((AG11-Settle)/365))) -> 0 | EZ11: =IF(AH11="",0,($C11/2+IF(29=$D11,100,0))*EXP(-CQ11*((AH11-Settle)/365))) -> 0 | FA11: =IF(AI11="",0,($C11/2+IF(30=$D11,100,0))*EXP(-CR11*((AI11-Settle)/365))) -> 0 | FB11: =IF(AJ11="",0,($C11/2+IF(31=$D11,100,0))*EXP(-CS11*((AJ11-Settle)/365))) -> 0 | FC11: =IF(AK11="",0,($C11/2+IF(32=$D11,100,0))*EXP(-CT11*((AK11-Settle)/365))) -> 0 | FD11: =IF(AL11="",0,($C11/2+IF(33=$D11,100,0))*EXP(-CU11*((AL11-Settle)/365))) -> 0 | FE11: =IF(AM11="",0,($C11/2+IF(34=$D11,100,0))*EXP(-CV11*((AM11-Settle)/365))) -> 0 | FF11: =IF(AN11="",0,($C11/2+IF(35=$D11,100,0))*EXP(-CW11*((AN11-Settle)/365))) -> 0 | FG11: =IF(AO11="",0,($C11/2+IF(36=$D11,100,0))*EXP(-CX11*((AO11-Settle)/365))) -> 0 | FH11: =IF(AP11="",0,($C11/2+IF(37=$D11,100,0))*EXP(-CY11*((AP11-Settle)/365))) -> 0 | FI11: =IF(AQ11="",0,($C11/2+IF(38=$D11,100,0))*EXP(-CZ11*((AQ11-Settle)/365))) -> 0 | FJ11: =IF(AR11="",0,($C11/2+IF(39=$D11,100,0))*EXP(-DA11*((AR11-Settle)/365))) -> 0 | FK11: =IF(AS11="",0,($C11/2+IF(40=$D11,100,0))*EXP(-DB11*((AS11-Settle)/365))) -> 0 | FL11: =IF(AT11="",0,($C11/2+IF(41=$D11,100,0))*EXP(-DC11*((AT11-Settle)/365))) -> 0 | FM11: =IF(AU11="",0,($C11/2+IF(42=$D11,100,0))*EXP(-DD11*((AU11-Settle)/365))) -> 0 | FN11: =IF(AV11="",0,($C11/2+IF(43=$D11,100,0))*EXP(-DE11*((AV11-Settle)/365))) -> 0 | FO11: =IF(AW11="",0,($C11/2+IF(44=$D11,100,0))*EXP(-DF11*((AW11-Settle)/365))) -> 0 | FP11: =IF(AX11="",0,($C11/2+IF(45=$D11,100,0))*EXP(-DG11*((AX11-Settle)/365))) -> 0 | FQ11: =IF(AY11="",0,($C11/2+IF(46=$D11,100,0))*EXP(-DH11*((AY11-Settle)/365))) -> 0 | FR11: =IF(AZ11="",0,($C11/2+IF(47=$D11,100,0))*EXP(-DI11*((AZ11-Settle)/365))) -> 0 | FS11: =IF(BA11="",0,($C11/2+IF(48=$D11,100,0))*EXP(-DJ11*((BA11-Settle)/365))) -> 0 | FT11: =IF(BB11="",0,($C11/2+IF(49=$D11,100,0))*EXP(-DK11*((BB11-Settle)/365))) -> 0 | FU11: =IF(BC11="",0,($C11/2+IF(50=$D11,100,0))*EXP(-DL11*((BC11-Settle)/365))) -> 0 | FV11: =IF(BD11="",0,($C11/2+IF(51=$D11,100,0))*EXP(-DM11*((BD11-Settle)/365))) -> 0 | FW11: =IF(BE11="",0,($C11/2+IF(52=$D11,100,0))*EXP(-DN11*((BE11-Settle)/365))) -> 0 | FX11: =IF(BF11="",0,($C11/2+IF(53=$D11,100,0))*EXP(-DO11*((BF11-Settle)/365))) -> 0 | FY11: =IF(BG11="",0,($C11/2+IF(54=$D11,100,0))*EXP(-DP11*((BG11-Settle)/365))) -> 0 | FZ11: =IF(BH11="",0,($C11/2+IF(55=$D11,100,0))*EXP(-DQ11*((BH11-Settle)/365))) -> 0 | GA11: =IF(BI11="",0,($C11/2+IF(56=$D11,100,0))*EXP(-DR11*((BI11-Settle)/365))) -> 0 | GB11: =IF(BJ11="",0,($C11/2+IF(57=$D11,100,0))*EXP(-DS11*((BJ11-Settle)/365))) -> 0 | GC11: =IF(BK11="",0,($C11/2+IF(58=$D11,100,0))*EXP(-DT11*((BK11-Settle)/365))) -> 0 | GD11: =IF(BL11="",0,($C11/2+IF(59=$D11,100,0))*EXP(-DU11*((BL11-Settle)/365))) -> 0 | GE11: =IF(BM11="",0,($C11/2+IF(60=$D11,100,0))*EXP(-DV11*((BM11-Settle)/365))) -> 0
A12: 9 | B12: =Bonds!B12 -> 46341 | C12: =Bonds!C12 -> 2 | D12: =Bonds!Q12 -> 1 | E12: =IF(DAY(B12)=DAY(EOMONTH(B12,0)),1,0) -> 0 | F12: =IF(1>$D12,"",IF($E12=1,EOMONTH(EDATE(Bonds!$I12,6*(1-1)),0),EDATE(Bonds!$I12,6*(1-1)))) -> 46341 | G12: =IF(2>$D12,"",IF($E12=1,EOMONTH(EDATE(Bonds!$I12,6*(2-1)),0),EDATE(Bonds!$I12,6*(2-1)))) | H12: =IF(3>$D12,"",IF($E12=1,EOMONTH(EDATE(Bonds!$I12,6*(3-1)),0),EDATE(Bonds!$I12,6*(3-1)))) | I12: =IF(4>$D12,"",IF($E12=1,EOMONTH(EDATE(Bonds!$I12,6*(4-1)),0),EDATE(Bonds!$I12,6*(4-1)))) | J12: =IF(5>$D12,"",IF($E12=1,EOMONTH(EDATE(Bonds!$I12,6*(5-1)),0),EDATE(Bonds!$I12,6*(5-1)))) | K12: =IF(6>$D12,"",IF($E12=1,EOMONTH(EDATE(Bonds!$I12,6*(6-1)),0),EDATE(Bonds!$I12,6*(6-1)))) | L12: =IF(7>$D12,"",IF($E12=1,EOMONTH(EDATE(Bonds!$I12,6*(7-1)),0),EDATE(Bonds!$I12,6*(7-1)))) | M12: =IF(8>$D12,"",IF($E12=1,EOMONTH(EDATE(Bonds!$I12,6*(8-1)),0),EDATE(Bonds!$I12,6*(8-1)))) | N12: =IF(9>$D12,"",IF($E12=1,EOMONTH(EDATE(Bonds!$I12,6*(9-1)),0),EDATE(Bonds!$I12,6*(9-1)))) | O12: =IF(10>$D12,"",IF($E12=1,EOMONTH(EDATE(Bonds!$I12,6*(10-1)),0),EDATE(Bonds!$I12,6*(10-1)))) | P12: =IF(11>$D12,"",IF($E12=1,EOMONTH(EDATE(Bonds!$I12,6*(11-1)),0),EDATE(Bonds!$I12,6*(11-1)))) | Q12: =IF(12>$D12,"",IF($E12=1,EOMONTH(EDATE(Bonds!$I12,6*(12-1)),0),EDATE(Bonds!$I12,6*(12-1)))) | R12: =IF(13>$D12,"",IF($E12=1,EOMONTH(EDATE(Bonds!$I12,6*(13-1)),0),EDATE(Bonds!$I12,6*(13-1)))) | S12: =IF(14>$D12,"",IF($E12=1,EOMONTH(EDATE(Bonds!$I12,6*(14-1)),0),EDATE(Bonds!$I12,6*(14-1)))) | T12: =IF(15>$D12,"",IF($E12=1,EOMONTH(EDATE(Bonds!$I12,6*(15-1)),0),EDATE(Bonds!$I12,6*(15-1)))) | U12: =IF(16>$D12,"",IF($E12=1,EOMONTH(EDATE(Bonds!$I12,6*(16-1)),0),EDATE(Bonds!$I12,6*(16-1)))) | V12: =IF(17>$D12,"",IF($E12=1,EOMONTH(EDATE(Bonds!$I12,6*(17-1)),0),EDATE(Bonds!$I12,6*(17-1)))) | W12: =IF(18>$D12,"",IF($E12=1,EOMONTH(EDATE(Bonds!$I12,6*(18-1)),0),EDATE(Bonds!$I12,6*(18-1)))) | X12: =IF(19>$D12,"",IF($E12=1,EOMONTH(EDATE(Bonds!$I12,6*(19-1)),0),EDATE(Bonds!$I12,6*(19-1)))) | Y12: =IF(20>$D12,"",IF($E12=1,EOMONTH(EDATE(Bonds!$I12,6*(20-1)),0),EDATE(Bonds!$I12,6*(20-1)))) | Z12: =IF(21>$D12,"",IF($E12=1,EOMONTH(EDATE(Bonds!$I12,6*(21-1)),0),EDATE(Bonds!$I12,6*(21-1)))) | AA12: =IF(22>$D12,"",IF($E12=1,EOMONTH(EDATE(Bonds!$I12,6*(22-1)),0),EDATE(Bonds!$I12,6*(22-1)))) | AB12: =IF(23>$D12,"",IF($E12=1,EOMONTH(EDATE(Bonds!$I12,6*(23-1)),0),EDATE(Bonds!$I12,6*(23-1)))) | AC12: =IF(24>$D12,"",IF($E12=1,EOMONTH(EDATE(Bonds!$I12,6*(24-1)),0),EDATE(Bonds!$I12,6*(24-1)))) | AD12: =IF(25>$D12,"",IF($E12=1,EOMONTH(EDATE(Bonds!$I12,6*(25-1)),0),EDATE(Bonds!$I12,6*(25-1)))) | AE12: =IF(26>$D12,"",IF($E12=1,EOMONTH(EDATE(Bonds!$I12,6*(26-1)),0),EDATE(Bonds!$I12,6*(26-1)))) | AF12: =IF(27>$D12,"",IF($E12=1,EOMONTH(EDATE(Bonds!$I12,6*(27-1)),0),EDATE(Bonds!$I12,6*(27-1)))) | AG12: =IF(28>$D12,"",IF($E12=1,EOMONTH(EDATE(Bonds!$I12,6*(28-1)),0),EDATE(Bonds!$I12,6*(28-1)))) | AH12: =IF(29>$D12,"",IF($E12=1,EOMONTH(EDATE(Bonds!$I12,6*(29-1)),0),EDATE(Bonds!$I12,6*(29-1)))) | AI12: =IF(30>$D12,"",IF($E12=1,EOMONTH(EDATE(Bonds!$I12,6*(30-1)),0),EDATE(Bonds!$I12,6*(30-1)))) | AJ12: =IF(31>$D12,"",IF($E12=1,EOMONTH(EDATE(Bonds!$I12,6*(31-1)),0),EDATE(Bonds!$I12,6*(31-1)))) | AK12: =IF(32>$D12,"",IF($E12=1,EOMONTH(EDATE(Bonds!$I12,6*(32-1)),0),EDATE(Bonds!$I12,6*(32-1)))) | AL12: =IF(33>$D12,"",IF($E12=1,EOMONTH(EDATE(Bonds!$I12,6*(33-1)),0),EDATE(Bonds!$I12,6*(33-1)))) | AM12: =IF(34>$D12,"",IF($E12=1,EOMONTH(EDATE(Bonds!$I12,6*(34-1)),0),EDATE(Bonds!$I12,6*(34-1)))) | AN12: =IF(35>$D12,"",IF($E12=1,EOMONTH(EDATE(Bonds!$I12,6*(35-1)),0),EDATE(Bonds!$I12,6*(35-1)))) | AO12: =IF(36>$D12,"",IF($E12=1,EOMONTH(EDATE(Bonds!$I12,6*(36-1)),0),EDATE(Bonds!$I12,6*(36-1)))) | AP12: =IF(37>$D12,"",IF($E12=1,EOMONTH(EDATE(Bonds!$I12,6*(37-1)),0),EDATE(Bonds!$I12,6*(37-1)))) | AQ12: =IF(38>$D12,"",IF($E12=1,EOMONTH(EDATE(Bonds!$I12,6*(38-1)),0),EDATE(Bonds!$I12,6*(38-1)))) | AR12: =IF(39>$D12,"",IF($E12=1,EOMONTH(EDATE(Bonds!$I12,6*(39-1)),0),EDATE(Bonds!$I12,6*(39-1)))) | AS12: =IF(40>$D12,"",IF($E12=1,EOMONTH(EDATE(Bonds!$I12,6*(40-1)),0),EDATE(Bonds!$I12,6*(40-1)))) | AT12: =IF(41>$D12,"",IF($E12=1,EOMONTH(EDATE(Bonds!$I12,6*(41-1)),0),EDATE(Bonds!$I12,6*(41-1)))) | AU12: =IF(42>$D12,"",IF($E12=1,EOMONTH(EDATE(Bonds!$I12,6*(42-1)),0),EDATE(Bonds!$I12,6*(42-1)))) | AV12: =IF(43>$D12,"",IF($E12=1,EOMONTH(EDATE(Bonds!$I12,6*(43-1)),0),EDATE(Bonds!$I12,6*(43-1)))) | AW12: =IF(44>$D12,"",IF($E12=1,EOMONTH(EDATE(Bonds!$I12,6*(44-1)),0),EDATE(Bonds!$I12,6*(44-1)))) | AX12: =IF(45>$D12,"",IF($E12=1,EOMONTH(EDATE(Bonds!$I12,6*(45-1)),0),EDATE(Bonds!$I12,6*(45-1)))) | AY12: =IF(46>$D12,"",IF($E12=1,EOMONTH(EDATE(Bonds!$I12,6*(46-1)),0),EDATE(Bonds!$I12,6*(46-1)))) | AZ12: =IF(47>$D12,"",IF($E12=1,EOMONTH(EDATE(Bonds!$I12,6*(47-1)),0),EDATE(Bonds!$I12,6*(47-1)))) | BA12: =IF(48>$D12,"",IF($E12=1,EOMONTH(EDATE(Bonds!$I12,6*(48-1)),0),EDATE(Bonds!$I12,6*(48-1)))) | BB12: =IF(49>$D12,"",IF($E12=1,EOMONTH(EDATE(Bonds!$I12,6*(49-1)),0),EDATE(Bonds!$I12,6*(49-1)))) | BC12: =IF(50>$D12,"",IF($E12=1,EOMONTH(EDATE(Bonds!$I12,6*(50-1)),0),EDATE(Bonds!$I12,6*(50-1)))) | BD12: =IF(51>$D12,"",IF($E12=1,EOMONTH(EDATE(Bonds!$I12,6*(51-1)),0),EDATE(Bonds!$I12,6*(51-1)))) | BE12: =IF(52>$D12,"",IF($E12=1,EOMONTH(EDATE(Bonds!$I12,6*(52-1)),0),EDATE(Bonds!$I12,6*(52-1)))) | BF12: =IF(53>$D12,"",IF($E12=1,EOMONTH(EDATE(Bonds!$I12,6*(53-1)),0),EDATE(Bonds!$I12,6*(53-1)))) | BG12: =IF(54>$D12,"",IF($E12=1,EOMONTH(EDATE(Bonds!$I12,6*(54-1)),0),EDATE(Bonds!$I12,6*(54-1)))) | BH12: =IF(55>$D12,"",IF($E12=1,EOMONTH(EDATE(Bonds!$I12,6*(55-1)),0),EDATE(Bonds!$I12,6*(55-1)))) | BI12: =IF(56>$D12,"",IF($E12=1,EOMONTH(EDATE(Bonds!$I12,6*(56-1)),0),EDATE(Bonds!$I12,6*(56-1)))) | BJ12: =IF(57>$D12,"",IF($E12=1,EOMONTH(EDATE(Bonds!$I12,6*(57-1)),0),EDATE(Bonds!$I12,6*(57-1)))) | BK12: =IF(58>$D12,"",IF($E12=1,EOMONTH(EDATE(Bonds!$I12,6*(58-1)),0),EDATE(Bonds!$I12,6*(58-1)))) | BL12: =IF(59>$D12,"",IF($E12=1,EOMONTH(EDATE(Bonds!$I12,6*(59-1)),0),EDATE(Bonds!$I12,6*(59-1)))) | BM12: =IF(60>$D12,"",IF($E12=1,EOMONTH(EDATE(Bonds!$I12,6*(60-1)),0),EDATE(Bonds!$I12,6*(60-1)))) | BO12: =IF(F12="","",Sv_beta0+Sv_beta1*(1-EXP(-((F12-Settle)/365)/Sv_tau1))/(((F12-Settle)/365)/Sv_tau1)+Sv_beta2*((1-EXP(-((F12-Settle)/365)/Sv_tau1))/(((F12-Settle)/365)/Sv_tau1)-EXP(-((F12-Settle)/365)/Sv_tau1))+Sv_beta3*((1-EXP(-((F12-Settle)/365)/Sv_tau2))/(((F12-Settle)/365)/Sv_tau2)-EXP(-((F12-Settle)/365)/Sv_tau2))) -> 0.037565785 | BP12: =IF(G12="","",Sv_beta0+Sv_beta1*(1-EXP(-((G12-Settle)/365)/Sv_tau1))/(((G12-Settle)/365)/Sv_tau1)+Sv_beta2*((1-EXP(-((G12-Settle)/365)/Sv_tau1))/(((G12-Settle)/365)/Sv_tau1)-EXP(-((G12-Settle)/365)/Sv_tau1))+Sv_beta3*((1-EXP(-((G12-Settle)/365)/Sv_tau2))/(((G12-Settle)/365)/Sv_tau2)-EXP(-((G12-Settle)/365)/Sv_tau2))) | BQ12: =IF(H12="","",Sv_beta0+Sv_beta1*(1-EXP(-((H12-Settle)/365)/Sv_tau1))/(((H12-Settle)/365)/Sv_tau1)+Sv_beta2*((1-EXP(-((H12-Settle)/365)/Sv_tau1))/(((H12-Settle)/365)/Sv_tau1)-EXP(-((H12-Settle)/365)/Sv_tau1))+Sv_beta3*((1-EXP(-((H12-Settle)/365)/Sv_tau2))/(((H12-Settle)/365)/Sv_tau2)-EXP(-((H12-Settle)/365)/Sv_tau2))) | BR12: =IF(I12="","",Sv_beta0+Sv_beta1*(1-EXP(-((I12-Settle)/365)/Sv_tau1))/(((I12-Settle)/365)/Sv_tau1)+Sv_beta2*((1-EXP(-((I12-Settle)/365)/Sv_tau1))/(((I12-Settle)/365)/Sv_tau1)-EXP(-((I12-Settle)/365)/Sv_tau1))+Sv_beta3*((1-EXP(-((I12-Settle)/365)/Sv_tau2))/(((I12-Settle)/365)/Sv_tau2)-EXP(-((I12-Settle)/365)/Sv_tau2))) | BS12: =IF(J12="","",Sv_beta0+Sv_beta1*(1-EXP(-((J12-Settle)/365)/Sv_tau1))/(((J12-Settle)/365)/Sv_tau1)+Sv_beta2*((1-EXP(-((J12-Settle)/365)/Sv_tau1))/(((J12-Settle)/365)/Sv_tau1)-EXP(-((J12-Settle)/365)/Sv_tau1))+Sv_beta3*((1-EXP(-((J12-Settle)/365)/Sv_tau2))/(((J12-Settle)/365)/Sv_tau2)-EXP(-((J12-Settle)/365)/Sv_tau2))) | BT12: =IF(K12="","",Sv_beta0+Sv_beta1*(1-EXP(-((K12-Settle)/365)/Sv_tau1))/(((K12-Settle)/365)/Sv_tau1)+Sv_beta2*((1-EXP(-((K12-Settle)/365)/Sv_tau1))/(((K12-Settle)/365)/Sv_tau1)-EXP(-((K12-Settle)/365)/Sv_tau1))+Sv_beta3*((1-EXP(-((K12-Settle)/365)/Sv_tau2))/(((K12-Settle)/365)/Sv_tau2)-EXP(-((K12-Settle)/365)/Sv_tau2))) | BU12: =IF(L12="","",Sv_beta0+Sv_beta1*(1-EXP(-((L12-Settle)/365)/Sv_tau1))/(((L12-Settle)/365)/Sv_tau1)+Sv_beta2*((1-EXP(-((L12-Settle)/365)/Sv_tau1))/(((L12-Settle)/365)/Sv_tau1)-EXP(-((L12-Settle)/365)/Sv_tau1))+Sv_beta3*((1-EXP(-((L12-Settle)/365)/Sv_tau2))/(((L12-Settle)/365)/Sv_tau2)-EXP(-((L12-Settle)/365)/Sv_tau2))) | BV12: =IF(M12="","",Sv_beta0+Sv_beta1*(1-EXP(-((M12-Settle)/365)/Sv_tau1))/(((M12-Settle)/365)/Sv_tau1)+Sv_beta2*((1-EXP(-((M12-Settle)/365)/Sv_tau1))/(((M12-Settle)/365)/Sv_tau1)-EXP(-((M12-Settle)/365)/Sv_tau1))+Sv_beta3*((1-EXP(-((M12-Settle)/365)/Sv_tau2))/(((M12-Settle)/365)/Sv_tau2)-EXP(-((M12-Settle)/365)/Sv_tau2))) | ... DV12: =IF(BM12="","",Sv_beta0+Sv_beta1*(1-EXP(-((BM12-Settle)/365)/Sv_tau1))/(((BM12-Settle)/365)/Sv_tau1)+Sv_beta2*((1-EXP(-((BM12-Settle)/365)/Sv_tau1))/(((BM12-Settle)/365)/Sv_tau1)-EXP(-((BM12-Settle)/365)/Sv_tau1))+Sv_beta3*((1-EXP(-((BM12-Settle)/365)/Sv_tau2))/(((BM12-Settle)/365)/Sv_tau2)-EXP(-((BM12-Settle)/365)/Sv_tau2))) | DX12: =IF(F12="",0,($C12/2+IF(1=$D12,100,0))*EXP(-BO12*((F12-Settle)/365))) -> 100.29561 | DY12: =IF(G12="",0,($C12/2+IF(2=$D12,100,0))*EXP(-BP12*((G12-Settle)/365))) -> 0 | DZ12: =IF(H12="",0,($C12/2+IF(3=$D12,100,0))*EXP(-BQ12*((H12-Settle)/365))) -> 0 | EA12: =IF(I12="",0,($C12/2+IF(4=$D12,100,0))*EXP(-BR12*((I12-Settle)/365))) -> 0 | EB12: =IF(J12="",0,($C12/2+IF(5=$D12,100,0))*EXP(-BS12*((J12-Settle)/365))) -> 0 | EC12: =IF(K12="",0,($C12/2+IF(6=$D12,100,0))*EXP(-BT12*((K12-Settle)/365))) -> 0 | ED12: =IF(L12="",0,($C12/2+IF(7=$D12,100,0))*EXP(-BU12*((L12-Settle)/365))) -> 0 | EE12: =IF(M12="",0,($C12/2+IF(8=$D12,100,0))*EXP(-BV12*((M12-Settle)/365))) -> 0 | EF12: =IF(N12="",0,($C12/2+IF(9=$D12,100,0))*EXP(-BW12*((N12-Settle)/365))) -> 0 | EG12: =IF(O12="",0,($C12/2+IF(10=$D12,100,0))*EXP(-BX12*((O12-Settle)/365))) -> 0 | EH12: =IF(P12="",0,($C12/2+IF(11=$D12,100,0))*EXP(-BY12*((P12-Settle)/365))) -> 0 | EI12: =IF(Q12="",0,($C12/2+IF(12=$D12,100,0))*EXP(-BZ12*((Q12-Settle)/365))) -> 0 | EJ12: =IF(R12="",0,($C12/2+IF(13=$D12,100,0))*EXP(-CA12*((R12-Settle)/365))) -> 0 | EK12: =IF(S12="",0,($C12/2+IF(14=$D12,100,0))*EXP(-CB12*((S12-Settle)/365))) -> 0 | EL12: =IF(T12="",0,($C12/2+IF(15=$D12,100,0))*EXP(-CC12*((T12-Settle)/365))) -> 0 | EM12: =IF(U12="",0,($C12/2+IF(16=$D12,100,0))*EXP(-CD12*((U12-Settle)/365))) -> 0 | EN12: =IF(V12="",0,($C12/2+IF(17=$D12,100,0))*EXP(-CE12*((V12-Settle)/365))) -> 0 | EO12: =IF(W12="",0,($C12/2+IF(18=$D12,100,0))*EXP(-CF12*((W12-Settle)/365))) -> 0 | EP12: =IF(X12="",0,($C12/2+IF(19=$D12,100,0))*EXP(-CG12*((X12-Settle)/365))) -> 0 | EQ12: =IF(Y12="",0,($C12/2+IF(20=$D12,100,0))*EXP(-CH12*((Y12-Settle)/365))) -> 0 | ER12: =IF(Z12="",0,($C12/2+IF(21=$D12,100,0))*EXP(-CI12*((Z12-Settle)/365))) -> 0 | ES12: =IF(AA12="",0,($C12/2+IF(22=$D12,100,0))*EXP(-CJ12*((AA12-Settle)/365))) -> 0 | ET12: =IF(AB12="",0,($C12/2+IF(23=$D12,100,0))*EXP(-CK12*((AB12-Settle)/365))) -> 0 | EU12: =IF(AC12="",0,($C12/2+IF(24=$D12,100,0))*EXP(-CL12*((AC12-Settle)/365))) -> 0 | EV12: =IF(AD12="",0,($C12/2+IF(25=$D12,100,0))*EXP(-CM12*((AD12-Settle)/365))) -> 0 | EW12: =IF(AE12="",0,($C12/2+IF(26=$D12,100,0))*EXP(-CN12*((AE12-Settle)/365))) -> 0 | EX12: =IF(AF12="",0,($C12/2+IF(27=$D12,100,0))*EXP(-CO12*((AF12-Settle)/365))) -> 0 | EY12: =IF(AG12="",0,($C12/2+IF(28=$D12,100,0))*EXP(-CP12*((AG12-Settle)/365))) -> 0 | EZ12: =IF(AH12="",0,($C12/2+IF(29=$D12,100,0))*EXP(-CQ12*((AH12-Settle)/365))) -> 0 | FA12: =IF(AI12="",0,($C12/2+IF(30=$D12,100,0))*EXP(-CR12*((AI12-Settle)/365))) -> 0 | FB12: =IF(AJ12="",0,($C12/2+IF(31=$D12,100,0))*EXP(-CS12*((AJ12-Settle)/365))) -> 0 | FC12: =IF(AK12="",0,($C12/2+IF(32=$D12,100,0))*EXP(-CT12*((AK12-Settle)/365))) -> 0 | FD12: =IF(AL12="",0,($C12/2+IF(33=$D12,100,0))*EXP(-CU12*((AL12-Settle)/365))) -> 0 | FE12: =IF(AM12="",0,($C12/2+IF(34=$D12,100,0))*EXP(-CV12*((AM12-Settle)/365))) -> 0 | FF12: =IF(AN12="",0,($C12/2+IF(35=$D12,100,0))*EXP(-CW12*((AN12-Settle)/365))) -> 0 | FG12: =IF(AO12="",0,($C12/2+IF(36=$D12,100,0))*EXP(-CX12*((AO12-Settle)/365))) -> 0 | FH12: =IF(AP12="",0,($C12/2+IF(37=$D12,100,0))*EXP(-CY12*((AP12-Settle)/365))) -> 0 | FI12: =IF(AQ12="",0,($C12/2+IF(38=$D12,100,0))*EXP(-CZ12*((AQ12-Settle)/365))) -> 0 | FJ12: =IF(AR12="",0,($C12/2+IF(39=$D12,100,0))*EXP(-DA12*((AR12-Settle)/365))) -> 0 | FK12: =IF(AS12="",0,($C12/2+IF(40=$D12,100,0))*EXP(-DB12*((AS12-Settle)/365))) -> 0 | FL12: =IF(AT12="",0,($C12/2+IF(41=$D12,100,0))*EXP(-DC12*((AT12-Settle)/365))) -> 0 | FM12: =IF(AU12="",0,($C12/2+IF(42=$D12,100,0))*EXP(-DD12*((AU12-Settle)/365))) -> 0 | FN12: =IF(AV12="",0,($C12/2+IF(43=$D12,100,0))*EXP(-DE12*((AV12-Settle)/365))) -> 0 | FO12: =IF(AW12="",0,($C12/2+IF(44=$D12,100,0))*EXP(-DF12*((AW12-Settle)/365))) -> 0 | FP12: =IF(AX12="",0,($C12/2+IF(45=$D12,100,0))*EXP(-DG12*((AX12-Settle)/365))) -> 0 | FQ12: =IF(AY12="",0,($C12/2+IF(46=$D12,100,0))*EXP(-DH12*((AY12-Settle)/365))) -> 0 | FR12: =IF(AZ12="",0,($C12/2+IF(47=$D12,100,0))*EXP(-DI12*((AZ12-Settle)/365))) -> 0 | FS12: =IF(BA12="",0,($C12/2+IF(48=$D12,100,0))*EXP(-DJ12*((BA12-Settle)/365))) -> 0 | FT12: =IF(BB12="",0,($C12/2+IF(49=$D12,100,0))*EXP(-DK12*((BB12-Settle)/365))) -> 0 | FU12: =IF(BC12="",0,($C12/2+IF(50=$D12,100,0))*EXP(-DL12*((BC12-Settle)/365))) -> 0 | FV12: =IF(BD12="",0,($C12/2+IF(51=$D12,100,0))*EXP(-DM12*((BD12-Settle)/365))) -> 0 | FW12: =IF(BE12="",0,($C12/2+IF(52=$D12,100,0))*EXP(-DN12*((BE12-Settle)/365))) -> 0 | FX12: =IF(BF12="",0,($C12/2+IF(53=$D12,100,0))*EXP(-DO12*((BF12-Settle)/365))) -> 0 | FY12: =IF(BG12="",0,($C12/2+IF(54=$D12,100,0))*EXP(-DP12*((BG12-Settle)/365))) -> 0 | FZ12: =IF(BH12="",0,($C12/2+IF(55=$D12,100,0))*EXP(-DQ12*((BH12-Settle)/365))) -> 0 | GA12: =IF(BI12="",0,($C12/2+IF(56=$D12,100,0))*EXP(-DR12*((BI12-Settle)/365))) -> 0 | GB12: =IF(BJ12="",0,($C12/2+IF(57=$D12,100,0))*EXP(-DS12*((BJ12-Settle)/365))) -> 0 | GC12: =IF(BK12="",0,($C12/2+IF(58=$D12,100,0))*EXP(-DT12*((BK12-Settle)/365))) -> 0 | GD12: =IF(BL12="",0,($C12/2+IF(59=$D12,100,0))*EXP(-DU12*((BL12-Settle)/365))) -> 0 | GE12: =IF(BM12="",0,($C12/2+IF(60=$D12,100,0))*EXP(-DV12*((BM12-Settle)/365))) -> 0
A13: 10 | B13: =Bonds!B13 -> 46341 | C13: =Bonds!C13 -> 4.625 | D13: =Bonds!Q13 -> 1 | E13: =IF(DAY(B13)=DAY(EOMONTH(B13,0)),1,0) -> 0 | F13: =IF(1>$D13,"",IF($E13=1,EOMONTH(EDATE(Bonds!$I13,6*(1-1)),0),EDATE(Bonds!$I13,6*(1-1)))) -> 46341 | G13: =IF(2>$D13,"",IF($E13=1,EOMONTH(EDATE(Bonds!$I13,6*(2-1)),0),EDATE(Bonds!$I13,6*(2-1)))) | H13: =IF(3>$D13,"",IF($E13=1,EOMONTH(EDATE(Bonds!$I13,6*(3-1)),0),EDATE(Bonds!$I13,6*(3-1)))) | I13: =IF(4>$D13,"",IF($E13=1,EOMONTH(EDATE(Bonds!$I13,6*(4-1)),0),EDATE(Bonds!$I13,6*(4-1)))) | J13: =IF(5>$D13,"",IF($E13=1,EOMONTH(EDATE(Bonds!$I13,6*(5-1)),0),EDATE(Bonds!$I13,6*(5-1)))) | K13: =IF(6>$D13,"",IF($E13=1,EOMONTH(EDATE(Bonds!$I13,6*(6-1)),0),EDATE(Bonds!$I13,6*(6-1)))) | L13: =IF(7>$D13,"",IF($E13=1,EOMONTH(EDATE(Bonds!$I13,6*(7-1)),0),EDATE(Bonds!$I13,6*(7-1)))) | M13: =IF(8>$D13,"",IF($E13=1,EOMONTH(EDATE(Bonds!$I13,6*(8-1)),0),EDATE(Bonds!$I13,6*(8-1)))) | N13: =IF(9>$D13,"",IF($E13=1,EOMONTH(EDATE(Bonds!$I13,6*(9-1)),0),EDATE(Bonds!$I13,6*(9-1)))) | O13: =IF(10>$D13,"",IF($E13=1,EOMONTH(EDATE(Bonds!$I13,6*(10-1)),0),EDATE(Bonds!$I13,6*(10-1)))) | P13: =IF(11>$D13,"",IF($E13=1,EOMONTH(EDATE(Bonds!$I13,6*(11-1)),0),EDATE(Bonds!$I13,6*(11-1)))) | Q13: =IF(12>$D13,"",IF($E13=1,EOMONTH(EDATE(Bonds!$I13,6*(12-1)),0),EDATE(Bonds!$I13,6*(12-1)))) | R13: =IF(13>$D13,"",IF($E13=1,EOMONTH(EDATE(Bonds!$I13,6*(13-1)),0),EDATE(Bonds!$I13,6*(13-1)))) | S13: =IF(14>$D13,"",IF($E13=1,EOMONTH(EDATE(Bonds!$I13,6*(14-1)),0),EDATE(Bonds!$I13,6*(14-1)))) | T13: =IF(15>$D13,"",IF($E13=1,EOMONTH(EDATE(Bonds!$I13,6*(15-1)),0),EDATE(Bonds!$I13,6*(15-1)))) | U13: =IF(16>$D13,"",IF($E13=1,EOMONTH(EDATE(Bonds!$I13,6*(16-1)),0),EDATE(Bonds!$I13,6*(16-1)))) | V13: =IF(17>$D13,"",IF($E13=1,EOMONTH(EDATE(Bonds!$I13,6*(17-1)),0),EDATE(Bonds!$I13,6*(17-1)))) | W13: =IF(18>$D13,"",IF($E13=1,EOMONTH(EDATE(Bonds!$I13,6*(18-1)),0),EDATE(Bonds!$I13,6*(18-1)))) | X13: =IF(19>$D13,"",IF($E13=1,EOMONTH(EDATE(Bonds!$I13,6*(19-1)),0),EDATE(Bonds!$I13,6*(19-1)))) | Y13: =IF(20>$D13,"",IF($E13=1,EOMONTH(EDATE(Bonds!$I13,6*(20-1)),0),EDATE(Bonds!$I13,6*(20-1)))) | Z13: =IF(21>$D13,"",IF($E13=1,EOMONTH(EDATE(Bonds!$I13,6*(21-1)),0),EDATE(Bonds!$I13,6*(21-1)))) | AA13: =IF(22>$D13,"",IF($E13=1,EOMONTH(EDATE(Bonds!$I13,6*(22-1)),0),EDATE(Bonds!$I13,6*(22-1)))) | AB13: =IF(23>$D13,"",IF($E13=1,EOMONTH(EDATE(Bonds!$I13,6*(23-1)),0),EDATE(Bonds!$I13,6*(23-1)))) | AC13: =IF(24>$D13,"",IF($E13=1,EOMONTH(EDATE(Bonds!$I13,6*(24-1)),0),EDATE(Bonds!$I13,6*(24-1)))) | AD13: =IF(25>$D13,"",IF($E13=1,EOMONTH(EDATE(Bonds!$I13,6*(25-1)),0),EDATE(Bonds!$I13,6*(25-1)))) | AE13: =IF(26>$D13,"",IF($E13=1,EOMONTH(EDATE(Bonds!$I13,6*(26-1)),0),EDATE(Bonds!$I13,6*(26-1)))) | AF13: =IF(27>$D13,"",IF($E13=1,EOMONTH(EDATE(Bonds!$I13,6*(27-1)),0),EDATE(Bonds!$I13,6*(27-1)))) | AG13: =IF(28>$D13,"",IF($E13=1,EOMONTH(EDATE(Bonds!$I13,6*(28-1)),0),EDATE(Bonds!$I13,6*(28-1)))) | AH13: =IF(29>$D13,"",IF($E13=1,EOMONTH(EDATE(Bonds!$I13,6*(29-1)),0),EDATE(Bonds!$I13,6*(29-1)))) | AI13: =IF(30>$D13,"",IF($E13=1,EOMONTH(EDATE(Bonds!$I13,6*(30-1)),0),EDATE(Bonds!$I13,6*(30-1)))) | AJ13: =IF(31>$D13,"",IF($E13=1,EOMONTH(EDATE(Bonds!$I13,6*(31-1)),0),EDATE(Bonds!$I13,6*(31-1)))) | AK13: =IF(32>$D13,"",IF($E13=1,EOMONTH(EDATE(Bonds!$I13,6*(32-1)),0),EDATE(Bonds!$I13,6*(32-1)))) | AL13: =IF(33>$D13,"",IF($E13=1,EOMONTH(EDATE(Bonds!$I13,6*(33-1)),0),EDATE(Bonds!$I13,6*(33-1)))) | AM13: =IF(34>$D13,"",IF($E13=1,EOMONTH(EDATE(Bonds!$I13,6*(34-1)),0),EDATE(Bonds!$I13,6*(34-1)))) | AN13: =IF(35>$D13,"",IF($E13=1,EOMONTH(EDATE(Bonds!$I13,6*(35-1)),0),EDATE(Bonds!$I13,6*(35-1)))) | AO13: =IF(36>$D13,"",IF($E13=1,EOMONTH(EDATE(Bonds!$I13,6*(36-1)),0),EDATE(Bonds!$I13,6*(36-1)))) | AP13: =IF(37>$D13,"",IF($E13=1,EOMONTH(EDATE(Bonds!$I13,6*(37-1)),0),EDATE(Bonds!$I13,6*(37-1)))) | AQ13: =IF(38>$D13,"",IF($E13=1,EOMONTH(EDATE(Bonds!$I13,6*(38-1)),0),EDATE(Bonds!$I13,6*(38-1)))) | AR13: =IF(39>$D13,"",IF($E13=1,EOMONTH(EDATE(Bonds!$I13,6*(39-1)),0),EDATE(Bonds!$I13,6*(39-1)))) | AS13: =IF(40>$D13,"",IF($E13=1,EOMONTH(EDATE(Bonds!$I13,6*(40-1)),0),EDATE(Bonds!$I13,6*(40-1)))) | AT13: =IF(41>$D13,"",IF($E13=1,EOMONTH(EDATE(Bonds!$I13,6*(41-1)),0),EDATE(Bonds!$I13,6*(41-1)))) | AU13: =IF(42>$D13,"",IF($E13=1,EOMONTH(EDATE(Bonds!$I13,6*(42-1)),0),EDATE(Bonds!$I13,6*(42-1)))) | AV13: =IF(43>$D13,"",IF($E13=1,EOMONTH(EDATE(Bonds!$I13,6*(43-1)),0),EDATE(Bonds!$I13,6*(43-1)))) | AW13: =IF(44>$D13,"",IF($E13=1,EOMONTH(EDATE(Bonds!$I13,6*(44-1)),0),EDATE(Bonds!$I13,6*(44-1)))) | AX13: =IF(45>$D13,"",IF($E13=1,EOMONTH(EDATE(Bonds!$I13,6*(45-1)),0),EDATE(Bonds!$I13,6*(45-1)))) | AY13: =IF(46>$D13,"",IF($E13=1,EOMONTH(EDATE(Bonds!$I13,6*(46-1)),0),EDATE(Bonds!$I13,6*(46-1)))) | AZ13: =IF(47>$D13,"",IF($E13=1,EOMONTH(EDATE(Bonds!$I13,6*(47-1)),0),EDATE(Bonds!$I13,6*(47-1)))) | BA13: =IF(48>$D13,"",IF($E13=1,EOMONTH(EDATE(Bonds!$I13,6*(48-1)),0),EDATE(Bonds!$I13,6*(48-1)))) | BB13: =IF(49>$D13,"",IF($E13=1,EOMONTH(EDATE(Bonds!$I13,6*(49-1)),0),EDATE(Bonds!$I13,6*(49-1)))) | BC13: =IF(50>$D13,"",IF($E13=1,EOMONTH(EDATE(Bonds!$I13,6*(50-1)),0),EDATE(Bonds!$I13,6*(50-1)))) | BD13: =IF(51>$D13,"",IF($E13=1,EOMONTH(EDATE(Bonds!$I13,6*(51-1)),0),EDATE(Bonds!$I13,6*(51-1)))) | BE13: =IF(52>$D13,"",IF($E13=1,EOMONTH(EDATE(Bonds!$I13,6*(52-1)),0),EDATE(Bonds!$I13,6*(52-1)))) | BF13: =IF(53>$D13,"",IF($E13=1,EOMONTH(EDATE(Bonds!$I13,6*(53-1)),0),EDATE(Bonds!$I13,6*(53-1)))) | BG13: =IF(54>$D13,"",IF($E13=1,EOMONTH(EDATE(Bonds!$I13,6*(54-1)),0),EDATE(Bonds!$I13,6*(54-1)))) | BH13: =IF(55>$D13,"",IF($E13=1,EOMONTH(EDATE(Bonds!$I13,6*(55-1)),0),EDATE(Bonds!$I13,6*(55-1)))) | BI13: =IF(56>$D13,"",IF($E13=1,EOMONTH(EDATE(Bonds!$I13,6*(56-1)),0),EDATE(Bonds!$I13,6*(56-1)))) | BJ13: =IF(57>$D13,"",IF($E13=1,EOMONTH(EDATE(Bonds!$I13,6*(57-1)),0),EDATE(Bonds!$I13,6*(57-1)))) | BK13: =IF(58>$D13,"",IF($E13=1,EOMONTH(EDATE(Bonds!$I13,6*(58-1)),0),EDATE(Bonds!$I13,6*(58-1)))) | BL13: =IF(59>$D13,"",IF($E13=1,EOMONTH(EDATE(Bonds!$I13,6*(59-1)),0),EDATE(Bonds!$I13,6*(59-1)))) | BM13: =IF(60>$D13,"",IF($E13=1,EOMONTH(EDATE(Bonds!$I13,6*(60-1)),0),EDATE(Bonds!$I13,6*(60-1)))) | BO13: =IF(F13="","",Sv_beta0+Sv_beta1*(1-EXP(-((F13-Settle)/365)/Sv_tau1))/(((F13-Settle)/365)/Sv_tau1)+Sv_beta2*((1-EXP(-((F13-Settle)/365)/Sv_tau1))/(((F13-Settle)/365)/Sv_tau1)-EXP(-((F13-Settle)/365)/Sv_tau1))+Sv_beta3*((1-EXP(-((F13-Settle)/365)/Sv_tau2))/(((F13-Settle)/365)/Sv_tau2)-EXP(-((F13-Settle)/365)/Sv_tau2))) -> 0.037565785 | BP13: =IF(G13="","",Sv_beta0+Sv_beta1*(1-EXP(-((G13-Settle)/365)/Sv_tau1))/(((G13-Settle)/365)/Sv_tau1)+Sv_beta2*((1-EXP(-((G13-Settle)/365)/Sv_tau1))/(((G13-Settle)/365)/Sv_tau1)-EXP(-((G13-Settle)/365)/Sv_tau1))+Sv_beta3*((1-EXP(-((G13-Settle)/365)/Sv_tau2))/(((G13-Settle)/365)/Sv_tau2)-EXP(-((G13-Settle)/365)/Sv_tau2))) | BQ13: =IF(H13="","",Sv_beta0+Sv_beta1*(1-EXP(-((H13-Settle)/365)/Sv_tau1))/(((H13-Settle)/365)/Sv_tau1)+Sv_beta2*((1-EXP(-((H13-Settle)/365)/Sv_tau1))/(((H13-Settle)/365)/Sv_tau1)-EXP(-((H13-Settle)/365)/Sv_tau1))+Sv_beta3*((1-EXP(-((H13-Settle)/365)/Sv_tau2))/(((H13-Settle)/365)/Sv_tau2)-EXP(-((H13-Settle)/365)/Sv_tau2))) | BR13: =IF(I13="","",Sv_beta0+Sv_beta1*(1-EXP(-((I13-Settle)/365)/Sv_tau1))/(((I13-Settle)/365)/Sv_tau1)+Sv_beta2*((1-EXP(-((I13-Settle)/365)/Sv_tau1))/(((I13-Settle)/365)/Sv_tau1)-EXP(-((I13-Settle)/365)/Sv_tau1))+Sv_beta3*((1-EXP(-((I13-Settle)/365)/Sv_tau2))/(((I13-Settle)/365)/Sv_tau2)-EXP(-((I13-Settle)/365)/Sv_tau2))) | BS13: =IF(J13="","",Sv_beta0+Sv_beta1*(1-EXP(-((J13-Settle)/365)/Sv_tau1))/(((J13-Settle)/365)/Sv_tau1)+Sv_beta2*((1-EXP(-((J13-Settle)/365)/Sv_tau1))/(((J13-Settle)/365)/Sv_tau1)-EXP(-((J13-Settle)/365)/Sv_tau1))+Sv_beta3*((1-EXP(-((J13-Settle)/365)/Sv_tau2))/(((J13-Settle)/365)/Sv_tau2)-EXP(-((J13-Settle)/365)/Sv_tau2))) | BT13: =IF(K13="","",Sv_beta0+Sv_beta1*(1-EXP(-((K13-Settle)/365)/Sv_tau1))/(((K13-Settle)/365)/Sv_tau1)+Sv_beta2*((1-EXP(-((K13-Settle)/365)/Sv_tau1))/(((K13-Settle)/365)/Sv_tau1)-EXP(-((K13-Settle)/365)/Sv_tau1))+Sv_beta3*((1-EXP(-((K13-Settle)/365)/Sv_tau2))/(((K13-Settle)/365)/Sv_tau2)-EXP(-((K13-Settle)/365)/Sv_tau2))) | BU13: =IF(L13="","",Sv_beta0+Sv_beta1*(1-EXP(-((L13-Settle)/365)/Sv_tau1))/(((L13-Settle)/365)/Sv_tau1)+Sv_beta2*((1-EXP(-((L13-Settle)/365)/Sv_tau1))/(((L13-Settle)/365)/Sv_tau1)-EXP(-((L13-Settle)/365)/Sv_tau1))+Sv_beta3*((1-EXP(-((L13-Settle)/365)/Sv_tau2))/(((L13-Settle)/365)/Sv_tau2)-EXP(-((L13-Settle)/365)/Sv_tau2))) | BV13: =IF(M13="","",Sv_beta0+Sv_beta1*(1-EXP(-((M13-Settle)/365)/Sv_tau1))/(((M13-Settle)/365)/Sv_tau1)+Sv_beta2*((1-EXP(-((M13-Settle)/365)/Sv_tau1))/(((M13-Settle)/365)/Sv_tau1)-EXP(-((M13-Settle)/365)/Sv_tau1))+Sv_beta3*((1-EXP(-((M13-Settle)/365)/Sv_tau2))/(((M13-Settle)/365)/Sv_tau2)-EXP(-((M13-Settle)/365)/Sv_tau2))) | ... DV13: =IF(BM13="","",Sv_beta0+Sv_beta1*(1-EXP(-((BM13-Settle)/365)/Sv_tau1))/(((BM13-Settle)/365)/Sv_tau1)+Sv_beta2*((1-EXP(-((BM13-Settle)/365)/Sv_tau1))/(((BM13-Settle)/365)/Sv_tau1)-EXP(-((BM13-Settle)/365)/Sv_tau1))+Sv_beta3*((1-EXP(-((BM13-Settle)/365)/Sv_tau2))/(((BM13-Settle)/365)/Sv_tau2)-EXP(-((BM13-Settle)/365)/Sv_tau2))) | DX13: =IF(F13="",0,($C13/2+IF(1=$D13,100,0))*EXP(-BO13*((F13-Settle)/365))) -> 101.59896 | DY13: =IF(G13="",0,($C13/2+IF(2=$D13,100,0))*EXP(-BP13*((G13-Settle)/365))) -> 0 | DZ13: =IF(H13="",0,($C13/2+IF(3=$D13,100,0))*EXP(-BQ13*((H13-Settle)/365))) -> 0 | EA13: =IF(I13="",0,($C13/2+IF(4=$D13,100,0))*EXP(-BR13*((I13-Settle)/365))) -> 0 | EB13: =IF(J13="",0,($C13/2+IF(5=$D13,100,0))*EXP(-BS13*((J13-Settle)/365))) -> 0 | EC13: =IF(K13="",0,($C13/2+IF(6=$D13,100,0))*EXP(-BT13*((K13-Settle)/365))) -> 0 | ED13: =IF(L13="",0,($C13/2+IF(7=$D13,100,0))*EXP(-BU13*((L13-Settle)/365))) -> 0 | EE13: =IF(M13="",0,($C13/2+IF(8=$D13,100,0))*EXP(-BV13*((M13-Settle)/365))) -> 0 | EF13: =IF(N13="",0,($C13/2+IF(9=$D13,100,0))*EXP(-BW13*((N13-Settle)/365))) -> 0 | EG13: =IF(O13="",0,($C13/2+IF(10=$D13,100,0))*EXP(-BX13*((O13-Settle)/365))) -> 0 | EH13: =IF(P13="",0,($C13/2+IF(11=$D13,100,0))*EXP(-BY13*((P13-Settle)/365))) -> 0 | EI13: =IF(Q13="",0,($C13/2+IF(12=$D13,100,0))*EXP(-BZ13*((Q13-Settle)/365))) -> 0 | EJ13: =IF(R13="",0,($C13/2+IF(13=$D13,100,0))*EXP(-CA13*((R13-Settle)/365))) -> 0 | EK13: =IF(S13="",0,($C13/2+IF(14=$D13,100,0))*EXP(-CB13*((S13-Settle)/365))) -> 0 | EL13: =IF(T13="",0,($C13/2+IF(15=$D13,100,0))*EXP(-CC13*((T13-Settle)/365))) -> 0 | EM13: =IF(U13="",0,($C13/2+IF(16=$D13,100,0))*EXP(-CD13*((U13-Settle)/365))) -> 0 | EN13: =IF(V13="",0,($C13/2+IF(17=$D13,100,0))*EXP(-CE13*((V13-Settle)/365))) -> 0 | EO13: =IF(W13="",0,($C13/2+IF(18=$D13,100,0))*EXP(-CF13*((W13-Settle)/365))) -> 0 | EP13: =IF(X13="",0,($C13/2+IF(19=$D13,100,0))*EXP(-CG13*((X13-Settle)/365))) -> 0 | EQ13: =IF(Y13="",0,($C13/2+IF(20=$D13,100,0))*EXP(-CH13*((Y13-Settle)/365))) -> 0 | ER13: =IF(Z13="",0,($C13/2+IF(21=$D13,100,0))*EXP(-CI13*((Z13-Settle)/365))) -> 0 | ES13: =IF(AA13="",0,($C13/2+IF(22=$D13,100,0))*EXP(-CJ13*((AA13-Settle)/365))) -> 0 | ET13: =IF(AB13="",0,($C13/2+IF(23=$D13,100,0))*EXP(-CK13*((AB13-Settle)/365))) -> 0 | EU13: =IF(AC13="",0,($C13/2+IF(24=$D13,100,0))*EXP(-CL13*((AC13-Settle)/365))) -> 0 | EV13: =IF(AD13="",0,($C13/2+IF(25=$D13,100,0))*EXP(-CM13*((AD13-Settle)/365))) -> 0 | EW13: =IF(AE13="",0,($C13/2+IF(26=$D13,100,0))*EXP(-CN13*((AE13-Settle)/365))) -> 0 | EX13: =IF(AF13="",0,($C13/2+IF(27=$D13,100,0))*EXP(-CO13*((AF13-Settle)/365))) -> 0 | EY13: =IF(AG13="",0,($C13/2+IF(28=$D13,100,0))*EXP(-CP13*((AG13-Settle)/365))) -> 0 | EZ13: =IF(AH13="",0,($C13/2+IF(29=$D13,100,0))*EXP(-CQ13*((AH13-Settle)/365))) -> 0 | FA13: =IF(AI13="",0,($C13/2+IF(30=$D13,100,0))*EXP(-CR13*((AI13-Settle)/365))) -> 0 | FB13: =IF(AJ13="",0,($C13/2+IF(31=$D13,100,0))*EXP(-CS13*((AJ13-Settle)/365))) -> 0 | FC13: =IF(AK13="",0,($C13/2+IF(32=$D13,100,0))*EXP(-CT13*((AK13-Settle)/365))) -> 0 | FD13: =IF(AL13="",0,($C13/2+IF(33=$D13,100,0))*EXP(-CU13*((AL13-Settle)/365))) -> 0 | FE13: =IF(AM13="",0,($C13/2+IF(34=$D13,100,0))*EXP(-CV13*((AM13-Settle)/365))) -> 0 | FF13: =IF(AN13="",0,($C13/2+IF(35=$D13,100,0))*EXP(-CW13*((AN13-Settle)/365))) -> 0 | FG13: =IF(AO13="",0,($C13/2+IF(36=$D13,100,0))*EXP(-CX13*((AO13-Settle)/365))) -> 0 | FH13: =IF(AP13="",0,($C13/2+IF(37=$D13,100,0))*EXP(-CY13*((AP13-Settle)/365))) -> 0 | FI13: =IF(AQ13="",0,($C13/2+IF(38=$D13,100,0))*EXP(-CZ13*((AQ13-Settle)/365))) -> 0 | FJ13: =IF(AR13="",0,($C13/2+IF(39=$D13,100,0))*EXP(-DA13*((AR13-Settle)/365))) -> 0 | FK13: =IF(AS13="",0,($C13/2+IF(40=$D13,100,0))*EXP(-DB13*((AS13-Settle)/365))) -> 0 | FL13: =IF(AT13="",0,($C13/2+IF(41=$D13,100,0))*EXP(-DC13*((AT13-Settle)/365))) -> 0 | FM13: =IF(AU13="",0,($C13/2+IF(42=$D13,100,0))*EXP(-DD13*((AU13-Settle)/365))) -> 0 | FN13: =IF(AV13="",0,($C13/2+IF(43=$D13,100,0))*EXP(-DE13*((AV13-Settle)/365))) -> 0 | FO13: =IF(AW13="",0,($C13/2+IF(44=$D13,100,0))*EXP(-DF13*((AW13-Settle)/365))) -> 0 | FP13: =IF(AX13="",0,($C13/2+IF(45=$D13,100,0))*EXP(-DG13*((AX13-Settle)/365))) -> 0 | FQ13: =IF(AY13="",0,($C13/2+IF(46=$D13,100,0))*EXP(-DH13*((AY13-Settle)/365))) -> 0 | FR13: =IF(AZ13="",0,($C13/2+IF(47=$D13,100,0))*EXP(-DI13*((AZ13-Settle)/365))) -> 0 | FS13: =IF(BA13="",0,($C13/2+IF(48=$D13,100,0))*EXP(-DJ13*((BA13-Settle)/365))) -> 0 | FT13: =IF(BB13="",0,($C13/2+IF(49=$D13,100,0))*EXP(-DK13*((BB13-Settle)/365))) -> 0 | FU13: =IF(BC13="",0,($C13/2+IF(50=$D13,100,0))*EXP(-DL13*((BC13-Settle)/365))) -> 0 | FV13: =IF(BD13="",0,($C13/2+IF(51=$D13,100,0))*EXP(-DM13*((BD13-Settle)/365))) -> 0 | FW13: =IF(BE13="",0,($C13/2+IF(52=$D13,100,0))*EXP(-DN13*((BE13-Settle)/365))) -> 0 | FX13: =IF(BF13="",0,($C13/2+IF(53=$D13,100,0))*EXP(-DO13*((BF13-Settle)/365))) -> 0 | FY13: =IF(BG13="",0,($C13/2+IF(54=$D13,100,0))*EXP(-DP13*((BG13-Settle)/365))) -> 0 | FZ13: =IF(BH13="",0,($C13/2+IF(55=$D13,100,0))*EXP(-DQ13*((BH13-Settle)/365))) -> 0 | GA13: =IF(BI13="",0,($C13/2+IF(56=$D13,100,0))*EXP(-DR13*((BI13-Settle)/365))) -> 0 | GB13: =IF(BJ13="",0,($C13/2+IF(57=$D13,100,0))*EXP(-DS13*((BJ13-Settle)/365))) -> 0 | GC13: =IF(BK13="",0,($C13/2+IF(58=$D13,100,0))*EXP(-DT13*((BK13-Settle)/365))) -> 0 | GD13: =IF(BL13="",0,($C13/2+IF(59=$D13,100,0))*EXP(-DU13*((BL13-Settle)/365))) -> 0 | GE13: =IF(BM13="",0,($C13/2+IF(60=$D13,100,0))*EXP(-DV13*((BM13-Settle)/365))) -> 0
A14: 11 | B14: =Bonds!B14 -> 46341 | C14: =Bonds!C14 -> 6.5 | D14: =Bonds!Q14 -> 1 | E14: =IF(DAY(B14)=DAY(EOMONTH(B14,0)),1,0) -> 0 | F14: =IF(1>$D14,"",IF($E14=1,EOMONTH(EDATE(Bonds!$I14,6*(1-1)),0),EDATE(Bonds!$I14,6*(1-1)))) -> 46341 | G14: =IF(2>$D14,"",IF($E14=1,EOMONTH(EDATE(Bonds!$I14,6*(2-1)),0),EDATE(Bonds!$I14,6*(2-1)))) | H14: =IF(3>$D14,"",IF($E14=1,EOMONTH(EDATE(Bonds!$I14,6*(3-1)),0),EDATE(Bonds!$I14,6*(3-1)))) | I14: =IF(4>$D14,"",IF($E14=1,EOMONTH(EDATE(Bonds!$I14,6*(4-1)),0),EDATE(Bonds!$I14,6*(4-1)))) | J14: =IF(5>$D14,"",IF($E14=1,EOMONTH(EDATE(Bonds!$I14,6*(5-1)),0),EDATE(Bonds!$I14,6*(5-1)))) | K14: =IF(6>$D14,"",IF($E14=1,EOMONTH(EDATE(Bonds!$I14,6*(6-1)),0),EDATE(Bonds!$I14,6*(6-1)))) | L14: =IF(7>$D14,"",IF($E14=1,EOMONTH(EDATE(Bonds!$I14,6*(7-1)),0),EDATE(Bonds!$I14,6*(7-1)))) | M14: =IF(8>$D14,"",IF($E14=1,EOMONTH(EDATE(Bonds!$I14,6*(8-1)),0),EDATE(Bonds!$I14,6*(8-1)))) | N14: =IF(9>$D14,"",IF($E14=1,EOMONTH(EDATE(Bonds!$I14,6*(9-1)),0),EDATE(Bonds!$I14,6*(9-1)))) | O14: =IF(10>$D14,"",IF($E14=1,EOMONTH(EDATE(Bonds!$I14,6*(10-1)),0),EDATE(Bonds!$I14,6*(10-1)))) | P14: =IF(11>$D14,"",IF($E14=1,EOMONTH(EDATE(Bonds!$I14,6*(11-1)),0),EDATE(Bonds!$I14,6*(11-1)))) | Q14: =IF(12>$D14,"",IF($E14=1,EOMONTH(EDATE(Bonds!$I14,6*(12-1)),0),EDATE(Bonds!$I14,6*(12-1)))) | R14: =IF(13>$D14,"",IF($E14=1,EOMONTH(EDATE(Bonds!$I14,6*(13-1)),0),EDATE(Bonds!$I14,6*(13-1)))) | S14: =IF(14>$D14,"",IF($E14=1,EOMONTH(EDATE(Bonds!$I14,6*(14-1)),0),EDATE(Bonds!$I14,6*(14-1)))) | T14: =IF(15>$D14,"",IF($E14=1,EOMONTH(EDATE(Bonds!$I14,6*(15-1)),0),EDATE(Bonds!$I14,6*(15-1)))) | U14: =IF(16>$D14,"",IF($E14=1,EOMONTH(EDATE(Bonds!$I14,6*(16-1)),0),EDATE(Bonds!$I14,6*(16-1)))) | V14: =IF(17>$D14,"",IF($E14=1,EOMONTH(EDATE(Bonds!$I14,6*(17-1)),0),EDATE(Bonds!$I14,6*(17-1)))) | W14: =IF(18>$D14,"",IF($E14=1,EOMONTH(EDATE(Bonds!$I14,6*(18-1)),0),EDATE(Bonds!$I14,6*(18-1)))) | X14: =IF(19>$D14,"",IF($E14=1,EOMONTH(EDATE(Bonds!$I14,6*(19-1)),0),EDATE(Bonds!$I14,6*(19-1)))) | Y14: =IF(20>$D14,"",IF($E14=1,EOMONTH(EDATE(Bonds!$I14,6*(20-1)),0),EDATE(Bonds!$I14,6*(20-1)))) | Z14: =IF(21>$D14,"",IF($E14=1,EOMONTH(EDATE(Bonds!$I14,6*(21-1)),0),EDATE(Bonds!$I14,6*(21-1)))) | AA14: =IF(22>$D14,"",IF($E14=1,EOMONTH(EDATE(Bonds!$I14,6*(22-1)),0),EDATE(Bonds!$I14,6*(22-1)))) | AB14: =IF(23>$D14,"",IF($E14=1,EOMONTH(EDATE(Bonds!$I14,6*(23-1)),0),EDATE(Bonds!$I14,6*(23-1)))) | AC14: =IF(24>$D14,"",IF($E14=1,EOMONTH(EDATE(Bonds!$I14,6*(24-1)),0),EDATE(Bonds!$I14,6*(24-1)))) | AD14: =IF(25>$D14,"",IF($E14=1,EOMONTH(EDATE(Bonds!$I14,6*(25-1)),0),EDATE(Bonds!$I14,6*(25-1)))) | AE14: =IF(26>$D14,"",IF($E14=1,EOMONTH(EDATE(Bonds!$I14,6*(26-1)),0),EDATE(Bonds!$I14,6*(26-1)))) | AF14: =IF(27>$D14,"",IF($E14=1,EOMONTH(EDATE(Bonds!$I14,6*(27-1)),0),EDATE(Bonds!$I14,6*(27-1)))) | AG14: =IF(28>$D14,"",IF($E14=1,EOMONTH(EDATE(Bonds!$I14,6*(28-1)),0),EDATE(Bonds!$I14,6*(28-1)))) | AH14: =IF(29>$D14,"",IF($E14=1,EOMONTH(EDATE(Bonds!$I14,6*(29-1)),0),EDATE(Bonds!$I14,6*(29-1)))) | AI14: =IF(30>$D14,"",IF($E14=1,EOMONTH(EDATE(Bonds!$I14,6*(30-1)),0),EDATE(Bonds!$I14,6*(30-1)))) | AJ14: =IF(31>$D14,"",IF($E14=1,EOMONTH(EDATE(Bonds!$I14,6*(31-1)),0),EDATE(Bonds!$I14,6*(31-1)))) | AK14: =IF(32>$D14,"",IF($E14=1,EOMONTH(EDATE(Bonds!$I14,6*(32-1)),0),EDATE(Bonds!$I14,6*(32-1)))) | AL14: =IF(33>$D14,"",IF($E14=1,EOMONTH(EDATE(Bonds!$I14,6*(33-1)),0),EDATE(Bonds!$I14,6*(33-1)))) | AM14: =IF(34>$D14,"",IF($E14=1,EOMONTH(EDATE(Bonds!$I14,6*(34-1)),0),EDATE(Bonds!$I14,6*(34-1)))) | AN14: =IF(35>$D14,"",IF($E14=1,EOMONTH(EDATE(Bonds!$I14,6*(35-1)),0),EDATE(Bonds!$I14,6*(35-1)))) | AO14: =IF(36>$D14,"",IF($E14=1,EOMONTH(EDATE(Bonds!$I14,6*(36-1)),0),EDATE(Bonds!$I14,6*(36-1)))) | AP14: =IF(37>$D14,"",IF($E14=1,EOMONTH(EDATE(Bonds!$I14,6*(37-1)),0),EDATE(Bonds!$I14,6*(37-1)))) | AQ14: =IF(38>$D14,"",IF($E14=1,EOMONTH(EDATE(Bonds!$I14,6*(38-1)),0),EDATE(Bonds!$I14,6*(38-1)))) | AR14: =IF(39>$D14,"",IF($E14=1,EOMONTH(EDATE(Bonds!$I14,6*(39-1)),0),EDATE(Bonds!$I14,6*(39-1)))) | AS14: =IF(40>$D14,"",IF($E14=1,EOMONTH(EDATE(Bonds!$I14,6*(40-1)),0),EDATE(Bonds!$I14,6*(40-1)))) | AT14: =IF(41>$D14,"",IF($E14=1,EOMONTH(EDATE(Bonds!$I14,6*(41-1)),0),EDATE(Bonds!$I14,6*(41-1)))) | AU14: =IF(42>$D14,"",IF($E14=1,EOMONTH(EDATE(Bonds!$I14,6*(42-1)),0),EDATE(Bonds!$I14,6*(42-1)))) | AV14: =IF(43>$D14,"",IF($E14=1,EOMONTH(EDATE(Bonds!$I14,6*(43-1)),0),EDATE(Bonds!$I14,6*(43-1)))) | AW14: =IF(44>$D14,"",IF($E14=1,EOMONTH(EDATE(Bonds!$I14,6*(44-1)),0),EDATE(Bonds!$I14,6*(44-1)))) | AX14: =IF(45>$D14,"",IF($E14=1,EOMONTH(EDATE(Bonds!$I14,6*(45-1)),0),EDATE(Bonds!$I14,6*(45-1)))) | AY14: =IF(46>$D14,"",IF($E14=1,EOMONTH(EDATE(Bonds!$I14,6*(46-1)),0),EDATE(Bonds!$I14,6*(46-1)))) | AZ14: =IF(47>$D14,"",IF($E14=1,EOMONTH(EDATE(Bonds!$I14,6*(47-1)),0),EDATE(Bonds!$I14,6*(47-1)))) | BA14: =IF(48>$D14,"",IF($E14=1,EOMONTH(EDATE(Bonds!$I14,6*(48-1)),0),EDATE(Bonds!$I14,6*(48-1)))) | BB14: =IF(49>$D14,"",IF($E14=1,EOMONTH(EDATE(Bonds!$I14,6*(49-1)),0),EDATE(Bonds!$I14,6*(49-1)))) | BC14: =IF(50>$D14,"",IF($E14=1,EOMONTH(EDATE(Bonds!$I14,6*(50-1)),0),EDATE(Bonds!$I14,6*(50-1)))) | BD14: =IF(51>$D14,"",IF($E14=1,EOMONTH(EDATE(Bonds!$I14,6*(51-1)),0),EDATE(Bonds!$I14,6*(51-1)))) | BE14: =IF(52>$D14,"",IF($E14=1,EOMONTH(EDATE(Bonds!$I14,6*(52-1)),0),EDATE(Bonds!$I14,6*(52-1)))) | BF14: =IF(53>$D14,"",IF($E14=1,EOMONTH(EDATE(Bonds!$I14,6*(53-1)),0),EDATE(Bonds!$I14,6*(53-1)))) | BG14: =IF(54>$D14,"",IF($E14=1,EOMONTH(EDATE(Bonds!$I14,6*(54-1)),0),EDATE(Bonds!$I14,6*(54-1)))) | BH14: =IF(55>$D14,"",IF($E14=1,EOMONTH(EDATE(Bonds!$I14,6*(55-1)),0),EDATE(Bonds!$I14,6*(55-1)))) | BI14: =IF(56>$D14,"",IF($E14=1,EOMONTH(EDATE(Bonds!$I14,6*(56-1)),0),EDATE(Bonds!$I14,6*(56-1)))) | BJ14: =IF(57>$D14,"",IF($E14=1,EOMONTH(EDATE(Bonds!$I14,6*(57-1)),0),EDATE(Bonds!$I14,6*(57-1)))) | BK14: =IF(58>$D14,"",IF($E14=1,EOMONTH(EDATE(Bonds!$I14,6*(58-1)),0),EDATE(Bonds!$I14,6*(58-1)))) | BL14: =IF(59>$D14,"",IF($E14=1,EOMONTH(EDATE(Bonds!$I14,6*(59-1)),0),EDATE(Bonds!$I14,6*(59-1)))) | BM14: =IF(60>$D14,"",IF($E14=1,EOMONTH(EDATE(Bonds!$I14,6*(60-1)),0),EDATE(Bonds!$I14,6*(60-1)))) | BO14: =IF(F14="","",Sv_beta0+Sv_beta1*(1-EXP(-((F14-Settle)/365)/Sv_tau1))/(((F14-Settle)/365)/Sv_tau1)+Sv_beta2*((1-EXP(-((F14-Settle)/365)/Sv_tau1))/(((F14-Settle)/365)/Sv_tau1)-EXP(-((F14-Settle)/365)/Sv_tau1))+Sv_beta3*((1-EXP(-((F14-Settle)/365)/Sv_tau2))/(((F14-Settle)/365)/Sv_tau2)-EXP(-((F14-Settle)/365)/Sv_tau2))) -> 0.037565785 | BP14: =IF(G14="","",Sv_beta0+Sv_beta1*(1-EXP(-((G14-Settle)/365)/Sv_tau1))/(((G14-Settle)/365)/Sv_tau1)+Sv_beta2*((1-EXP(-((G14-Settle)/365)/Sv_tau1))/(((G14-Settle)/365)/Sv_tau1)-EXP(-((G14-Settle)/365)/Sv_tau1))+Sv_beta3*((1-EXP(-((G14-Settle)/365)/Sv_tau2))/(((G14-Settle)/365)/Sv_tau2)-EXP(-((G14-Settle)/365)/Sv_tau2))) | BQ14: =IF(H14="","",Sv_beta0+Sv_beta1*(1-EXP(-((H14-Settle)/365)/Sv_tau1))/(((H14-Settle)/365)/Sv_tau1)+Sv_beta2*((1-EXP(-((H14-Settle)/365)/Sv_tau1))/(((H14-Settle)/365)/Sv_tau1)-EXP(-((H14-Settle)/365)/Sv_tau1))+Sv_beta3*((1-EXP(-((H14-Settle)/365)/Sv_tau2))/(((H14-Settle)/365)/Sv_tau2)-EXP(-((H14-Settle)/365)/Sv_tau2))) | BR14: =IF(I14="","",Sv_beta0+Sv_beta1*(1-EXP(-((I14-Settle)/365)/Sv_tau1))/(((I14-Settle)/365)/Sv_tau1)+Sv_beta2*((1-EXP(-((I14-Settle)/365)/Sv_tau1))/(((I14-Settle)/365)/Sv_tau1)-EXP(-((I14-Settle)/365)/Sv_tau1))+Sv_beta3*((1-EXP(-((I14-Settle)/365)/Sv_tau2))/(((I14-Settle)/365)/Sv_tau2)-EXP(-((I14-Settle)/365)/Sv_tau2))) | BS14: =IF(J14="","",Sv_beta0+Sv_beta1*(1-EXP(-((J14-Settle)/365)/Sv_tau1))/(((J14-Settle)/365)/Sv_tau1)+Sv_beta2*((1-EXP(-((J14-Settle)/365)/Sv_tau1))/(((J14-Settle)/365)/Sv_tau1)-EXP(-((J14-Settle)/365)/Sv_tau1))+Sv_beta3*((1-EXP(-((J14-Settle)/365)/Sv_tau2))/(((J14-Settle)/365)/Sv_tau2)-EXP(-((J14-Settle)/365)/Sv_tau2))) | BT14: =IF(K14="","",Sv_beta0+Sv_beta1*(1-EXP(-((K14-Settle)/365)/Sv_tau1))/(((K14-Settle)/365)/Sv_tau1)+Sv_beta2*((1-EXP(-((K14-Settle)/365)/Sv_tau1))/(((K14-Settle)/365)/Sv_tau1)-EXP(-((K14-Settle)/365)/Sv_tau1))+Sv_beta3*((1-EXP(-((K14-Settle)/365)/Sv_tau2))/(((K14-Settle)/365)/Sv_tau2)-EXP(-((K14-Settle)/365)/Sv_tau2))) | BU14: =IF(L14="","",Sv_beta0+Sv_beta1*(1-EXP(-((L14-Settle)/365)/Sv_tau1))/(((L14-Settle)/365)/Sv_tau1)+Sv_beta2*((1-EXP(-((L14-Settle)/365)/Sv_tau1))/(((L14-Settle)/365)/Sv_tau1)-EXP(-((L14-Settle)/365)/Sv_tau1))+Sv_beta3*((1-EXP(-((L14-Settle)/365)/Sv_tau2))/(((L14-Settle)/365)/Sv_tau2)-EXP(-((L14-Settle)/365)/Sv_tau2))) | BV14: =IF(M14="","",Sv_beta0+Sv_beta1*(1-EXP(-((M14-Settle)/365)/Sv_tau1))/(((M14-Settle)/365)/Sv_tau1)+Sv_beta2*((1-EXP(-((M14-Settle)/365)/Sv_tau1))/(((M14-Settle)/365)/Sv_tau1)-EXP(-((M14-Settle)/365)/Sv_tau1))+Sv_beta3*((1-EXP(-((M14-Settle)/365)/Sv_tau2))/(((M14-Settle)/365)/Sv_tau2)-EXP(-((M14-Settle)/365)/Sv_tau2))) | ... DV14: =IF(BM14="","",Sv_beta0+Sv_beta1*(1-EXP(-((BM14-Settle)/365)/Sv_tau1))/(((BM14-Settle)/365)/Sv_tau1)+Sv_beta2*((1-EXP(-((BM14-Settle)/365)/Sv_tau1))/(((BM14-Settle)/365)/Sv_tau1)-EXP(-((BM14-Settle)/365)/Sv_tau1))+Sv_beta3*((1-EXP(-((BM14-Settle)/365)/Sv_tau2))/(((BM14-Settle)/365)/Sv_tau2)-EXP(-((BM14-Settle)/365)/Sv_tau2))) | DX14: =IF(F14="",0,($C14/2+IF(1=$D14,100,0))*EXP(-BO14*((F14-Settle)/365))) -> 102.52992 | DY14: =IF(G14="",0,($C14/2+IF(2=$D14,100,0))*EXP(-BP14*((G14-Settle)/365))) -> 0 | DZ14: =IF(H14="",0,($C14/2+IF(3=$D14,100,0))*EXP(-BQ14*((H14-Settle)/365))) -> 0 | EA14: =IF(I14="",0,($C14/2+IF(4=$D14,100,0))*EXP(-BR14*((I14-Settle)/365))) -> 0 | EB14: =IF(J14="",0,($C14/2+IF(5=$D14,100,0))*EXP(-BS14*((J14-Settle)/365))) -> 0 | EC14: =IF(K14="",0,($C14/2+IF(6=$D14,100,0))*EXP(-BT14*((K14-Settle)/365))) -> 0 | ED14: =IF(L14="",0,($C14/2+IF(7=$D14,100,0))*EXP(-BU14*((L14-Settle)/365))) -> 0 | EE14: =IF(M14="",0,($C14/2+IF(8=$D14,100,0))*EXP(-BV14*((M14-Settle)/365))) -> 0 | EF14: =IF(N14="",0,($C14/2+IF(9=$D14,100,0))*EXP(-BW14*((N14-Settle)/365))) -> 0 | EG14: =IF(O14="",0,($C14/2+IF(10=$D14,100,0))*EXP(-BX14*((O14-Settle)/365))) -> 0 | EH14: =IF(P14="",0,($C14/2+IF(11=$D14,100,0))*EXP(-BY14*((P14-Settle)/365))) -> 0 | EI14: =IF(Q14="",0,($C14/2+IF(12=$D14,100,0))*EXP(-BZ14*((Q14-Settle)/365))) -> 0 | EJ14: =IF(R14="",0,($C14/2+IF(13=$D14,100,0))*EXP(-CA14*((R14-Settle)/365))) -> 0 | EK14: =IF(S14="",0,($C14/2+IF(14=$D14,100,0))*EXP(-CB14*((S14-Settle)/365))) -> 0 | EL14: =IF(T14="",0,($C14/2+IF(15=$D14,100,0))*EXP(-CC14*((T14-Settle)/365))) -> 0 | EM14: =IF(U14="",0,($C14/2+IF(16=$D14,100,0))*EXP(-CD14*((U14-Settle)/365))) -> 0 | EN14: =IF(V14="",0,($C14/2+IF(17=$D14,100,0))*EXP(-CE14*((V14-Settle)/365))) -> 0 | EO14: =IF(W14="",0,($C14/2+IF(18=$D14,100,0))*EXP(-CF14*((W14-Settle)/365))) -> 0 | EP14: =IF(X14="",0,($C14/2+IF(19=$D14,100,0))*EXP(-CG14*((X14-Settle)/365))) -> 0 | EQ14: =IF(Y14="",0,($C14/2+IF(20=$D14,100,0))*EXP(-CH14*((Y14-Settle)/365))) -> 0 | ER14: =IF(Z14="",0,($C14/2+IF(21=$D14,100,0))*EXP(-CI14*((Z14-Settle)/365))) -> 0 | ES14: =IF(AA14="",0,($C14/2+IF(22=$D14,100,0))*EXP(-CJ14*((AA14-Settle)/365))) -> 0 | ET14: =IF(AB14="",0,($C14/2+IF(23=$D14,100,0))*EXP(-CK14*((AB14-Settle)/365))) -> 0 | EU14: =IF(AC14="",0,($C14/2+IF(24=$D14,100,0))*EXP(-CL14*((AC14-Settle)/365))) -> 0 | EV14: =IF(AD14="",0,($C14/2+IF(25=$D14,100,0))*EXP(-CM14*((AD14-Settle)/365))) -> 0 | EW14: =IF(AE14="",0,($C14/2+IF(26=$D14,100,0))*EXP(-CN14*((AE14-Settle)/365))) -> 0 | EX14: =IF(AF14="",0,($C14/2+IF(27=$D14,100,0))*EXP(-CO14*((AF14-Settle)/365))) -> 0 | EY14: =IF(AG14="",0,($C14/2+IF(28=$D14,100,0))*EXP(-CP14*((AG14-Settle)/365))) -> 0 | EZ14: =IF(AH14="",0,($C14/2+IF(29=$D14,100,0))*EXP(-CQ14*((AH14-Settle)/365))) -> 0 | FA14: =IF(AI14="",0,($C14/2+IF(30=$D14,100,0))*EXP(-CR14*((AI14-Settle)/365))) -> 0 | FB14: =IF(AJ14="",0,($C14/2+IF(31=$D14,100,0))*EXP(-CS14*((AJ14-Settle)/365))) -> 0 | FC14: =IF(AK14="",0,($C14/2+IF(32=$D14,100,0))*EXP(-CT14*((AK14-Settle)/365))) -> 0 | FD14: =IF(AL14="",0,($C14/2+IF(33=$D14,100,0))*EXP(-CU14*((AL14-Settle)/365))) -> 0 | FE14: =IF(AM14="",0,($C14/2+IF(34=$D14,100,0))*EXP(-CV14*((AM14-Settle)/365))) -> 0 | FF14: =IF(AN14="",0,($C14/2+IF(35=$D14,100,0))*EXP(-CW14*((AN14-Settle)/365))) -> 0 | FG14: =IF(AO14="",0,($C14/2+IF(36=$D14,100,0))*EXP(-CX14*((AO14-Settle)/365))) -> 0 | FH14: =IF(AP14="",0,($C14/2+IF(37=$D14,100,0))*EXP(-CY14*((AP14-Settle)/365))) -> 0 | FI14: =IF(AQ14="",0,($C14/2+IF(38=$D14,100,0))*EXP(-CZ14*((AQ14-Settle)/365))) -> 0 | FJ14: =IF(AR14="",0,($C14/2+IF(39=$D14,100,0))*EXP(-DA14*((AR14-Settle)/365))) -> 0 | FK14: =IF(AS14="",0,($C14/2+IF(40=$D14,100,0))*EXP(-DB14*((AS14-Settle)/365))) -> 0 | FL14: =IF(AT14="",0,($C14/2+IF(41=$D14,100,0))*EXP(-DC14*((AT14-Settle)/365))) -> 0 | FM14: =IF(AU14="",0,($C14/2+IF(42=$D14,100,0))*EXP(-DD14*((AU14-Settle)/365))) -> 0 | FN14: =IF(AV14="",0,($C14/2+IF(43=$D14,100,0))*EXP(-DE14*((AV14-Settle)/365))) -> 0 | FO14: =IF(AW14="",0,($C14/2+IF(44=$D14,100,0))*EXP(-DF14*((AW14-Settle)/365))) -> 0 | FP14: =IF(AX14="",0,($C14/2+IF(45=$D14,100,0))*EXP(-DG14*((AX14-Settle)/365))) -> 0 | FQ14: =IF(AY14="",0,($C14/2+IF(46=$D14,100,0))*EXP(-DH14*((AY14-Settle)/365))) -> 0 | FR14: =IF(AZ14="",0,($C14/2+IF(47=$D14,100,0))*EXP(-DI14*((AZ14-Settle)/365))) -> 0 | FS14: =IF(BA14="",0,($C14/2+IF(48=$D14,100,0))*EXP(-DJ14*((BA14-Settle)/365))) -> 0 | FT14: =IF(BB14="",0,($C14/2+IF(49=$D14,100,0))*EXP(-DK14*((BB14-Settle)/365))) -> 0 | FU14: =IF(BC14="",0,($C14/2+IF(50=$D14,100,0))*EXP(-DL14*((BC14-Settle)/365))) -> 0 | FV14: =IF(BD14="",0,($C14/2+IF(51=$D14,100,0))*EXP(-DM14*((BD14-Settle)/365))) -> 0 | FW14: =IF(BE14="",0,($C14/2+IF(52=$D14,100,0))*EXP(-DN14*((BE14-Settle)/365))) -> 0 | FX14: =IF(BF14="",0,($C14/2+IF(53=$D14,100,0))*EXP(-DO14*((BF14-Settle)/365))) -> 0 | FY14: =IF(BG14="",0,($C14/2+IF(54=$D14,100,0))*EXP(-DP14*((BG14-Settle)/365))) -> 0 | FZ14: =IF(BH14="",0,($C14/2+IF(55=$D14,100,0))*EXP(-DQ14*((BH14-Settle)/365))) -> 0 | GA14: =IF(BI14="",0,($C14/2+IF(56=$D14,100,0))*EXP(-DR14*((BI14-Settle)/365))) -> 0 | GB14: =IF(BJ14="",0,($C14/2+IF(57=$D14,100,0))*EXP(-DS14*((BJ14-Settle)/365))) -> 0 | GC14: =IF(BK14="",0,($C14/2+IF(58=$D14,100,0))*EXP(-DT14*((BK14-Settle)/365))) -> 0 | GD14: =IF(BL14="",0,($C14/2+IF(59=$D14,100,0))*EXP(-DU14*((BL14-Settle)/365))) -> 0 | GE14: =IF(BM14="",0,($C14/2+IF(60=$D14,100,0))*EXP(-DV14*((BM14-Settle)/365))) -> 0
A15: 12 | B15: =Bonds!B15 -> 46356 | C15: =Bonds!C15 -> 1.25 | D15: =Bonds!Q15 -> 1 | E15: =IF(DAY(B15)=DAY(EOMONTH(B15,0)),1,0) -> 1 | F15: =IF(1>$D15,"",IF($E15=1,EOMONTH(EDATE(Bonds!$I15,6*(1-1)),0),EDATE(Bonds!$I15,6*(1-1)))) -> 46356 | G15: =IF(2>$D15,"",IF($E15=1,EOMONTH(EDATE(Bonds!$I15,6*(2-1)),0),EDATE(Bonds!$I15,6*(2-1)))) | H15: =IF(3>$D15,"",IF($E15=1,EOMONTH(EDATE(Bonds!$I15,6*(3-1)),0),EDATE(Bonds!$I15,6*(3-1)))) | I15: =IF(4>$D15,"",IF($E15=1,EOMONTH(EDATE(Bonds!$I15,6*(4-1)),0),EDATE(Bonds!$I15,6*(4-1)))) | J15: =IF(5>$D15,"",IF($E15=1,EOMONTH(EDATE(Bonds!$I15,6*(5-1)),0),EDATE(Bonds!$I15,6*(5-1)))) | K15: =IF(6>$D15,"",IF($E15=1,EOMONTH(EDATE(Bonds!$I15,6*(6-1)),0),EDATE(Bonds!$I15,6*(6-1)))) | L15: =IF(7>$D15,"",IF($E15=1,EOMONTH(EDATE(Bonds!$I15,6*(7-1)),0),EDATE(Bonds!$I15,6*(7-1)))) | M15: =IF(8>$D15,"",IF($E15=1,EOMONTH(EDATE(Bonds!$I15,6*(8-1)),0),EDATE(Bonds!$I15,6*(8-1)))) | N15: =IF(9>$D15,"",IF($E15=1,EOMONTH(EDATE(Bonds!$I15,6*(9-1)),0),EDATE(Bonds!$I15,6*(9-1)))) | O15: =IF(10>$D15,"",IF($E15=1,EOMONTH(EDATE(Bonds!$I15,6*(10-1)),0),EDATE(Bonds!$I15,6*(10-1)))) | P15: =IF(11>$D15,"",IF($E15=1,EOMONTH(EDATE(Bonds!$I15,6*(11-1)),0),EDATE(Bonds!$I15,6*(11-1)))) | Q15: =IF(12>$D15,"",IF($E15=1,EOMONTH(EDATE(Bonds!$I15,6*(12-1)),0),EDATE(Bonds!$I15,6*(12-1)))) | R15: =IF(13>$D15,"",IF($E15=1,EOMONTH(EDATE(Bonds!$I15,6*(13-1)),0),EDATE(Bonds!$I15,6*(13-1)))) | S15: =IF(14>$D15,"",IF($E15=1,EOMONTH(EDATE(Bonds!$I15,6*(14-1)),0),EDATE(Bonds!$I15,6*(14-1)))) | T15: =IF(15>$D15,"",IF($E15=1,EOMONTH(EDATE(Bonds!$I15,6*(15-1)),0),EDATE(Bonds!$I15,6*(15-1)))) | U15: =IF(16>$D15,"",IF($E15=1,EOMONTH(EDATE(Bonds!$I15,6*(16-1)),0),EDATE(Bonds!$I15,6*(16-1)))) | V15: =IF(17>$D15,"",IF($E15=1,EOMONTH(EDATE(Bonds!$I15,6*(17-1)),0),EDATE(Bonds!$I15,6*(17-1)))) | W15: =IF(18>$D15,"",IF($E15=1,EOMONTH(EDATE(Bonds!$I15,6*(18-1)),0),EDATE(Bonds!$I15,6*(18-1)))) | X15: =IF(19>$D15,"",IF($E15=1,EOMONTH(EDATE(Bonds!$I15,6*(19-1)),0),EDATE(Bonds!$I15,6*(19-1)))) | Y15: =IF(20>$D15,"",IF($E15=1,EOMONTH(EDATE(Bonds!$I15,6*(20-1)),0),EDATE(Bonds!$I15,6*(20-1)))) | Z15: =IF(21>$D15,"",IF($E15=1,EOMONTH(EDATE(Bonds!$I15,6*(21-1)),0),EDATE(Bonds!$I15,6*(21-1)))) | AA15: =IF(22>$D15,"",IF($E15=1,EOMONTH(EDATE(Bonds!$I15,6*(22-1)),0),EDATE(Bonds!$I15,6*(22-1)))) | AB15: =IF(23>$D15,"",IF($E15=1,EOMONTH(EDATE(Bonds!$I15,6*(23-1)),0),EDATE(Bonds!$I15,6*(23-1)))) | AC15: =IF(24>$D15,"",IF($E15=1,EOMONTH(EDATE(Bonds!$I15,6*(24-1)),0),EDATE(Bonds!$I15,6*(24-1)))) | AD15: =IF(25>$D15,"",IF($E15=1,EOMONTH(EDATE(Bonds!$I15,6*(25-1)),0),EDATE(Bonds!$I15,6*(25-1)))) | AE15: =IF(26>$D15,"",IF($E15=1,EOMONTH(EDATE(Bonds!$I15,6*(26-1)),0),EDATE(Bonds!$I15,6*(26-1)))) | AF15: =IF(27>$D15,"",IF($E15=1,EOMONTH(EDATE(Bonds!$I15,6*(27-1)),0),EDATE(Bonds!$I15,6*(27-1)))) | AG15: =IF(28>$D15,"",IF($E15=1,EOMONTH(EDATE(Bonds!$I15,6*(28-1)),0),EDATE(Bonds!$I15,6*(28-1)))) | AH15: =IF(29>$D15,"",IF($E15=1,EOMONTH(EDATE(Bonds!$I15,6*(29-1)),0),EDATE(Bonds!$I15,6*(29-1)))) | AI15: =IF(30>$D15,"",IF($E15=1,EOMONTH(EDATE(Bonds!$I15,6*(30-1)),0),EDATE(Bonds!$I15,6*(30-1)))) | AJ15: =IF(31>$D15,"",IF($E15=1,EOMONTH(EDATE(Bonds!$I15,6*(31-1)),0),EDATE(Bonds!$I15,6*(31-1)))) | AK15: =IF(32>$D15,"",IF($E15=1,EOMONTH(EDATE(Bonds!$I15,6*(32-1)),0),EDATE(Bonds!$I15,6*(32-1)))) | AL15: =IF(33>$D15,"",IF($E15=1,EOMONTH(EDATE(Bonds!$I15,6*(33-1)),0),EDATE(Bonds!$I15,6*(33-1)))) | AM15: =IF(34>$D15,"",IF($E15=1,EOMONTH(EDATE(Bonds!$I15,6*(34-1)),0),EDATE(Bonds!$I15,6*(34-1)))) | AN15: =IF(35>$D15,"",IF($E15=1,EOMONTH(EDATE(Bonds!$I15,6*(35-1)),0),EDATE(Bonds!$I15,6*(35-1)))) | AO15: =IF(36>$D15,"",IF($E15=1,EOMONTH(EDATE(Bonds!$I15,6*(36-1)),0),EDATE(Bonds!$I15,6*(36-1)))) | AP15: =IF(37>$D15,"",IF($E15=1,EOMONTH(EDATE(Bonds!$I15,6*(37-1)),0),EDATE(Bonds!$I15,6*(37-1)))) | AQ15: =IF(38>$D15,"",IF($E15=1,EOMONTH(EDATE(Bonds!$I15,6*(38-1)),0),EDATE(Bonds!$I15,6*(38-1)))) | AR15: =IF(39>$D15,"",IF($E15=1,EOMONTH(EDATE(Bonds!$I15,6*(39-1)),0),EDATE(Bonds!$I15,6*(39-1)))) | AS15: =IF(40>$D15,"",IF($E15=1,EOMONTH(EDATE(Bonds!$I15,6*(40-1)),0),EDATE(Bonds!$I15,6*(40-1)))) | AT15: =IF(41>$D15,"",IF($E15=1,EOMONTH(EDATE(Bonds!$I15,6*(41-1)),0),EDATE(Bonds!$I15,6*(41-1)))) | AU15: =IF(42>$D15,"",IF($E15=1,EOMONTH(EDATE(Bonds!$I15,6*(42-1)),0),EDATE(Bonds!$I15,6*(42-1)))) | AV15: =IF(43>$D15,"",IF($E15=1,EOMONTH(EDATE(Bonds!$I15,6*(43-1)),0),EDATE(Bonds!$I15,6*(43-1)))) | AW15: =IF(44>$D15,"",IF($E15=1,EOMONTH(EDATE(Bonds!$I15,6*(44-1)),0),EDATE(Bonds!$I15,6*(44-1)))) | AX15: =IF(45>$D15,"",IF($E15=1,EOMONTH(EDATE(Bonds!$I15,6*(45-1)),0),EDATE(Bonds!$I15,6*(45-1)))) | AY15: =IF(46>$D15,"",IF($E15=1,EOMONTH(EDATE(Bonds!$I15,6*(46-1)),0),EDATE(Bonds!$I15,6*(46-1)))) | AZ15: =IF(47>$D15,"",IF($E15=1,EOMONTH(EDATE(Bonds!$I15,6*(47-1)),0),EDATE(Bonds!$I15,6*(47-1)))) | BA15: =IF(48>$D15,"",IF($E15=1,EOMONTH(EDATE(Bonds!$I15,6*(48-1)),0),EDATE(Bonds!$I15,6*(48-1)))) | BB15: =IF(49>$D15,"",IF($E15=1,EOMONTH(EDATE(Bonds!$I15,6*(49-1)),0),EDATE(Bonds!$I15,6*(49-1)))) | BC15: =IF(50>$D15,"",IF($E15=1,EOMONTH(EDATE(Bonds!$I15,6*(50-1)),0),EDATE(Bonds!$I15,6*(50-1)))) | BD15: =IF(51>$D15,"",IF($E15=1,EOMONTH(EDATE(Bonds!$I15,6*(51-1)),0),EDATE(Bonds!$I15,6*(51-1)))) | BE15: =IF(52>$D15,"",IF($E15=1,EOMONTH(EDATE(Bonds!$I15,6*(52-1)),0),EDATE(Bonds!$I15,6*(52-1)))) | BF15: =IF(53>$D15,"",IF($E15=1,EOMONTH(EDATE(Bonds!$I15,6*(53-1)),0),EDATE(Bonds!$I15,6*(53-1)))) | BG15: =IF(54>$D15,"",IF($E15=1,EOMONTH(EDATE(Bonds!$I15,6*(54-1)),0),EDATE(Bonds!$I15,6*(54-1)))) | BH15: =IF(55>$D15,"",IF($E15=1,EOMONTH(EDATE(Bonds!$I15,6*(55-1)),0),EDATE(Bonds!$I15,6*(55-1)))) | BI15: =IF(56>$D15,"",IF($E15=1,EOMONTH(EDATE(Bonds!$I15,6*(56-1)),0),EDATE(Bonds!$I15,6*(56-1)))) | BJ15: =IF(57>$D15,"",IF($E15=1,EOMONTH(EDATE(Bonds!$I15,6*(57-1)),0),EDATE(Bonds!$I15,6*(57-1)))) | BK15: =IF(58>$D15,"",IF($E15=1,EOMONTH(EDATE(Bonds!$I15,6*(58-1)),0),EDATE(Bonds!$I15,6*(58-1)))) | BL15: =IF(59>$D15,"",IF($E15=1,EOMONTH(EDATE(Bonds!$I15,6*(59-1)),0),EDATE(Bonds!$I15,6*(59-1)))) | BM15: =IF(60>$D15,"",IF($E15=1,EOMONTH(EDATE(Bonds!$I15,6*(60-1)),0),EDATE(Bonds!$I15,6*(60-1)))) | BO15: =IF(F15="","",Sv_beta0+Sv_beta1*(1-EXP(-((F15-Settle)/365)/Sv_tau1))/(((F15-Settle)/365)/Sv_tau1)+Sv_beta2*((1-EXP(-((F15-Settle)/365)/Sv_tau1))/(((F15-Settle)/365)/Sv_tau1)-EXP(-((F15-Settle)/365)/Sv_tau1))+Sv_beta3*((1-EXP(-((F15-Settle)/365)/Sv_tau2))/(((F15-Settle)/365)/Sv_tau2)-EXP(-((F15-Settle)/365)/Sv_tau2))) -> 0.037824451 | BP15: =IF(G15="","",Sv_beta0+Sv_beta1*(1-EXP(-((G15-Settle)/365)/Sv_tau1))/(((G15-Settle)/365)/Sv_tau1)+Sv_beta2*((1-EXP(-((G15-Settle)/365)/Sv_tau1))/(((G15-Settle)/365)/Sv_tau1)-EXP(-((G15-Settle)/365)/Sv_tau1))+Sv_beta3*((1-EXP(-((G15-Settle)/365)/Sv_tau2))/(((G15-Settle)/365)/Sv_tau2)-EXP(-((G15-Settle)/365)/Sv_tau2))) | BQ15: =IF(H15="","",Sv_beta0+Sv_beta1*(1-EXP(-((H15-Settle)/365)/Sv_tau1))/(((H15-Settle)/365)/Sv_tau1)+Sv_beta2*((1-EXP(-((H15-Settle)/365)/Sv_tau1))/(((H15-Settle)/365)/Sv_tau1)-EXP(-((H15-Settle)/365)/Sv_tau1))+Sv_beta3*((1-EXP(-((H15-Settle)/365)/Sv_tau2))/(((H15-Settle)/365)/Sv_tau2)-EXP(-((H15-Settle)/365)/Sv_tau2))) | BR15: =IF(I15="","",Sv_beta0+Sv_beta1*(1-EXP(-((I15-Settle)/365)/Sv_tau1))/(((I15-Settle)/365)/Sv_tau1)+Sv_beta2*((1-EXP(-((I15-Settle)/365)/Sv_tau1))/(((I15-Settle)/365)/Sv_tau1)-EXP(-((I15-Settle)/365)/Sv_tau1))+Sv_beta3*((1-EXP(-((I15-Settle)/365)/Sv_tau2))/(((I15-Settle)/365)/Sv_tau2)-EXP(-((I15-Settle)/365)/Sv_tau2))) | BS15: =IF(J15="","",Sv_beta0+Sv_beta1*(1-EXP(-((J15-Settle)/365)/Sv_tau1))/(((J15-Settle)/365)/Sv_tau1)+Sv_beta2*((1-EXP(-((J15-Settle)/365)/Sv_tau1))/(((J15-Settle)/365)/Sv_tau1)-EXP(-((J15-Settle)/365)/Sv_tau1))+Sv_beta3*((1-EXP(-((J15-Settle)/365)/Sv_tau2))/(((J15-Settle)/365)/Sv_tau2)-EXP(-((J15-Settle)/365)/Sv_tau2))) | BT15: =IF(K15="","",Sv_beta0+Sv_beta1*(1-EXP(-((K15-Settle)/365)/Sv_tau1))/(((K15-Settle)/365)/Sv_tau1)+Sv_beta2*((1-EXP(-((K15-Settle)/365)/Sv_tau1))/(((K15-Settle)/365)/Sv_tau1)-EXP(-((K15-Settle)/365)/Sv_tau1))+Sv_beta3*((1-EXP(-((K15-Settle)/365)/Sv_tau2))/(((K15-Settle)/365)/Sv_tau2)-EXP(-((K15-Settle)/365)/Sv_tau2))) | BU15: =IF(L15="","",Sv_beta0+Sv_beta1*(1-EXP(-((L15-Settle)/365)/Sv_tau1))/(((L15-Settle)/365)/Sv_tau1)+Sv_beta2*((1-EXP(-((L15-Settle)/365)/Sv_tau1))/(((L15-Settle)/365)/Sv_tau1)-EXP(-((L15-Settle)/365)/Sv_tau1))+Sv_beta3*((1-EXP(-((L15-Settle)/365)/Sv_tau2))/(((L15-Settle)/365)/Sv_tau2)-EXP(-((L15-Settle)/365)/Sv_tau2))) | BV15: =IF(M15="","",Sv_beta0+Sv_beta1*(1-EXP(-((M15-Settle)/365)/Sv_tau1))/(((M15-Settle)/365)/Sv_tau1)+Sv_beta2*((1-EXP(-((M15-Settle)/365)/Sv_tau1))/(((M15-Settle)/365)/Sv_tau1)-EXP(-((M15-Settle)/365)/Sv_tau1))+Sv_beta3*((1-EXP(-((M15-Settle)/365)/Sv_tau2))/(((M15-Settle)/365)/Sv_tau2)-EXP(-((M15-Settle)/365)/Sv_tau2))) | ... DV15: =IF(BM15="","",Sv_beta0+Sv_beta1*(1-EXP(-((BM15-Settle)/365)/Sv_tau1))/(((BM15-Settle)/365)/Sv_tau1)+Sv_beta2*((1-EXP(-((BM15-Settle)/365)/Sv_tau1))/(((BM15-Settle)/365)/Sv_tau1)-EXP(-((BM15-Settle)/365)/Sv_tau1))+Sv_beta3*((1-EXP(-((BM15-Settle)/365)/Sv_tau2))/(((BM15-Settle)/365)/Sv_tau2)-EXP(-((BM15-Settle)/365)/Sv_tau2))) | DX15: =IF(F15="",0,($C15/2+IF(1=$D15,100,0))*EXP(-BO15*((F15-Settle)/365))) -> 99.763218 | DY15: =IF(G15="",0,($C15/2+IF(2=$D15,100,0))*EXP(-BP15*((G15-Settle)/365))) -> 0 | DZ15: =IF(H15="",0,($C15/2+IF(3=$D15,100,0))*EXP(-BQ15*((H15-Settle)/365))) -> 0 | EA15: =IF(I15="",0,($C15/2+IF(4=$D15,100,0))*EXP(-BR15*((I15-Settle)/365))) -> 0 | EB15: =IF(J15="",0,($C15/2+IF(5=$D15,100,0))*EXP(-BS15*((J15-Settle)/365))) -> 0 | EC15: =IF(K15="",0,($C15/2+IF(6=$D15,100,0))*EXP(-BT15*((K15-Settle)/365))) -> 0 | ED15: =IF(L15="",0,($C15/2+IF(7=$D15,100,0))*EXP(-BU15*((L15-Settle)/365))) -> 0 | EE15: =IF(M15="",0,($C15/2+IF(8=$D15,100,0))*EXP(-BV15*((M15-Settle)/365))) -> 0 | EF15: =IF(N15="",0,($C15/2+IF(9=$D15,100,0))*EXP(-BW15*((N15-Settle)/365))) -> 0 | EG15: =IF(O15="",0,($C15/2+IF(10=$D15,100,0))*EXP(-BX15*((O15-Settle)/365))) -> 0 | EH15: =IF(P15="",0,($C15/2+IF(11=$D15,100,0))*EXP(-BY15*((P15-Settle)/365))) -> 0 | EI15: =IF(Q15="",0,($C15/2+IF(12=$D15,100,0))*EXP(-BZ15*((Q15-Settle)/365))) -> 0 | EJ15: =IF(R15="",0,($C15/2+IF(13=$D15,100,0))*EXP(-CA15*((R15-Settle)/365))) -> 0 | EK15: =IF(S15="",0,($C15/2+IF(14=$D15,100,0))*EXP(-CB15*((S15-Settle)/365))) -> 0 | EL15: =IF(T15="",0,($C15/2+IF(15=$D15,100,0))*EXP(-CC15*((T15-Settle)/365))) -> 0 | EM15: =IF(U15="",0,($C15/2+IF(16=$D15,100,0))*EXP(-CD15*((U15-Settle)/365))) -> 0 | EN15: =IF(V15="",0,($C15/2+IF(17=$D15,100,0))*EXP(-CE15*((V15-Settle)/365))) -> 0 | EO15: =IF(W15="",0,($C15/2+IF(18=$D15,100,0))*EXP(-CF15*((W15-Settle)/365))) -> 0 | EP15: =IF(X15="",0,($C15/2+IF(19=$D15,100,0))*EXP(-CG15*((X15-Settle)/365))) -> 0 | EQ15: =IF(Y15="",0,($C15/2+IF(20=$D15,100,0))*EXP(-CH15*((Y15-Settle)/365))) -> 0 | ER15: =IF(Z15="",0,($C15/2+IF(21=$D15,100,0))*EXP(-CI15*((Z15-Settle)/365))) -> 0 | ES15: =IF(AA15="",0,($C15/2+IF(22=$D15,100,0))*EXP(-CJ15*((AA15-Settle)/365))) -> 0 | ET15: =IF(AB15="",0,($C15/2+IF(23=$D15,100,0))*EXP(-CK15*((AB15-Settle)/365))) -> 0 | EU15: =IF(AC15="",0,($C15/2+IF(24=$D15,100,0))*EXP(-CL15*((AC15-Settle)/365))) -> 0 | EV15: =IF(AD15="",0,($C15/2+IF(25=$D15,100,0))*EXP(-CM15*((AD15-Settle)/365))) -> 0 | EW15: =IF(AE15="",0,($C15/2+IF(26=$D15,100,0))*EXP(-CN15*((AE15-Settle)/365))) -> 0 | EX15: =IF(AF15="",0,($C15/2+IF(27=$D15,100,0))*EXP(-CO15*((AF15-Settle)/365))) -> 0 | EY15: =IF(AG15="",0,($C15/2+IF(28=$D15,100,0))*EXP(-CP15*((AG15-Settle)/365))) -> 0 | EZ15: =IF(AH15="",0,($C15/2+IF(29=$D15,100,0))*EXP(-CQ15*((AH15-Settle)/365))) -> 0 | FA15: =IF(AI15="",0,($C15/2+IF(30=$D15,100,0))*EXP(-CR15*((AI15-Settle)/365))) -> 0 | FB15: =IF(AJ15="",0,($C15/2+IF(31=$D15,100,0))*EXP(-CS15*((AJ15-Settle)/365))) -> 0 | FC15: =IF(AK15="",0,($C15/2+IF(32=$D15,100,0))*EXP(-CT15*((AK15-Settle)/365))) -> 0 | FD15: =IF(AL15="",0,($C15/2+IF(33=$D15,100,0))*EXP(-CU15*((AL15-Settle)/365))) -> 0 | FE15: =IF(AM15="",0,($C15/2+IF(34=$D15,100,0))*EXP(-CV15*((AM15-Settle)/365))) -> 0 | FF15: =IF(AN15="",0,($C15/2+IF(35=$D15,100,0))*EXP(-CW15*((AN15-Settle)/365))) -> 0 | FG15: =IF(AO15="",0,($C15/2+IF(36=$D15,100,0))*EXP(-CX15*((AO15-Settle)/365))) -> 0 | FH15: =IF(AP15="",0,($C15/2+IF(37=$D15,100,0))*EXP(-CY15*((AP15-Settle)/365))) -> 0 | FI15: =IF(AQ15="",0,($C15/2+IF(38=$D15,100,0))*EXP(-CZ15*((AQ15-Settle)/365))) -> 0 | FJ15: =IF(AR15="",0,($C15/2+IF(39=$D15,100,0))*EXP(-DA15*((AR15-Settle)/365))) -> 0 | FK15: =IF(AS15="",0,($C15/2+IF(40=$D15,100,0))*EXP(-DB15*((AS15-Settle)/365))) -> 0 | FL15: =IF(AT15="",0,($C15/2+IF(41=$D15,100,0))*EXP(-DC15*((AT15-Settle)/365))) -> 0 | FM15: =IF(AU15="",0,($C15/2+IF(42=$D15,100,0))*EXP(-DD15*((AU15-Settle)/365))) -> 0 | FN15: =IF(AV15="",0,($C15/2+IF(43=$D15,100,0))*EXP(-DE15*((AV15-Settle)/365))) -> 0 | FO15: =IF(AW15="",0,($C15/2+IF(44=$D15,100,0))*EXP(-DF15*((AW15-Settle)/365))) -> 0 | FP15: =IF(AX15="",0,($C15/2+IF(45=$D15,100,0))*EXP(-DG15*((AX15-Settle)/365))) -> 0 | FQ15: =IF(AY15="",0,($C15/2+IF(46=$D15,100,0))*EXP(-DH15*((AY15-Settle)/365))) -> 0 | FR15: =IF(AZ15="",0,($C15/2+IF(47=$D15,100,0))*EXP(-DI15*((AZ15-Settle)/365))) -> 0 | FS15: =IF(BA15="",0,($C15/2+IF(48=$D15,100,0))*EXP(-DJ15*((BA15-Settle)/365))) -> 0 | FT15: =IF(BB15="",0,($C15/2+IF(49=$D15,100,0))*EXP(-DK15*((BB15-Settle)/365))) -> 0 | FU15: =IF(BC15="",0,($C15/2+IF(50=$D15,100,0))*EXP(-DL15*((BC15-Settle)/365))) -> 0 | FV15: =IF(BD15="",0,($C15/2+IF(51=$D15,100,0))*EXP(-DM15*((BD15-Settle)/365))) -> 0 | FW15: =IF(BE15="",0,($C15/2+IF(52=$D15,100,0))*EXP(-DN15*((BE15-Settle)/365))) -> 0 | FX15: =IF(BF15="",0,($C15/2+IF(53=$D15,100,0))*EXP(-DO15*((BF15-Settle)/365))) -> 0 | FY15: =IF(BG15="",0,($C15/2+IF(54=$D15,100,0))*EXP(-DP15*((BG15-Settle)/365))) -> 0 | FZ15: =IF(BH15="",0,($C15/2+IF(55=$D15,100,0))*EXP(-DQ15*((BH15-Settle)/365))) -> 0 | GA15: =IF(BI15="",0,($C15/2+IF(56=$D15,100,0))*EXP(-DR15*((BI15-Settle)/365))) -> 0 | GB15: =IF(BJ15="",0,($C15/2+IF(57=$D15,100,0))*EXP(-DS15*((BJ15-Settle)/365))) -> 0 | GC15: =IF(BK15="",0,($C15/2+IF(58=$D15,100,0))*EXP(-DT15*((BK15-Settle)/365))) -> 0 | GD15: =IF(BL15="",0,($C15/2+IF(59=$D15,100,0))*EXP(-DU15*((BL15-Settle)/365))) -> 0 | GE15: =IF(BM15="",0,($C15/2+IF(60=$D15,100,0))*EXP(-DV15*((BM15-Settle)/365))) -> 0
